Workbook

Sheet DASHBOARD
A1: MANAGEMENT DASHBOARD
A2: Live KPIs — updates automatically as you enter data. All values GBP (£). Reporting date is set on the SETTINGS sheet.
B4: STOCK | E4: SALES | H4: PROFIT & TRADING | K4: ⚠ WARNINGS / EXCEPTIONS
B5: Total stock items | C5: =COUNTA('INVENTORY MASTER'!$A$4:$A$63) -> 6 | E5: Today's sales | F5: =SUMIFS(SALES!$K$4:$K$63,SALES!$B$4:$B$63,SETTINGS!$W$6) -> 0 | H5: Gross profit this month | I5: =SUMIFS(SALES!$N$4:$N$63,SALES!$B$4:$B$63,">="&SETTINGS!$W$7,SALES!$B$4:$B$63,"<="&SETTINGS!$W$8) -> 0 | K5: Stock below minimum price | L5: =SUMPRODUCT(('INVENTORY MASTER'!$AO$4:$AO$63<>"")*('INVENTORY MASTER'!$AN$4:$AN$63<>"")*('INVENTORY MASTER'!$AO$4:$AO$63<'INVENTORY MASTER'!$AN$4:$AN$63)) -> 0
B6: Watches | C6: =COUNTIF('INVENTORY MASTER'!$E$4:$E$63,"Watch") -> 3 | E6: This week's sales | F6: =SUMIFS(SALES!$K$4:$K$63,SALES!$B$4:$B$63,">="&SETTINGS!$W$11,SALES!$B$4:$B$63,"<="&SETTINGS!$W$6) -> 0 | H6: Gross profit this year | I6: =SUMIFS(SALES!$N$4:$N$63,SALES!$B$4:$B$63,">="&SETTINGS!$W$9,SALES!$B$4:$B$63,"<="&SETTINGS!$W$10) -> 2100 | K6: Missing / lost stock | L6: =COUNTIF('INVENTORY MASTER'!$AS$4:$AS$63,"Lost/Missing") -> 0
B7: Jewellery items | C7: =COUNTIF('INVENTORY MASTER'!$E$4:$E$63,"Ring")+COUNTIF('INVENTORY MASTER'!$E$4:$E$63,"Bracelet")+COUNTIF('INVENTORY MASTER'!$E$4:$E$63,"Necklace")+COUNTIF('INVENTORY MASTER'!$E$4:$E$63,"Pendant")+COUNTIF('INVENTORY MASTER'!$E$4:$E$63,"Earrings")+COUNTIF('INVENTORY MASTER'!$E$4:$E$63,"Chain")+COUNTIF('INVENTORY MASTER'!$E$4:$E$63,"Gold")+COUNTIF('INVENTORY MASTER'!$E$4:$E$63,"Diamond Jewellery") -> 3 | E7: Sales this month | F7: =SUMIFS(SALES!$K$4:$K$63,SALES!$B$4:$B$63,">="&SETTINGS!$W$7,SALES!$B$4:$B$63,"<="&SETTINGS!$W$8) -> 0 | H7: Avg gross profit / sale | I7: =IFERROR(SUMIFS(SALES!$N$4:$N$63,SALES!$B$4:$B$63,">="&SETTINGS!$W$9,SALES!$B$4:$B$63,"<="&SETTINGS!$W$10)/COUNTIFS(SALES!$B$4:$B$63,">="&SETTINGS!$W$9,SALES!$B$4:$B$63,"<="&SETTINGS!$W$10),0) -> 2100 | K7: Overdue stock movements | L7: =SUMPRODUCT(('STOCK MOVEMENT'!$K$4:$K$63<>"")*('STOCK MOVEMENT'!$K$4:$K$63<SETTINGS!$W$6)*('STOCK MOVEMENT'!$M$4:$M$63<>"Yes")*('STOCK MOVEMENT'!$L$4:$L$63="")) -> 1
B8: Available items | C8: =COUNTIF('INVENTORY MASTER'!$AS$4:$AS$63,"Available") -> 4 | E8: Sales this year | F8: =SUMIFS(SALES!$K$4:$K$63,SALES!$B$4:$B$63,">="&SETTINGS!$W$9,SALES!$B$4:$B$63,"<="&SETTINGS!$W$10) -> 10200 | H8: Avg gross margin % | I8: =IFERROR(SUMIFS(SALES!$N$4:$N$63,SALES!$B$4:$B$63,">="&SETTINGS!$W$9,SALES!$B$4:$B$63,"<="&SETTINGS!$W$10)/SUMIFS(SALES!$K$4:$K$63,SALES!$B$4:$B$63,">="&SETTINGS!$W$9,SALES!$B$4:$B$63,"<="&SETTINGS!$W$10),0) -> 0.20588235 | K8: Negative-margin sales | L8: =COUNTIF(SALES!$N$4:$N$63,"<0") -> 0
B9: Reserved items | C9: =COUNTIF('INVENTORY MASTER'!$AS$4:$AS$63,"Reserved") -> 0 | E9: Number of sales (year) | F9: =COUNTIFS(SALES!$B$4:$B$63,">="&SETTINGS!$W$9,SALES!$B$4:$B$63,"<="&SETTINGS!$W$10) -> 1 | H9: Operating expenses this month | I9: =SUMIFS(EXPENSES!$I$4:$I$83,EXPENSES!$B$4:$B$83,">="&SETTINGS!$W$7,EXPENSES!$B$4:$B$83,"<="&SETTINGS!$W$8) -> 0 | K9: Missing serial (watches) | L9: =SUMPRODUCT(('INVENTORY MASTER'!$A$4:$A$63<>"")*('INVENTORY MASTER'!$E$4:$E$63="Watch")*('INVENTORY MASTER'!$J$4:$J$63="")) -> 0
B10: Sold items | C10: =COUNTIF('INVENTORY MASTER'!$AS$4:$AS$63,"Sold") -> 1 | H10: Operating expenses this year | I10: =SUMIFS(EXPENSES!$I$4:$I$83,EXPENSES!$B$4:$B$83,">="&SETTINGS!$W$9,EXPENSES!$B$4:$B$83,"<="&SETTINGS!$W$10) -> 8720 | K10: Duplicate serial numbers | L10: =SUMPRODUCT(('INVENTORY MASTER'!$J$4:$J$63<>"")*(COUNTIF('INVENTORY MASTER'!$J$4:$J$63,'INVENTORY MASTER'!$J$4:$J$63&"")>1)) -> 0
B11: Items outside premises | C11: =SUMPRODUCT(('INVENTORY MASTER'!$A$4:$A$63<>"")*('INVENTORY MASTER'!$AS$4:$AS$63<>"Sold")*('INVENTORY MASTER'!$AR$4:$AR$63<>"Shop Display")*('INVENTORY MASTER'!$AR$4:$AR$63<>"Shop Safe")*('INVENTORY MASTER'!$AR$4:$AR$63<>"Office")) -> 1 | E11: PARTNERS | H11: Net trading result (year) | I11: =I6-I10 -> -6620 | K11: Missing purchase price | L11: =SUMPRODUCT(('INVENTORY MASTER'!$A$4:$A$63<>"")*('INVENTORY MASTER'!$AE$4:$AE$63="")) -> 0
B12: Missing items | C12: =COUNTIF('INVENTORY MASTER'!$AS$4:$AS$63,"Lost/Missing") -> 0 | E12: Partner 1 outstanding | F12: ='PARTNER SUMMARY'!$B$16 -> 18100 | H12: Potential GP on inventory | I12: =C15 -> 6410 | K12: Missing supplier details | L12: =SUMPRODUCT(('INVENTORY MASTER'!$A$4:$A$63<>"")*('INVENTORY MASTER'!$AA$4:$AA$63="")) -> 0
B13: Total stock at cost | C13: =SUMIF('INVENTORY MASTER'!$AS$4:$AS$63,"<>Sold",'INVENTORY MASTER'!$AI$4:$AI$63)-SUMIF('INVENTORY MASTER'!$AS$4:$AS$63,"Written Off",'INVENTORY MASTER'!$AI$4:$AI$63) -> 14690 | E13: Partner 2 outstanding | F13: ='PARTNER SUMMARY'!$C$16 -> 3550 | H13: Stock below min price (count) | I13: =SUMPRODUCT(('INVENTORY MASTER'!$AO$4:$AO$63<>"")*('INVENTORY MASTER'!$AN$4:$AN$63<>"")*('INVENTORY MASTER'!$AO$4:$AO$63<'INVENTORY MASTER'!$AN$4:$AN$63)) -> 0 | K13: Items without photos/docs | L13: =SUMPRODUCT(('INVENTORY MASTER'!$A$4:$A$63<>"")*('INVENTORY MASTER'!$AS$4:$AS$63<>"Sold")*('INVENTORY MASTER'!$BA$4:$BA$63="")) -> 1
B14: Expected retail value | C14: =SUMIF('INVENTORY MASTER'!$AS$4:$AS$63,"<>Sold",'INVENTORY MASTER'!$AM$4:$AM$63)-SUMIF('INVENTORY MASTER'!$AS$4:$AS$63,"Written Off",'INVENTORY MASTER'!$AM$4:$AM$63) -> 21100 | E14: Partner 3 outstanding | F14: ='PARTNER SUMMARY'!$D$16 -> 7790 | H14: Discounts > 20%% (count) | I14: =COUNTIF(SALES!$M$4:$M$63,">0.2") -> 0 | K14: Sold but still 'Available' | L14: =SUMPRODUCT(('INVENTORY MASTER'!$AT$4:$AT$63<>"")*('INVENTORY MASTER'!$AS$4:$AS$63="Available")) -> 0
B15: Potential stock profit | C15: =C14-C13 -> 6410 | E15: Total partner funding outstanding | F15: ='PARTNER SUMMARY'!$E$16 -> 29440 | H15: Negative-margin sales (count) | I15: =COUNTIF(SALES!$N$4:$N$63,"<0") -> 0 | K15: Unreconciled partner txns | L15: =COUNTIF('PARTNER CONTRIBUTIONS'!$M$4:$M$63,">0") -> 5
B19: MONTHLY PERFORMANCE (reporting year) | F19: BY CATEGORY | J19: BY EMPLOYEE | M19: EXPENSES BY CATEGORY
B20: Month | C20: Sales | D20: Gross Profit | F20: Category | G20: Sales | H20: Stock Value | J20: Employee | K20: Sales | M20: Category | N20: Amount
B21: Jan | C21: =SUMIFS(SALES!$K$4:$K$63,SALES!$B$4:$B$63,">="&DATE(YEAR(SETTINGS!$W$9),1,1),SALES!$B$4:$B$63,"<="&EOMONTH(DATE(YEAR(SETTINGS!$W$9),1,1),0)) -> 0 | D21: =SUMIFS(SALES!$N$4:$N$63,SALES!$B$4:$B$63,">="&DATE(YEAR(SETTINGS!$W$9),1,1),SALES!$B$4:$B$63,"<="&EOMONTH(DATE(YEAR(SETTINGS!$W$9),1,1),0)) -> 0 | F21: Watch | G21: =SUMIFS(SALES!$K$4:$K$63,SALES!$E$4:$E$63,"Watch") -> 10200 | H21: =SUMIFS('INVENTORY MASTER'!$AI$4:$AI$63,'INVENTORY MASTER'!$E$4:$E$63,"Watch")-SUMIFS('INVENTORY MASTER'!$AI$4:$AI$63,'INVENTORY MASTER'!$E$4:$E$63,"Watch",'INVENTORY MASTER'!$AS$4:$AS$63,"Sold")-SUMIFS('INVENTORY MASTER'!$AI$4:$AI$63,'INVENTORY MASTER'!$E$4:$E$63,"Watch",'INVENTORY MASTER'!$AS$4:$AS$63,"Written Off") -> 7990 | J21: Sarah Hughes | K21: =SUMIFS(SALES!$K$4:$K$63,SALES!$F$4:$F$63,"Sarah Hughes") -> 10200 | M21: Rent | N21: =SUMIFS(EXPENSES!$I$4:$I$83,EXPENSES!$D$4:$D$83,"Rent") -> 3000
B22: Feb | C22: =SUMIFS(SALES!$K$4:$K$63,SALES!$B$4:$B$63,">="&DATE(YEAR(SETTINGS!$W$9),2,1),SALES!$B$4:$B$63,"<="&EOMONTH(DATE(YEAR(SETTINGS!$W$9),2,1),0)) -> 10200 | D22: =SUMIFS(SALES!$N$4:$N$63,SALES!$B$4:$B$63,">="&DATE(YEAR(SETTINGS!$W$9),2,1),SALES!$B$4:$B$63,"<="&EOMONTH(DATE(YEAR(SETTINGS!$W$9),2,1),0)) -> 2100 | F22: Ring | G22: =SUMIFS(SALES!$K$4:$K$63,SALES!$E$4:$E$63,"Ring") -> 0 | H22: =SUMIFS('INVENTORY MASTER'!$AI$4:$AI$63,'INVENTORY MASTER'!$E$4:$E$63,"Ring")-SUMIFS('INVENTORY MASTER'!$AI$4:$AI$63,'INVENTORY MASTER'!$E$4:$E$63,"Ring",'INVENTORY MASTER'!$AS$4:$AS$63,"Sold")-SUMIFS('INVENTORY MASTER'!$AI$4:$AI$63,'INVENTORY MASTER'!$E$4:$E$63,"Ring",'INVENTORY MASTER'!$AS$4:$AS$63,"Written Off") -> 0 | J22: James Patel | K22: =SUMIFS(SALES!$K$4:$K$63,SALES!$F$4:$F$63,"James Patel") -> 0 | M22: Refurbishment | N22: =SUMIFS(EXPENSES!$I$4:$I$83,EXPENSES!$D$4:$D$83,"Refurbishment") -> 5000
B23: Mar | C23: =SUMIFS(SALES!$K$4:$K$63,SALES!$B$4:$B$63,">="&DATE(YEAR(SETTINGS!$W$9),3,1),SALES!$B$4:$B$63,"<="&EOMONTH(DATE(YEAR(SETTINGS!$W$9),3,1),0)) -> 0 | D23: =SUMIFS(SALES!$N$4:$N$63,SALES!$B$4:$B$63,">="&DATE(YEAR(SETTINGS!$W$9),3,1),SALES!$B$4:$B$63,"<="&EOMONTH(DATE(YEAR(SETTINGS!$W$9),3,1),0)) -> 0 | F23: Bracelet | G23: =SUMIFS(SALES!$K$4:$K$63,SALES!$E$4:$E$63,"Bracelet") -> 0 | H23: =SUMIFS('INVENTORY MASTER'!$AI$4:$AI$63,'INVENTORY MASTER'!$E$4:$E$63,"Bracelet")-SUMIFS('INVENTORY MASTER'!$AI$4:$AI$63,'INVENTORY MASTER'!$E$4:$E$63,"Bracelet",'INVENTORY MASTER'!$AS$4:$AS$63,"Sold")-SUMIFS('INVENTORY MASTER'!$AI$4:$AI$63,'INVENTORY MASTER'!$E$4:$E$63,"Bracelet",'INVENTORY MASTER'!$AS$4:$AS$63,"Written Off") -> 1650 | J23: Olivia Brown | K23: =SUMIFS(SALES!$K$4:$K$63,SALES!$F$4:$F$63,"Olivia Brown") -> 0 | M23: Insurance | N23: =SUMIFS(EXPENSES!$I$4:$I$83,EXPENSES!$D$4:$D$83,"Insurance") -> 0
B24: Apr | C24: =SUMIFS(SALES!$K$4:$K$63,SALES!$B$4:$B$63,">="&DATE(YEAR(SETTINGS!$W$9),4,1),SALES!$B$4:$B$63,"<="&EOMONTH(DATE(YEAR(SETTINGS!$W$9),4,1),0)) -> 0 | D24: =SUMIFS(SALES!$N$4:$N$63,SALES!$B$4:$B$63,">="&DATE(YEAR(SETTINGS!$W$9),4,1),SALES!$B$4:$B$63,"<="&EOMONTH(DATE(YEAR(SETTINGS!$W$9),4,1),0)) -> 0 | F24: Necklace | G24: =SUMIFS(SALES!$K$4:$K$63,SALES!$E$4:$E$63,"Necklace") -> 0 | H24: =SUMIFS('INVENTORY MASTER'!$AI$4:$AI$63,'INVENTORY MASTER'!$E$4:$E$63,"Necklace")-SUMIFS('INVENTORY MASTER'!$AI$4:$AI$63,'INVENTORY MASTER'!$E$4:$E$63,"Necklace",'INVENTORY MASTER'!$AS$4:$AS$63,"Sold")-SUMIFS('INVENTORY MASTER'!$AI$4:$AI$63,'INVENTORY MASTER'!$E$4:$E$63,"Necklace",'INVENTORY MASTER'!$AS$4:$AS$63,"Written Off") -> 0 | J24: David Khan | K24: =SUMIFS(SALES!$K$4:$K$63,SALES!$F$4:$F$63,"David Khan") -> 0 | M24: Staff Wages | N24: =SUMIFS(EXPENSES!$I$4:$I$83,EXPENSES!$D$4:$D$83,"Staff Wages") -> 0
B25: May | C25: =SUMIFS(SALES!$K$4:$K$63,SALES!$B$4:$B$63,">="&DATE(YEAR(SETTINGS!$W$9),5,1),SALES!$B$4:$B$63,"<="&EOMONTH(DATE(YEAR(SETTINGS!$W$9),5,1),0)) -> 0 | D25: =SUMIFS(SALES!$N$4:$N$63,SALES!$B$4:$B$63,">="&DATE(YEAR(SETTINGS!$W$9),5,1),SALES!$B$4:$B$63,"<="&EOMONTH(DATE(YEAR(SETTINGS!$W$9),5,1),0)) -> 0 | F25: Pendant | G25: =SUMIFS(SALES!$K$4:$K$63,SALES!$E$4:$E$63,"Pendant") -> 0 | H25: =SUMIFS('INVENTORY MASTER'!$AI$4:$AI$63,'INVENTORY MASTER'!$E$4:$E$63,"Pendant")-SUMIFS('INVENTORY MASTER'!$AI$4:$AI$63,'INVENTORY MASTER'!$E$4:$E$63,"Pendant",'INVENTORY MASTER'!$AS$4:$AS$63,"Sold")-SUMIFS('INVENTORY MASTER'!$AI$4:$AI$63,'INVENTORY MASTER'!$E$4:$E$63,"Pendant",'INVENTORY MASTER'!$AS$4:$AS$63,"Written Off") -> 0 | M25: Marketing | N25: =SUMIFS(EXPENSES!$I$4:$I$83,EXPENSES!$D$4:$D$83,"Marketing") -> 0
B26: Jun | C26: =SUMIFS(SALES!$K$4:$K$63,SALES!$B$4:$B$63,">="&DATE(YEAR(SETTINGS!$W$9),6,1),SALES!$B$4:$B$63,"<="&EOMONTH(DATE(YEAR(SETTINGS!$W$9),6,1),0)) -> 0 | D26: =SUMIFS(SALES!$N$4:$N$63,SALES!$B$4:$B$63,">="&DATE(YEAR(SETTINGS!$W$9),6,1),SALES!$B$4:$B$63,"<="&EOMONTH(DATE(YEAR(SETTINGS!$W$9),6,1),0)) -> 0 | F26: Earrings | G26: =SUMIFS(SALES!$K$4:$K$63,SALES!$E$4:$E$63,"Earrings") -> 0 | H26: =SUMIFS('INVENTORY MASTER'!$AI$4:$AI$63,'INVENTORY MASTER'!$E$4:$E$63,"Earrings")-SUMIFS('INVENTORY MASTER'!$AI$4:$AI$63,'INVENTORY MASTER'!$E$4:$E$63,"Earrings",'INVENTORY MASTER'!$AS$4:$AS$63,"Sold")-SUMIFS('INVENTORY MASTER'!$AI$4:$AI$63,'INVENTORY MASTER'!$E$4:$E$63,"Earrings",'INVENTORY MASTER'!$AS$4:$AS$63,"Written Off") -> 0 | M26: Stock Insurance | N26: =SUMIFS(EXPENSES!$I$4:$I$83,EXPENSES!$D$4:$D$83,"Stock Insurance") -> 720
B27: Jul | C27: =SUMIFS(SALES!$K$4:$K$63,SALES!$B$4:$B$63,">="&DATE(YEAR(SETTINGS!$W$9),7,1),SALES!$B$4:$B$63,"<="&EOMONTH(DATE(YEAR(SETTINGS!$W$9),7,1),0)) -> 0 | D27: =SUMIFS(SALES!$N$4:$N$63,SALES!$B$4:$B$63,">="&DATE(YEAR(SETTINGS!$W$9),7,1),SALES!$B$4:$B$63,"<="&EOMONTH(DATE(YEAR(SETTINGS!$W$9),7,1),0)) -> 0 | F27: Chain | G27: =SUMIFS(SALES!$K$4:$K$63,SALES!$E$4:$E$63,"Chain") -> 0 | H27: =SUMIFS('INVENTORY MASTER'!$AI$4:$AI$63,'INVENTORY MASTER'!$E$4:$E$63,"Chain")-SUMIFS('INVENTORY MASTER'!$AI$4:$AI$63,'INVENTORY MASTER'!$E$4:$E$63,"Chain",'INVENTORY MASTER'!$AS$4:$AS$63,"Sold")-SUMIFS('INVENTORY MASTER'!$AI$4:$AI$63,'INVENTORY MASTER'!$E$4:$E$63,"Chain",'INVENTORY MASTER'!$AS$4:$AS$63,"Written Off") -> 0 | M27: Business Rates | N27: =SUMIFS(EXPENSES!$I$4:$I$83,EXPENSES!$D$4:$D$83,"Business Rates") -> 0
B28: Aug | C28: =SUMIFS(SALES!$K$4:$K$63,SALES!$B$4:$B$63,">="&DATE(YEAR(SETTINGS!$W$9),8,1),SALES!$B$4:$B$63,"<="&EOMONTH(DATE(YEAR(SETTINGS!$W$9),8,1),0)) -> 0 | D28: =SUMIFS(SALES!$N$4:$N$63,SALES!$B$4:$B$63,">="&DATE(YEAR(SETTINGS!$W$9),8,1),SALES!$B$4:$B$63,"<="&EOMONTH(DATE(YEAR(SETTINGS!$W$9),8,1),0)) -> 0 | F28: Gold | G28: =SUMIFS(SALES!$K$4:$K$63,SALES!$E$4:$E$63,"Gold") -> 0 | H28: =SUMIFS('INVENTORY MASTER'!$AI$4:$AI$63,'INVENTORY MASTER'!$E$4:$E$63,"Gold")-SUMIFS('INVENTORY MASTER'!$AI$4:$AI$63,'INVENTORY MASTER'!$E$4:$E$63,"Gold",'INVENTORY MASTER'!$AS$4:$AS$63,"Sold")-SUMIFS('INVENTORY MASTER'!$AI$4:$AI$63,'INVENTORY MASTER'!$E$4:$E$63,"Gold",'INVENTORY MASTER'!$AS$4:$AS$63,"Written Off") -> 1500 | M28: Software | N28: =SUMIFS(EXPENSES!$I$4:$I$83,EXPENSES!$D$4:$D$83,"Software") -> 0
B29: Sep | C29: =SUMIFS(SALES!$K$4:$K$63,SALES!$B$4:$B$63,">="&DATE(YEAR(SETTINGS!$W$9),9,1),SALES!$B$4:$B$63,"<="&EOMONTH(DATE(YEAR(SETTINGS!$W$9),9,1),0)) -> 0 | D29: =SUMIFS(SALES!$N$4:$N$63,SALES!$B$4:$B$63,">="&DATE(YEAR(SETTINGS!$W$9),9,1),SALES!$B$4:$B$63,"<="&EOMONTH(DATE(YEAR(SETTINGS!$W$9),9,1),0)) -> 0 | F29: Diamond Jewellery | G29: =SUMIFS(SALES!$K$4:$K$63,SALES!$E$4:$E$63,"Diamond Jewellery") -> 0 | H29: =SUMIFS('INVENTORY MASTER'!$AI$4:$AI$63,'INVENTORY MASTER'!$E$4:$E$63,"Diamond Jewellery")-SUMIFS('INVENTORY MASTER'!$AI$4:$AI$63,'INVENTORY MASTER'!$E$4:$E$63,"Diamond Jewellery",'INVENTORY MASTER'!$AS$4:$AS$63,"Sold")-SUMIFS('INVENTORY MASTER'!$AI$4:$AI$63,'INVENTORY MASTER'!$E$4:$E$63,"Diamond Jewellery",'INVENTORY MASTER'!$AS$4:$AS$63,"Written Off") -> 3550 | M29: Miscellaneous | N29: =SUMIFS(EXPENSES!$I$4:$I$83,EXPENSES!$D$4:$D$83,"Miscellaneous") -> 0
B30: Oct | C30: =SUMIFS(SALES!$K$4:$K$63,SALES!$B$4:$B$63,">="&DATE(YEAR(SETTINGS!$W$9),10,1),SALES!$B$4:$B$63,"<="&EOMONTH(DATE(YEAR(SETTINGS!$W$9),10,1),0)) -> 0 | D30: =SUMIFS(SALES!$N$4:$N$63,SALES!$B$4:$B$63,">="&DATE(YEAR(SETTINGS!$W$9),10,1),SALES!$B$4:$B$63,"<="&EOMONTH(DATE(YEAR(SETTINGS!$W$9),10,1),0)) -> 0 | F30: Other | G30: =SUMIFS(SALES!$K$4:$K$63,SALES!$E$4:$E$63,"Other") -> 0 | H30: =SUMIFS('INVENTORY MASTER'!$AI$4:$AI$63,'INVENTORY MASTER'!$E$4:$E$63,"Other")-SUMIFS('INVENTORY MASTER'!$AI$4:$AI$63,'INVENTORY MASTER'!$E$4:$E$63,"Other",'INVENTORY MASTER'!$AS$4:$AS$63,"Sold")-SUMIFS('INVENTORY MASTER'!$AI$4:$AI$63,'INVENTORY MASTER'!$E$4:$E$63,"Other",'INVENTORY MASTER'!$AS$4:$AS$63,"Written Off") -> 0
B31: Nov | C31: =SUMIFS(SALES!$K$4:$K$63,SALES!$B$4:$B$63,">="&DATE(YEAR(SETTINGS!$W$9),11,1),SALES!$B$4:$B$63,"<="&EOMONTH(DATE(YEAR(SETTINGS!$W$9),11,1),0)) -> 0 | D31: =SUMIFS(SALES!$N$4:$N$63,SALES!$B$4:$B$63,">="&DATE(YEAR(SETTINGS!$W$9),11,1),SALES!$B$4:$B$63,"<="&EOMONTH(DATE(YEAR(SETTINGS!$W$9),11,1),0)) -> 0
B32: Dec | C32: =SUMIFS(SALES!$K$4:$K$63,SALES!$B$4:$B$63,">="&DATE(YEAR(SETTINGS!$W$9),12,1),SALES!$B$4:$B$63,"<="&EOMONTH(DATE(YEAR(SETTINGS!$W$9),12,1),0)) -> 0 | D32: =SUMIFS(SALES!$N$4:$N$63,SALES!$B$4:$B$63,">="&DATE(YEAR(SETTINGS!$W$9),12,1),SALES!$B$4:$B$63,"<="&EOMONTH(DATE(YEAR(SETTINGS!$W$9),12,1),0)) -> 0
B34: PARTNER CONTRIBUTIONS vs REIMBURSEMENTS
B35: Partner | C35: Introduced | D35: Reimbursed
B36: Partner 1 | C36: =SUMIFS('PARTNER CONTRIBUTIONS'!$H$4:$H$63,'PARTNER CONTRIBUTIONS'!$C$4:$C$63,"Partner 1") -> 18100 | D36: =SUMIFS('PARTNER CONTRIBUTIONS'!$K$4:$K$63,'PARTNER CONTRIBUTIONS'!$C$4:$C$63,"Partner 1") -> 0
B37: Partner 2 | C37: =SUMIFS('PARTNER CONTRIBUTIONS'!$H$4:$H$63,'PARTNER CONTRIBUTIONS'!$C$4:$C$63,"Partner 2") -> 3550 | D37: =SUMIFS('PARTNER CONTRIBUTIONS'!$K$4:$K$63,'PARTNER CONTRIBUTIONS'!$C$4:$C$63,"Partner 2") -> 0
B38: Partner 3 | C38: =SUMIFS('PARTNER CONTRIBUTIONS'!$H$4:$H$63,'PARTNER CONTRIBUTIONS'!$C$4:$C$63,"Partner 3") -> 9790 | D38: =SUMIFS('PARTNER CONTRIBUTIONS'!$K$4:$K$63,'PARTNER CONTRIBUTIONS'!$C$4:$C$63,"Partner 3") -> 2000

Sheet INSTRUCTIONS
A1: READ ME — How to use this workbook
A2: Jewellery & Luxury Watch Shop Management System · Version 1 · GBP (£) · Dates DD/MM/YYYY
B4: Colour key
B5: Cream cells | C5: You type here (data entry). Example: Purchase Price, Selling Price, dropdowns.
B6: Grey cells | C6: Calculated automatically by formula — do not type over these. They are protected.
B7: Gold band | C7: Section headings / key totals.
B8: Red highlight | C8: A warning that needs attention (below minimum price, missing stock, overdue, negative margin).
B10: Getting started — enter your data in this order
C11: 1. SETTINGS — rename Partner 1/2/3 to real names, set staff names, check ownership % totals 100%.
C12: 2. INVENTORY MASTER — add every item of current stock (use the ID helper on SETTINGS for the next WAT-/JWL- number).
C13: 3. PARTNER CONTRIBUTIONS — record who personally funded each item / cost, and whether it is a loan or capital.
C14: 4. BUILDING & SETUP + EXPENSES — enter refurbishment, rent and other business costs.
C15: 5. SALES — record each sale by Stock ID; cost and profit fill in automatically.
C16: 6. Check the DASHBOARD — all KPIs, charts and warnings update automatically.
B18: Partner accounting principle (important)
B19: Paid By ≠ Ownership | C19: Who paid for an item does NOT mean they own it. Record the funding nature (Partner Loan / Capital / Business Purchase) in 'Funding Type' and log every partner payment in PARTNER CONTRIBUTIONS.
B20: What the business owes | C20: PARTNER CONTRIBUTIONS keeps a running current-account: Amount introduced − Reimbursed = Outstanding. PARTNER SUMMARY and the DASHBOARD show what is owed to each partner.
B21: Profit is NOT auto-split | C21: Ownership % on SETTINGS is informational only. Profit is not divided automatically because ownership may differ from funding.
B23: Profit levels
B24: Item gross profit | C24: Selling Price − Landed Cost (per item). Rent/overheads do NOT affect item gross profit.
B25: Net trading result | C25: Total gross profit − operating expenses. Shown on the DASHBOARD and MONTH-END sheets.
B27: Adding a PHOTO to each item
B28: Best method (Excel 365) | C28: On INVENTORY MASTER, click the 'Photo' cell for the row, then Insert > Pictures > Place in Cell > This Device. The picture sits inside the cell and sorts/filters with the item.
B29: Any Excel version | C29: Save each photo in a folder (or cloud) and put its file path or URL in the 'Photo/Document Link' column.
B30: Sample images | C30: The example rows show floating placeholder pictures so you can see the idea — delete them and use Place in Cell for real stock.
B31: Model vs Serial | C31: 'Model/Ref Number' (e.g. 126610LN) and 'Serial Number' (the unique piece number) are separate columns — fill in both. Watch Details repeats them for watches.
B33: Buying in USD, Dirham (AED) or other currencies
B34: 1. Pick the currency | C34: On INVENTORY MASTER set 'Purchase Currency' (GBP, USD, AED, EUR...) from the dropdown.
B35: 2. Enter the foreign price | C35: Type what you paid in that currency in 'Original Purchase Price' (e.g. 22,000 for AED 22,000).
B36: 3. Rate to GBP | C36: Type the exchange rate you got in 'FX Rate to GBP' (GBP per 1 unit, e.g. USD 0.79). Leave it blank to use the indicative rate on SETTINGS.
B37: Result | C37: 'Purchase Price (GBP)' converts automatically (Original x rate). All profit, stock value and dashboard figures then use the GBP amount — GBP rows always use rate 1.
B38: Update rates | C38: Maintain the CURRENCIES & FX RATES table on SETTINGS. Historical buys keep the exact rate typed on their row, so past costs never change when today's rates move.
B40: Notes & limitations
B41: Example rows | C41: Rows marked 'EXAMPLE' are dummy data — delete them before going live.
B42: Protection / password | C42: Every sheet is READ-ONLY and password protected — staff can view, select, copy and filter, but cannot change anything. A PARTNER edits by: Review ▸ Unprotect Sheet ▸ enter password 643216 ▸ make changes ▸ Review ▸ Protect Sheet (re-enter 643216). The workbook structure is also locked (no adding/removing sheets).
B43: Change the password | C43: Do it per sheet in Excel: Review ▸ Unprotect Sheet (643216), then Review ▸ Protect Sheet and type a new password. Repeat for each sheet, and Review ▸ Protect Workbook for the structure. Keep the password safe — it cannot be recovered if lost.
B44: Open-password (optional) | C44: To also require a password just to OPEN the file, do it in Excel: File ▸ Info ▸ Protect Workbook ▸ Encrypt with Password. (This can only be set in Excel, not generated here.)
B45: Who changed what | C45: Excel cannot auto-log edits without a macro. Record price changes, write-offs and refunds in the AUDIT LOG sheet. Ask if you'd like an automatic macro-based log (.xlsm).
B46: Slicers / PivotTables | C46: Native Excel slicers and PivotTables can be added on top; summary tables here use SUMIFS/COUNTIFS so the file recalculates everywhere, including in the browser.
B47: Migration | C47: Each sheet is a clean table keyed by Stock ID / IDs, ready to export to Airtable, a database or a POS/inventory app.

Sheet INVENTORY MASTER
A1: INVENTORY MASTER
A2: Every physical item entering the business. Cream = you enter · Grey = auto-calculated. 'Paid By' does NOT mean ownership — record ownership in Funding Type & the Partner ledger.
A3: Stock ID | B3: Photo | C3: Barcode/QR Ref | D3: Date Purchased | E3: Category | F3: Subcategory | G3: Brand | H3: Model | I3: Model/Ref Number | J3: Serial Number | K3: Description | L3: Metal | M3: Metal Purity | N3: Weight (g) | O3: Stone Type | P3: Stone Carat | Q3: Diamond Colour | R3: Diamond Clarity | S3: Ring Size | T3: Watch Case Size | U3: Watch Movement | V3: Watch Year | W3: Box Included | X3: Papers Included | Y3: Warranty Included | Z3: Condition | AA3: Supplier Name | AB3: Supplier Type | AC3: Supplier Invoice Ref | AD3: Purchase Currency | AE3: Original Purchase Price | AF3: FX Rate to GBP | AG3: Purchase Price (GBP) | AH3: Additional Costs | AI3: Total Landed Cost | AJ3: Paid By | AK3: Funding Type | AL3: Ownership/Funding Notes | AM3: Target Selling Price | AN3: Minimum Selling Price | AO3: Current Advertised Price | AP3: Expected Gross Profit | AQ3: Expected Margin % | AR3: Current Location | AS3: Stock Status | AT3: Date Sold | AU3: Actual Selling Price | AV3: Actual Gross Profit | AW3: Actual Margin % | AX3: Salesperson | AY3: Customer/Invoice Ref | AZ3: Payment Method | BA3: Photo/Document Link | BB3: Notes
A4: WAT-0001 | C4: BC100001 | D4: 46037 | E4: Watch | F4: Luxury Watch | G4: Rolex | H4: Submariner | I4: 126610LN | J4: ROL123456 | K4: Rolex Submariner Date 41mm, black dial | T4: 41mm | U4: Automatic | V4: 2022 | W4: Yes | X4: Yes | Y4: Yes | Z4: Excellent | AA4: Prestige Watch Co | AB4: Watch Dealer | AC4: PWC-4471 | AD4: GBP | AE4: 8000 | AG4: =IF($AE4="","",$AE4*IF($AD4="GBP",1,IF($AF4<>"",$AF4,IFERROR(INDEX(SETTINGS!$W$29:$W$36,MATCH($AD4,SETTINGS!$V$29:$V$36,0)),1)))) -> 8000 | AH4: 100 | AI4: =IF(N($AG4)+N($AH4)=0,"",N($AG4)+N($AH4)) -> 8100 | AJ4: Partner 1 | AK4: Partner Loan | AL4: EXAMPLE – funded personally by Partner 1; business owes reimbursement | AM4: 10500 | AN4: 9500 | AO4: 10500 | AP4: =IF(OR($AM4="",$AI4=""),"",$AM4-$AI4) -> 2400 | AQ4: =IF(OR($AM4="",$AM4=0,$AP4=""),"",$AP4/$AM4) -> 0.22857143 | AR4: Shop Safe | AS4: Sold | AT4: 46063 | AU4: 10200 | AV4: =IF(OR($AU4="",$AI4=""),"",$AU4-$AI4) -> 2100 | AW4: =IF(OR($AU4="",$AU4=0,$AV4=""),"",$AV4/$AU4) -> 0.20588235 | AX4: Sarah Hughes | AY4: INV-1001 | AZ4: Bank Transfer | BA4: link/wat-0001.jpg | BB4: EXAMPLE ROW – safe to delete
A5: JWL-0001 | C5: BC200001 | D5: 46042 | E5: Diamond Jewellery | F5: Solitaire Ring | G5: Bespoke | H5: Solitaire | K5: Platinum solitaire diamond ring 1.01ct | L5: Platinum | M5: 950 Platinum | N5: 5.2 | O5: Diamond | P5: 1.01 | Q5: F | R5: VS1 | S5: M | Z5: New | AA5: Hatton Diamonds | AB5: Jewellery Dealer | AC5: HD-9987 | AD5: GBP | AE5: 3500 | AG5: =IF($AE5="","",$AE5*IF($AD5="GBP",1,IF($AF5<>"",$AF5,IFERROR(INDEX(SETTINGS!$W$29:$W$36,MATCH($AD5,SETTINGS!$V$29:$V$36,0)),1)))) -> 3500 | AH5: 50 | AI5: =IF(N($AG5)+N($AH5)=0,"",N($AG5)+N($AH5)) -> 3550 | AJ5: Partner 2 | AK5: Partner Loan | AL5: EXAMPLE – funded personally by Partner 2 | AM5: 5500 | AN5: 4800 | AO5: 5500 | AP5: =IF(OR($AM5="",$AI5=""),"",$AM5-$AI5) -> 1950 | AQ5: =IF(OR($AM5="",$AM5=0,$AP5=""),"",$AP5/$AM5) -> 0.35454545 | AR5: Shop Display | AS5: Available | AV5: =IF(OR($AU5="",$AI5=""),"",$AU5-$AI5) | AW5: =IF(OR($AU5="",$AU5=0,$AV5=""),"",$AV5/$AU5) | BA5: link/jwl-0001.jpg | BB5: EXAMPLE ROW – safe to delete
A6: WAT-0002 | C6: BC100002 | D6: 46047 | E6: Watch | F6: Luxury Watch | G6: Omega | H6: Speedmaster | I6: 310.30.42 | J6: OMG789012 | K6: Omega Speedmaster Moonwatch 42mm | T6: 42mm | U6: Manual | V6: 2023 | W6: Yes | X6: No | Y6: No | Z6: Very Good | AA6: City Auctions | AB6: Auction | AC6: CA-2201 | AD6: USD | AE6: 4000 | AF6: 0.79 | AG6: =IF($AE6="","",$AE6*IF($AD6="GBP",1,IF($AF6<>"",$AF6,IFERROR(INDEX(SETTINGS!$W$29:$W$36,MATCH($AD6,SETTINGS!$V$29:$V$36,0)),1)))) -> 3160 | AH6: 40 | AI6: =IF(N($AG6)+N($AH6)=0,"",N($AG6)+N($AH6)) -> 3200 | AJ6: Business Bank Account | AK6: Business Purchase | AL6: EXAMPLE – bought in US Dollars ($4,000 × 0.79 = £3,160) | AM6: 4500 | AN6: 4000 | AO6: 4500 | AP6: =IF(OR($AM6="",$AI6=""),"",$AM6-$AI6) -> 1300 | AQ6: =IF(OR($AM6="",$AM6=0,$AP6=""),"",$AP6/$AM6) -> 0.28888889 | AR6: Shop Display | AS6: Available | AV6: =IF(OR($AU6="",$AI6=""),"",$AU6-$AI6) | AW6: =IF(OR($AU6="",$AU6=0,$AV6=""),"",$AV6/$AU6) | BA6: link/wat-0002.jpg | BB6: EXAMPLE ROW – safe to delete
A7: JWL-0002 | C7: BC200002 | D7: 46054 | E7: Gold | F7: Chain Necklace | H7: Belcher Chain | K7: 18ct yellow gold belcher chain necklace | L7: Gold | M7: 18ct | N7: 22.5 | Z7: New | AA7: Goldsmith Wholesale | AB7: Wholesaler | AC7: GW-5540 | AD7: GBP | AE7: 1500 | AG7: =IF($AE7="","",$AE7*IF($AD7="GBP",1,IF($AF7<>"",$AF7,IFERROR(INDEX(SETTINGS!$W$29:$W$36,MATCH($AD7,SETTINGS!$V$29:$V$36,0)),1)))) -> 1500 | AH7: 0 | AI7: =IF(N($AG7)+N($AH7)=0,"",N($AG7)+N($AH7)) -> 1500 | AJ7: Business Bank Account | AK7: Business Purchase | AL7: EXAMPLE – business owned stock | AM7: 2200 | AN7: 1900 | AO7: 2200 | AP7: =IF(OR($AM7="",$AI7=""),"",$AM7-$AI7) -> 700 | AQ7: =IF(OR($AM7="",$AM7=0,$AP7=""),"",$AP7/$AM7) -> 0.31818182 | AR7: Shop Safe | AS7: Available | AV7: =IF(OR($AU7="",$AI7=""),"",$AU7-$AI7) | AW7: =IF(OR($AU7="",$AU7=0,$AV7=""),"",$AV7/$AU7) | BA7: link/jwl-0002.jpg | BB7: EXAMPLE ROW – safe to delete
A8: WAT-0003 | C8: BC100003 | D8: 46058 | E8: Watch | F8: Luxury Watch | G8: Cartier | H8: Santos | I8: WSSA0018 | J8: CAR334455 | K8: Cartier Santos Medium steel | T8: 35mm | U8: Automatic | V8: 2021 | W8: Yes | X8: Yes | Y8: Yes | Z8: Excellent | AA8: Private Seller | AB8: Private Seller | AC8: PS-0007 | AD8: AED | AE8: 22000 | AF8: 0.215 | AG8: =IF($AE8="","",$AE8*IF($AD8="GBP",1,IF($AF8<>"",$AF8,IFERROR(INDEX(SETTINGS!$W$29:$W$36,MATCH($AD8,SETTINGS!$V$29:$V$36,0)),1)))) -> 4730 | AH8: 60 | AI8: =IF(N($AG8)+N($AH8)=0,"",N($AG8)+N($AH8)) -> 4790 | AJ8: Partner 3 | AK8: Partner Loan | AL8: EXAMPLE – bought in UAE Dirham (22,000 AED × 0.215 = £4,730); with Partner 3 | AM8: 6500 | AN8: 5900 | AO8: 6500 | AP8: =IF(OR($AM8="",$AI8=""),"",$AM8-$AI8) -> 1710 | AQ8: =IF(OR($AM8="",$AM8=0,$AP8=""),"",$AP8/$AM8) -> 0.26307692 | AR8: Partner 3 | AS8: With Partner | AV8: =IF(OR($AU8="",$AI8=""),"",$AU8-$AI8) | AW8: =IF(OR($AU8="",$AU8=0,$AV8=""),"",$AV8/$AU8) | BB8: EXAMPLE ROW – safe to delete
A9: JWL-0003 | C9: BC200003 | D9: 46063 | E9: Bracelet | F9: Bangle | H9: Gold Bangle | K9: 22ct gold hand bracelet / bangle | L9: Gold | M9: 22ct | N9: 18 | O9: None | Z9: New | AA9: Goldsmith Wholesale | AB9: Wholesaler | AC9: GW-5541 | AD9: GBP | AE9: 1650 | AG9: =IF($AE9="","",$AE9*IF($AD9="GBP",1,IF($AF9<>"",$AF9,IFERROR(INDEX(SETTINGS!$W$29:$W$36,MATCH($AD9,SETTINGS!$V$29:$V$36,0)),1)))) -> 1650 | AH9: 0 | AI9: =IF(N($AG9)+N($AH9)=0,"",N($AG9)+N($AH9)) -> 1650 | AJ9: Business Bank Account | AK9: Business Purchase | AL9: EXAMPLE – gold bangle; use Jewellery Details for the gold calculator | AM9: 2400 | AN9: 2050 | AO9: 2400 | AP9: =IF(OR($AM9="",$AI9=""),"",$AM9-$AI9) -> 750 | AQ9: =IF(OR($AM9="",$AM9=0,$AP9=""),"",$AP9/$AM9) -> 0.3125 | AR9: Shop Safe | AS9: Available | AV9: =IF(OR($AU9="",$AI9=""),"",$AU9-$AI9) | AW9: =IF(OR($AU9="",$AU9=0,$AV9=""),"",$AV9/$AU9) | BA9: link/jwl-0003.jpg | BB9: EXAMPLE bracelet – safe to delete
AG10: =IF($AE10="","",$AE10*IF($AD10="GBP",1,IF($AF10<>"",$AF10,IFERROR(INDEX(SETTINGS!$W$29:$W$36,MATCH($AD10,SETTINGS!$V$29:$V$36,0)),1)))) | AI10: =IF(N($AG10)+N($AH10)=0,"",N($AG10)+N($AH10)) | AP10: =IF(OR($AM10="",$AI10=""),"",$AM10-$AI10) | AQ10: =IF(OR($AM10="",$AM10=0,$AP10=""),"",$AP10/$AM10) | AV10: =IF(OR($AU10="",$AI10=""),"",$AU10-$AI10) | AW10: =IF(OR($AU10="",$AU10=0,$AV10=""),"",$AV10/$AU10)
AG11: =IF($AE11="","",$AE11*IF($AD11="GBP",1,IF($AF11<>"",$AF11,IFERROR(INDEX(SETTINGS!$W$29:$W$36,MATCH($AD11,SETTINGS!$V$29:$V$36,0)),1)))) | AI11: =IF(N($AG11)+N($AH11)=0,"",N($AG11)+N($AH11)) | AP11: =IF(OR($AM11="",$AI11=""),"",$AM11-$AI11) | AQ11: =IF(OR($AM11="",$AM11=0,$AP11=""),"",$AP11/$AM11) | AV11: =IF(OR($AU11="",$AI11=""),"",$AU11-$AI11) | AW11: =IF(OR($AU11="",$AU11=0,$AV11=""),"",$AV11/$AU11)
AG12: =IF($AE12="","",$AE12*IF($AD12="GBP",1,IF($AF12<>"",$AF12,IFERROR(INDEX(SETTINGS!$W$29:$W$36,MATCH($AD12,SETTINGS!$V$29:$V$36,0)),1)))) | AI12: =IF(N($AG12)+N($AH12)=0,"",N($AG12)+N($AH12)) | AP12: =IF(OR($AM12="",$AI12=""),"",$AM12-$AI12) | AQ12: =IF(OR($AM12="",$AM12=0,$AP12=""),"",$AP12/$AM12) | AV12: =IF(OR($AU12="",$AI12=""),"",$AU12-$AI12) | AW12: =IF(OR($AU12="",$AU12=0,$AV12=""),"",$AV12/$AU12)
AG13: =IF($AE13="","",$AE13*IF($AD13="GBP",1,IF($AF13<>"",$AF13,IFERROR(INDEX(SETTINGS!$W$29:$W$36,MATCH($AD13,SETTINGS!$V$29:$V$36,0)),1)))) | AI13: =IF(N($AG13)+N($AH13)=0,"",N($AG13)+N($AH13)) | AP13: =IF(OR($AM13="",$AI13=""),"",$AM13-$AI13) | AQ13: =IF(OR($AM13="",$AM13=0,$AP13=""),"",$AP13/$AM13) | AV13: =IF(OR($AU13="",$AI13=""),"",$AU13-$AI13) | AW13: =IF(OR($AU13="",$AU13=0,$AV13=""),"",$AV13/$AU13)
AG14: =IF($AE14="","",$AE14*IF($AD14="GBP",1,IF($AF14<>"",$AF14,IFERROR(INDEX(SETTINGS!$W$29:$W$36,MATCH($AD14,SETTINGS!$V$29:$V$36,0)),1)))) | AI14: =IF(N($AG14)+N($AH14)=0,"",N($AG14)+N($AH14)) | AP14: =IF(OR($AM14="",$AI14=""),"",$AM14-$AI14) | AQ14: =IF(OR($AM14="",$AM14=0,$AP14=""),"",$AP14/$AM14) | AV14: =IF(OR($AU14="",$AI14=""),"",$AU14-$AI14) | AW14: =IF(OR($AU14="",$AU14=0,$AV14=""),"",$AV14/$AU14)
AG15: =IF($AE15="","",$AE15*IF($AD15="GBP",1,IF($AF15<>"",$AF15,IFERROR(INDEX(SETTINGS!$W$29:$W$36,MATCH($AD15,SETTINGS!$V$29:$V$36,0)),1)))) | AI15: =IF(N($AG15)+N($AH15)=0,"",N($AG15)+N($AH15)) | AP15: =IF(OR($AM15="",$AI15=""),"",$AM15-$AI15) | AQ15: =IF(OR($AM15="",$AM15=0,$AP15=""),"",$AP15/$AM15) | AV15: =IF(OR($AU15="",$AI15=""),"",$AU15-$AI15) | AW15: =IF(OR($AU15="",$AU15=0,$AV15=""),"",$AV15/$AU15)
AG16: =IF($AE16="","",$AE16*IF($AD16="GBP",1,IF($AF16<>"",$AF16,IFERROR(INDEX(SETTINGS!$W$29:$W$36,MATCH($AD16,SETTINGS!$V$29:$V$36,0)),1)))) | AI16: =IF(N($AG16)+N($AH16)=0,"",N($AG16)+N($AH16)) | AP16: =IF(OR($AM16="",$AI16=""),"",$AM16-$AI16) | AQ16: =IF(OR($AM16="",$AM16=0,$AP16=""),"",$AP16/$AM16) | AV16: =IF(OR($AU16="",$AI16=""),"",$AU16-$AI16) | AW16: =IF(OR($AU16="",$AU16=0,$AV16=""),"",$AV16/$AU16)
AG17: =IF($AE17="","",$AE17*IF($AD17="GBP",1,IF($AF17<>"",$AF17,IFERROR(INDEX(SETTINGS!$W$29:$W$36,MATCH($AD17,SETTINGS!$V$29:$V$36,0)),1)))) | AI17: =IF(N($AG17)+N($AH17)=0,"",N($AG17)+N($AH17)) | AP17: =IF(OR($AM17="",$AI17=""),"",$AM17-$AI17) | AQ17: =IF(OR($AM17="",$AM17=0,$AP17=""),"",$AP17/$AM17) | AV17: =IF(OR($AU17="",$AI17=""),"",$AU17-$AI17) | AW17: =IF(OR($AU17="",$AU17=0,$AV17=""),"",$AV17/$AU17)
AG18: =IF($AE18="","",$AE18*IF($AD18="GBP",1,IF($AF18<>"",$AF18,IFERROR(INDEX(SETTINGS!$W$29:$W$36,MATCH($AD18,SETTINGS!$V$29:$V$36,0)),1)))) | AI18: =IF(N($AG18)+N($AH18)=0,"",N($AG18)+N($AH18)) | AP18: =IF(OR($AM18="",$AI18=""),"",$AM18-$AI18) | AQ18: =IF(OR($AM18="",$AM18=0,$AP18=""),"",$AP18/$AM18) | AV18: =IF(OR($AU18="",$AI18=""),"",$AU18-$AI18) | AW18: =IF(OR($AU18="",$AU18=0,$AV18=""),"",$AV18/$AU18)
AG19: =IF($AE19="","",$AE19*IF($AD19="GBP",1,IF($AF19<>"",$AF19,IFERROR(INDEX(SETTINGS!$W$29:$W$36,MATCH($AD19,SETTINGS!$V$29:$V$36,0)),1)))) | AI19: =IF(N($AG19)+N($AH19)=0,"",N($AG19)+N($AH19)) | AP19: =IF(OR($AM19="",$AI19=""),"",$AM19-$AI19) | AQ19: =IF(OR($AM19="",$AM19=0,$AP19=""),"",$AP19/$AM19) | AV19: =IF(OR($AU19="",$AI19=""),"",$AU19-$AI19) | AW19: =IF(OR($AU19="",$AU19=0,$AV19=""),"",$AV19/$AU19)
AG20: =IF($AE20="","",$AE20*IF($AD20="GBP",1,IF($AF20<>"",$AF20,IFERROR(INDEX(SETTINGS!$W$29:$W$36,MATCH($AD20,SETTINGS!$V$29:$V$36,0)),1)))) | AI20: =IF(N($AG20)+N($AH20)=0,"",N($AG20)+N($AH20)) | AP20: =IF(OR($AM20="",$AI20=""),"",$AM20-$AI20) | AQ20: =IF(OR($AM20="",$AM20=0,$AP20=""),"",$AP20/$AM20) | AV20: =IF(OR($AU20="",$AI20=""),"",$AU20-$AI20) | AW20: =IF(OR($AU20="",$AU20=0,$AV20=""),"",$AV20/$AU20)
AG21: =IF($AE21="","",$AE21*IF($AD21="GBP",1,IF($AF21<>"",$AF21,IFERROR(INDEX(SETTINGS!$W$29:$W$36,MATCH($AD21,SETTINGS!$V$29:$V$36,0)),1)))) | AI21: =IF(N($AG21)+N($AH21)=0,"",N($AG21)+N($AH21)) | AP21: =IF(OR($AM21="",$AI21=""),"",$AM21-$AI21) | AQ21: =IF(OR($AM21="",$AM21=0,$AP21=""),"",$AP21/$AM21) | AV21: =IF(OR($AU21="",$AI21=""),"",$AU21-$AI21) | AW21: =IF(OR($AU21="",$AU21=0,$AV21=""),"",$AV21/$AU21)
... AG63: =IF($AE63="","",$AE63*IF($AD63="GBP",1,IF($AF63<>"",$AF63,IFERROR(INDEX(SETTINGS!$W$29:$W$36,MATCH($AD63,SETTINGS!$V$29:$V$36,0)),1)))) | AI63: =IF(N($AG63)+N($AH63)=0,"",N($AG63)+N($AH63)) | AP63: =IF(OR($AM63="",$AI63=""),"",$AM63-$AI63) | AQ63: =IF(OR($AM63="",$AM63=0,$AP63=""),"",$AP63/$AM63) | AV63: =IF(OR($AU63="",$AI63=""),"",$AU63-$AI63) | AW63: =IF(OR($AU63="",$AU63=0,$AV63=""),"",$AV63/$AU63)

Sheet WATCH DETAILS
A1: WATCH DETAILS
A2: Watch-specific view. Enter a Stock ID (dropdown) — details pull automatically from Inventory Master. Cream fields are watch-only extras you can enter.
A3: Stock ID | B3: Brand | C3: Model | D3: Reference Number | E3: Serial Number | F3: Year | G3: Case Size | H3: Case Material | I3: Dial Colour | J3: Bracelet/Strap | K3: Movement | L3: Auto/Manual/Quartz | M3: Box | N3: Papers | O3: Warranty Card | P3: Warranty Date | Q3: Service History | R3: Last Service | S3: Condition | T3: Purchase Cost | U3: Target Price | V3: Current Price | W3: Status | X3: Location | Y3: Notes
A4: WAT-0001 | B4: =IF($A4="","",IFERROR(INDEX('INVENTORY MASTER'!$G$4:$G$63,MATCH($A4,'INVENTORY MASTER'!$A$4:$A$63,0)),"")) -> Rolex | C4: =IF($A4="","",IFERROR(INDEX('INVENTORY MASTER'!$H$4:$H$63,MATCH($A4,'INVENTORY MASTER'!$A$4:$A$63,0)),"")) -> Submariner | D4: =IF($A4="","",IFERROR(INDEX('INVENTORY MASTER'!$I$4:$I$63,MATCH($A4,'INVENTORY MASTER'!$A$4:$A$63,0)),"")) -> 126610LN | E4: =IF($A4="","",IFERROR(INDEX('INVENTORY MASTER'!$J$4:$J$63,MATCH($A4,'INVENTORY MASTER'!$A$4:$A$63,0)),"")) -> ROL123456 | F4: =IF($A4="","",IFERROR(INDEX('INVENTORY MASTER'!$V$4:$V$63,MATCH($A4,'INVENTORY MASTER'!$A$4:$A$63,0)),"")) -> 2022 | G4: =IF($A4="","",IFERROR(INDEX('INVENTORY MASTER'!$T$4:$T$63,MATCH($A4,'INVENTORY MASTER'!$A$4:$A$63,0)),"")) -> 41mm | K4: =IF($A4="","",IFERROR(INDEX('INVENTORY MASTER'!$U$4:$U$63,MATCH($A4,'INVENTORY MASTER'!$A$4:$A$63,0)),"")) -> Automatic | L4: =IF($A4="","",IFERROR(INDEX('INVENTORY MASTER'!$U$4:$U$63,MATCH($A4,'INVENTORY MASTER'!$A$4:$A$63,0)),"")) -> Automatic | M4: =IF($A4="","",IFERROR(INDEX('INVENTORY MASTER'!$W$4:$W$63,MATCH($A4,'INVENTORY MASTER'!$A$4:$A$63,0)),"")) -> Yes | N4: =IF($A4="","",IFERROR(INDEX('INVENTORY MASTER'!$X$4:$X$63,MATCH($A4,'INVENTORY MASTER'!$A$4:$A$63,0)),"")) -> Yes | O4: =IF($A4="","",IFERROR(INDEX('INVENTORY MASTER'!$Y$4:$Y$63,MATCH($A4,'INVENTORY MASTER'!$A$4:$A$63,0)),"")) -> Yes | S4: =IF($A4="","",IFERROR(INDEX('INVENTORY MASTER'!$Z$4:$Z$63,MATCH($A4,'INVENTORY MASTER'!$A$4:$A$63,0)),"")) -> Excellent | T4: =IF($A4="","",IFERROR(INDEX('INVENTORY MASTER'!$AI$4:$AI$63,MATCH($A4,'INVENTORY MASTER'!$A$4:$A$63,0)),"")) -> 8100 | U4: =IF($A4="","",IFERROR(INDEX('INVENTORY MASTER'!$AM$4:$AM$63,MATCH($A4,'INVENTORY MASTER'!$A$4:$A$63,0)),"")) -> 10500 | V4: =IF($A4="","",IFERROR(INDEX('INVENTORY MASTER'!$AO$4:$AO$63,MATCH($A4,'INVENTORY MASTER'!$A$4:$A$63,0)),"")) -> 10500 | W4: =IF($A4="","",IFERROR(INDEX('INVENTORY MASTER'!$AS$4:$AS$63,MATCH($A4,'INVENTORY MASTER'!$A$4:$A$63,0)),"")) -> Sold | X4: =IF($A4="","",IFERROR(INDEX('INVENTORY MASTER'!$AR$4:$AR$63,MATCH($A4,'INVENTORY MASTER'!$A$4:$A$63,0)),"")) -> Shop Safe
A5: WAT-0002 | B5: =IF($A5="","",IFERROR(INDEX('INVENTORY MASTER'!$G$4:$G$63,MATCH($A5,'INVENTORY MASTER'!$A$4:$A$63,0)),"")) -> Omega | C5: =IF($A5="","",IFERROR(INDEX('INVENTORY MASTER'!$H$4:$H$63,MATCH($A5,'INVENTORY MASTER'!$A$4:$A$63,0)),"")) -> Speedmaster | D5: =IF($A5="","",IFERROR(INDEX('INVENTORY MASTER'!$I$4:$I$63,MATCH($A5,'INVENTORY MASTER'!$A$4:$A$63,0)),"")) -> 310.30.42 | E5: =IF($A5="","",IFERROR(INDEX('INVENTORY MASTER'!$J$4:$J$63,MATCH($A5,'INVENTORY MASTER'!$A$4:$A$63,0)),"")) -> OMG789012 | F5: =IF($A5="","",IFERROR(INDEX('INVENTORY MASTER'!$V$4:$V$63,MATCH($A5,'INVENTORY MASTER'!$A$4:$A$63,0)),"")) -> 2023 | G5: =IF($A5="","",IFERROR(INDEX('INVENTORY MASTER'!$T$4:$T$63,MATCH($A5,'INVENTORY MASTER'!$A$4:$A$63,0)),"")) -> 42mm | K5: =IF($A5="","",IFERROR(INDEX('INVENTORY MASTER'!$U$4:$U$63,MATCH($A5,'INVENTORY MASTER'!$A$4:$A$63,0)),"")) -> Manual | L5: =IF($A5="","",IFERROR(INDEX('INVENTORY MASTER'!$U$4:$U$63,MATCH($A5,'INVENTORY MASTER'!$A$4:$A$63,0)),"")) -> Manual | M5: =IF($A5="","",IFERROR(INDEX('INVENTORY MASTER'!$W$4:$W$63,MATCH($A5,'INVENTORY MASTER'!$A$4:$A$63,0)),"")) -> Yes | N5: =IF($A5="","",IFERROR(INDEX('INVENTORY MASTER'!$X$4:$X$63,MATCH($A5,'INVENTORY MASTER'!$A$4:$A$63,0)),"")) -> No | O5: =IF($A5="","",IFERROR(INDEX('INVENTORY MASTER'!$Y$4:$Y$63,MATCH($A5,'INVENTORY MASTER'!$A$4:$A$63,0)),"")) -> No | S5: =IF($A5="","",IFERROR(INDEX('INVENTORY MASTER'!$Z$4:$Z$63,MATCH($A5,'INVENTORY MASTER'!$A$4:$A$63,0)),"")) -> Very Good | T5: =IF($A5="","",IFERROR(INDEX('INVENTORY MASTER'!$AI$4:$AI$63,MATCH($A5,'INVENTORY MASTER'!$A$4:$A$63,0)),"")) -> 3200 | U5: =IF($A5="","",IFERROR(INDEX('INVENTORY MASTER'!$AM$4:$AM$63,MATCH($A5,'INVENTORY MASTER'!$A$4:$A$63,0)),"")) -> 4500 | V5: =IF($A5="","",IFERROR(INDEX('INVENTORY MASTER'!$AO$4:$AO$63,MATCH($A5,'INVENTORY MASTER'!$A$4:$A$63,0)),"")) -> 4500 | W5: =IF($A5="","",IFERROR(INDEX('INVENTORY MASTER'!$AS$4:$AS$63,MATCH($A5,'INVENTORY MASTER'!$A$4:$A$63,0)),"")) -> Available | X5: =IF($A5="","",IFERROR(INDEX('INVENTORY MASTER'!$AR$4:$AR$63,MATCH($A5,'INVENTORY MASTER'!$A$4:$A$63,0)),"")) -> Shop Display
A6: WAT-0003 | B6: =IF($A6="","",IFERROR(INDEX('INVENTORY MASTER'!$G$4:$G$63,MATCH($A6,'INVENTORY MASTER'!$A$4:$A$63,0)),"")) -> Cartier | C6: =IF($A6="","",IFERROR(INDEX('INVENTORY MASTER'!$H$4:$H$63,MATCH($A6,'INVENTORY MASTER'!$A$4:$A$63,0)),"")) -> Santos | D6: =IF($A6="","",IFERROR(INDEX('INVENTORY MASTER'!$I$4:$I$63,MATCH($A6,'INVENTORY MASTER'!$A$4:$A$63,0)),"")) -> WSSA0018 | E6: =IF($A6="","",IFERROR(INDEX('INVENTORY MASTER'!$J$4:$J$63,MATCH($A6,'INVENTORY MASTER'!$A$4:$A$63,0)),"")) -> CAR334455 | F6: =IF($A6="","",IFERROR(INDEX('INVENTORY MASTER'!$V$4:$V$63,MATCH($A6,'INVENTORY MASTER'!$A$4:$A$63,0)),"")) -> 2021 | G6: =IF($A6="","",IFERROR(INDEX('INVENTORY MASTER'!$T$4:$T$63,MATCH($A6,'INVENTORY MASTER'!$A$4:$A$63,0)),"")) -> 35mm | K6: =IF($A6="","",IFERROR(INDEX('INVENTORY MASTER'!$U$4:$U$63,MATCH($A6,'INVENTORY MASTER'!$A$4:$A$63,0)),"")) -> Automatic | L6: =IF($A6="","",IFERROR(INDEX('INVENTORY MASTER'!$U$4:$U$63,MATCH($A6,'INVENTORY MASTER'!$A$4:$A$63,0)),"")) -> Automatic | M6: =IF($A6="","",IFERROR(INDEX('INVENTORY MASTER'!$W$4:$W$63,MATCH($A6,'INVENTORY MASTER'!$A$4:$A$63,0)),"")) -> Yes | N6: =IF($A6="","",IFERROR(INDEX('INVENTORY MASTER'!$X$4:$X$63,MATCH($A6,'INVENTORY MASTER'!$A$4:$A$63,0)),"")) -> Yes | O6: =IF($A6="","",IFERROR(INDEX('INVENTORY MASTER'!$Y$4:$Y$63,MATCH($A6,'INVENTORY MASTER'!$A$4:$A$63,0)),"")) -> Yes | S6: =IF($A6="","",IFERROR(INDEX('INVENTORY MASTER'!$Z$4:$Z$63,MATCH($A6,'INVENTORY MASTER'!$A$4:$A$63,0)),"")) -> Excellent | T6: =IF($A6="","",IFERROR(INDEX('INVENTORY MASTER'!$AI$4:$AI$63,MATCH($A6,'INVENTORY MASTER'!$A$4:$A$63,0)),"")) -> 4790 | U6: =IF($A6="","",IFERROR(INDEX('INVENTORY MASTER'!$AM$4:$AM$63,MATCH($A6,'INVENTORY MASTER'!$A$4:$A$63,0)),"")) -> 6500 | V6: =IF($A6="","",IFERROR(INDEX('INVENTORY MASTER'!$AO$4:$AO$63,MATCH($A6,'INVENTORY MASTER'!$A$4:$A$63,0)),"")) -> 6500 | W6: =IF($A6="","",IFERROR(INDEX('INVENTORY MASTER'!$AS$4:$AS$63,MATCH($A6,'INVENTORY MASTER'!$A$4:$A$63,0)),"")) -> With Partner | X6: =IF($A6="","",IFERROR(INDEX('INVENTORY MASTER'!$AR$4:$AR$63,MATCH($A6,'INVENTORY MASTER'!$A$4:$A$63,0)),"")) -> Partner 3
B7: =IF($A7="","",IFERROR(INDEX('INVENTORY MASTER'!$G$4:$G$63,MATCH($A7,'INVENTORY MASTER'!$A$4:$A$63,0)),"")) | C7: =IF($A7="","",IFERROR(INDEX('INVENTORY MASTER'!$H$4:$H$63,MATCH($A7,'INVENTORY MASTER'!$A$4:$A$63,0)),"")) | D7: =IF($A7="","",IFERROR(INDEX('INVENTORY MASTER'!$I$4:$I$63,MATCH($A7,'INVENTORY MASTER'!$A$4:$A$63,0)),"")) | E7: =IF($A7="","",IFERROR(INDEX('INVENTORY MASTER'!$J$4:$J$63,MATCH($A7,'INVENTORY MASTER'!$A$4:$A$63,0)),"")) | F7: =IF($A7="","",IFERROR(INDEX('INVENTORY MASTER'!$V$4:$V$63,MATCH($A7,'INVENTORY MASTER'!$A$4:$A$63,0)),"")) | G7: =IF($A7="","",IFERROR(INDEX('INVENTORY MASTER'!$T$4:$T$63,MATCH($A7,'INVENTORY MASTER'!$A$4:$A$63,0)),"")) | K7: =IF($A7="","",IFERROR(INDEX('INVENTORY MASTER'!$U$4:$U$63,MATCH($A7,'INVENTORY MASTER'!$A$4:$A$63,0)),"")) | L7: =IF($A7="","",IFERROR(INDEX('INVENTORY MASTER'!$U$4:$U$63,MATCH($A7,'INVENTORY MASTER'!$A$4:$A$63,0)),"")) | M7: =IF($A7="","",IFERROR(INDEX('INVENTORY MASTER'!$W$4:$W$63,MATCH($A7,'INVENTORY MASTER'!$A$4:$A$63,0)),"")) | N7: =IF($A7="","",IFERROR(INDEX('INVENTORY MASTER'!$X$4:$X$63,MATCH($A7,'INVENTORY MASTER'!$A$4:$A$63,0)),"")) | O7: =IF($A7="","",IFERROR(INDEX('INVENTORY MASTER'!$Y$4:$Y$63,MATCH($A7,'INVENTORY MASTER'!$A$4:$A$63,0)),"")) | S7: =IF($A7="","",IFERROR(INDEX('INVENTORY MASTER'!$Z$4:$Z$63,MATCH($A7,'INVENTORY MASTER'!$A$4:$A$63,0)),"")) | T7: =IF($A7="","",IFERROR(INDEX('INVENTORY MASTER'!$AI$4:$AI$63,MATCH($A7,'INVENTORY MASTER'!$A$4:$A$63,0)),"")) | U7: =IF($A7="","",IFERROR(INDEX('INVENTORY MASTER'!$AM$4:$AM$63,MATCH($A7,'INVENTORY MASTER'!$A$4:$A$63,0)),"")) | V7: =IF($A7="","",IFERROR(INDEX('INVENTORY MASTER'!$AO$4:$AO$63,MATCH($A7,'INVENTORY MASTER'!$A$4:$A$63,0)),"")) | W7: =IF($A7="","",IFERROR(INDEX('INVENTORY MASTER'!$AS$4:$AS$63,MATCH($A7,'INVENTORY MASTER'!$A$4:$A$63,0)),"")) | X7: =IF($A7="","",IFERROR(INDEX('INVENTORY MASTER'!$AR$4:$AR$63,MATCH($A7,'INVENTORY MASTER'!$A$4:$A$63,0)),""))
B8: =IF($A8="","",IFERROR(INDEX('INVENTORY MASTER'!$G$4:$G$63,MATCH($A8,'INVENTORY MASTER'!$A$4:$A$63,0)),"")) | C8: =IF($A8="","",IFERROR(INDEX('INVENTORY MASTER'!$H$4:$H$63,MATCH($A8,'INVENTORY MASTER'!$A$4:$A$63,0)),"")) | D8: =IF($A8="","",IFERROR(INDEX('INVENTORY MASTER'!$I$4:$I$63,MATCH($A8,'INVENTORY MASTER'!$A$4:$A$63,0)),"")) | E8: =IF($A8="","",IFERROR(INDEX('INVENTORY MASTER'!$J$4:$J$63,MATCH($A8,'INVENTORY MASTER'!$A$4:$A$63,0)),"")) | F8: =IF($A8="","",IFERROR(INDEX('INVENTORY MASTER'!$V$4:$V$63,MATCH($A8,'INVENTORY MASTER'!$A$4:$A$63,0)),"")) | G8: =IF($A8="","",IFERROR(INDEX('INVENTORY MASTER'!$T$4:$T$63,MATCH($A8,'INVENTORY MASTER'!$A$4:$A$63,0)),"")) | K8: =IF($A8="","",IFERROR(INDEX('INVENTORY MASTER'!$U$4:$U$63,MATCH($A8,'INVENTORY MASTER'!$A$4:$A$63,0)),"")) | L8: =IF($A8="","",IFERROR(INDEX('INVENTORY MASTER'!$U$4:$U$63,MATCH($A8,'INVENTORY MASTER'!$A$4:$A$63,0)),"")) | M8: =IF($A8="","",IFERROR(INDEX('INVENTORY MASTER'!$W$4:$W$63,MATCH($A8,'INVENTORY MASTER'!$A$4:$A$63,0)),"")) | N8: =IF($A8="","",IFERROR(INDEX('INVENTORY MASTER'!$X$4:$X$63,MATCH($A8,'INVENTORY MASTER'!$A$4:$A$63,0)),"")) | O8: =IF($A8="","",IFERROR(INDEX('INVENTORY MASTER'!$Y$4:$Y$63,MATCH($A8,'INVENTORY MASTER'!$A$4:$A$63,0)),"")) | S8: =IF($A8="","",IFERROR(INDEX('INVENTORY MASTER'!$Z$4:$Z$63,MATCH($A8,'INVENTORY MASTER'!$A$4:$A$63,0)),"")) | T8: =IF($A8="","",IFERROR(INDEX('INVENTORY MASTER'!$AI$4:$AI$63,MATCH($A8,'INVENTORY MASTER'!$A$4:$A$63,0)),"")) | U8: =IF($A8="","",IFERROR(INDEX('INVENTORY MASTER'!$AM$4:$AM$63,MATCH($A8,'INVENTORY MASTER'!$A$4:$A$63,0)),"")) | V8: =IF($A8="","",IFERROR(INDEX('INVENTORY MASTER'!$AO$4:$AO$63,MATCH($A8,'INVENTORY MASTER'!$A$4:$A$63,0)),"")) | W8: =IF($A8="","",IFERROR(INDEX('INVENTORY MASTER'!$AS$4:$AS$63,MATCH($A8,'INVENTORY MASTER'!$A$4:$A$63,0)),"")) | X8: =IF($A8="","",IFERROR(INDEX('INVENTORY MASTER'!$AR$4:$AR$63,MATCH($A8,'INVENTORY MASTER'!$A$4:$A$63,0)),""))
B9: =IF($A9="","",IFERROR(INDEX('INVENTORY MASTER'!$G$4:$G$63,MATCH($A9,'INVENTORY MASTER'!$A$4:$A$63,0)),"")) | C9: =IF($A9="","",IFERROR(INDEX('INVENTORY MASTER'!$H$4:$H$63,MATCH($A9,'INVENTORY MASTER'!$A$4:$A$63,0)),"")) | D9: =IF($A9="","",IFERROR(INDEX('INVENTORY MASTER'!$I$4:$I$63,MATCH($A9,'INVENTORY MASTER'!$A$4:$A$63,0)),"")) | E9: =IF($A9="","",IFERROR(INDEX('INVENTORY MASTER'!$J$4:$J$63,MATCH($A9,'INVENTORY MASTER'!$A$4:$A$63,0)),"")) | F9: =IF($A9="","",IFERROR(INDEX('INVENTORY MASTER'!$V$4:$V$63,MATCH($A9,'INVENTORY MASTER'!$A$4:$A$63,0)),"")) | G9: =IF($A9="","",IFERROR(INDEX('INVENTORY MASTER'!$T$4:$T$63,MATCH($A9,'INVENTORY MASTER'!$A$4:$A$63,0)),"")) | K9: =IF($A9="","",IFERROR(INDEX('INVENTORY MASTER'!$U$4:$U$63,MATCH($A9,'INVENTORY MASTER'!$A$4:$A$63,0)),"")) | L9: =IF($A9="","",IFERROR(INDEX('INVENTORY MASTER'!$U$4:$U$63,MATCH($A9,'INVENTORY MASTER'!$A$4:$A$63,0)),"")) | M9: =IF($A9="","",IFERROR(INDEX('INVENTORY MASTER'!$W$4:$W$63,MATCH($A9,'INVENTORY MASTER'!$A$4:$A$63,0)),"")) | N9: =IF($A9="","",IFERROR(INDEX('INVENTORY MASTER'!$X$4:$X$63,MATCH($A9,'INVENTORY MASTER'!$A$4:$A$63,0)),"")) | O9: =IF($A9="","",IFERROR(INDEX('INVENTORY MASTER'!$Y$4:$Y$63,MATCH($A9,'INVENTORY MASTER'!$A$4:$A$63,0)),"")) | S9: =IF($A9="","",IFERROR(INDEX('INVENTORY MASTER'!$Z$4:$Z$63,MATCH($A9,'INVENTORY MASTER'!$A$4:$A$63,0)),"")) | T9: =IF($A9="","",IFERROR(INDEX('INVENTORY MASTER'!$AI$4:$AI$63,MATCH($A9,'INVENTORY MASTER'!$A$4:$A$63,0)),"")) | U9: =IF($A9="","",IFERROR(INDEX('INVENTORY MASTER'!$AM$4:$AM$63,MATCH($A9,'INVENTORY MASTER'!$A$4:$A$63,0)),"")) | V9: =IF($A9="","",IFERROR(INDEX('INVENTORY MASTER'!$AO$4:$AO$63,MATCH($A9,'INVENTORY MASTER'!$A$4:$A$63,0)),"")) | W9: =IF($A9="","",IFERROR(INDEX('INVENTORY MASTER'!$AS$4:$AS$63,MATCH($A9,'INVENTORY MASTER'!$A$4:$A$63,0)),"")) | X9: =IF($A9="","",IFERROR(INDEX('INVENTORY MASTER'!$AR$4:$AR$63,MATCH($A9,'INVENTORY MASTER'!$A$4:$A$63,0)),""))
B10: =IF($A10="","",IFERROR(INDEX('INVENTORY MASTER'!$G$4:$G$63,MATCH($A10,'INVENTORY MASTER'!$A$4:$A$63,0)),"")) | C10: =IF($A10="","",IFERROR(INDEX('INVENTORY MASTER'!$H$4:$H$63,MATCH($A10,'INVENTORY MASTER'!$A$4:$A$63,0)),"")) | D10: =IF($A10="","",IFERROR(INDEX('INVENTORY MASTER'!$I$4:$I$63,MATCH($A10,'INVENTORY MASTER'!$A$4:$A$63,0)),"")) | E10: =IF($A10="","",IFERROR(INDEX('INVENTORY MASTER'!$J$4:$J$63,MATCH($A10,'INVENTORY MASTER'!$A$4:$A$63,0)),"")) | F10: =IF($A10="","",IFERROR(INDEX('INVENTORY MASTER'!$V$4:$V$63,MATCH($A10,'INVENTORY MASTER'!$A$4:$A$63,0)),"")) | G10: =IF($A10="","",IFERROR(INDEX('INVENTORY MASTER'!$T$4:$T$63,MATCH($A10,'INVENTORY MASTER'!$A$4:$A$63,0)),"")) | K10: =IF($A10="","",IFERROR(INDEX('INVENTORY MASTER'!$U$4:$U$63,MATCH($A10,'INVENTORY MASTER'!$A$4:$A$63,0)),"")) | L10: =IF($A10="","",IFERROR(INDEX('INVENTORY MASTER'!$U$4:$U$63,MATCH($A10,'INVENTORY MASTER'!$A$4:$A$63,0)),"")) | M10: =IF($A10="","",IFERROR(INDEX('INVENTORY MASTER'!$W$4:$W$63,MATCH($A10,'INVENTORY MASTER'!$A$4:$A$63,0)),"")) | N10: =IF($A10="","",IFERROR(INDEX('INVENTORY MASTER'!$X$4:$X$63,MATCH($A10,'INVENTORY MASTER'!$A$4:$A$63,0)),"")) | O10: =IF($A10="","",IFERROR(INDEX('INVENTORY MASTER'!$Y$4:$Y$63,MATCH($A10,'INVENTORY MASTER'!$A$4:$A$63,0)),"")) | S10: =IF($A10="","",IFERROR(INDEX('INVENTORY MASTER'!$Z$4:$Z$63,MATCH($A10,'INVENTORY MASTER'!$A$4:$A$63,0)),"")) | T10: =IF($A10="","",IFERROR(INDEX('INVENTORY MASTER'!$AI$4:$AI$63,MATCH($A10,'INVENTORY MASTER'!$A$4:$A$63,0)),"")) | U10: =IF($A10="","",IFERROR(INDEX('INVENTORY MASTER'!$AM$4:$AM$63,MATCH($A10,'INVENTORY MASTER'!$A$4:$A$63,0)),"")) | V10: =IF($A10="","",IFERROR(INDEX('INVENTORY MASTER'!$AO$4:$AO$63,MATCH($A10,'INVENTORY MASTER'!$A$4:$A$63,0)),"")) | W10: =IF($A10="","",IFERROR(INDEX('INVENTORY MASTER'!$AS$4:$AS$63,MATCH($A10,'INVENTORY MASTER'!$A$4:$A$63,0)),"")) | X10: =IF($A10="","",IFERROR(INDEX('INVENTORY MASTER'!$AR$4:$AR$63,MATCH($A10,'INVENTORY MASTER'!$A$4:$A$63,0)),""))
B11: =IF($A11="","",IFERROR(INDEX('INVENTORY MASTER'!$G$4:$G$63,MATCH($A11,'INVENTORY MASTER'!$A$4:$A$63,0)),"")) | C11: =IF($A11="","",IFERROR(INDEX('INVENTORY MASTER'!$H$4:$H$63,MATCH($A11,'INVENTORY MASTER'!$A$4:$A$63,0)),"")) | D11: =IF($A11="","",IFERROR(INDEX('INVENTORY MASTER'!$I$4:$I$63,MATCH($A11,'INVENTORY MASTER'!$A$4:$A$63,0)),"")) | E11: =IF($A11="","",IFERROR(INDEX('INVENTORY MASTER'!$J$4:$J$63,MATCH($A11,'INVENTORY MASTER'!$A$4:$A$63,0)),"")) | F11: =IF($A11="","",IFERROR(INDEX('INVENTORY MASTER'!$V$4:$V$63,MATCH($A11,'INVENTORY MASTER'!$A$4:$A$63,0)),"")) | G11: =IF($A11="","",IFERROR(INDEX('INVENTORY MASTER'!$T$4:$T$63,MATCH($A11,'INVENTORY MASTER'!$A$4:$A$63,0)),"")) | K11: =IF($A11="","",IFERROR(INDEX('INVENTORY MASTER'!$U$4:$U$63,MATCH($A11,'INVENTORY MASTER'!$A$4:$A$63,0)),"")) | L11: =IF($A11="","",IFERROR(INDEX('INVENTORY MASTER'!$U$4:$U$63,MATCH($A11,'INVENTORY MASTER'!$A$4:$A$63,0)),"")) | M11: =IF($A11="","",IFERROR(INDEX('INVENTORY MASTER'!$W$4:$W$63,MATCH($A11,'INVENTORY MASTER'!$A$4:$A$63,0)),"")) | N11: =IF($A11="","",IFERROR(INDEX('INVENTORY MASTER'!$X$4:$X$63,MATCH($A11,'INVENTORY MASTER'!$A$4:$A$63,0)),"")) | O11: =IF($A11="","",IFERROR(INDEX('INVENTORY MASTER'!$Y$4:$Y$63,MATCH($A11,'INVENTORY MASTER'!$A$4:$A$63,0)),"")) | S11: =IF($A11="","",IFERROR(INDEX('INVENTORY MASTER'!$Z$4:$Z$63,MATCH($A11,'INVENTORY MASTER'!$A$4:$A$63,0)),"")) | T11: =IF($A11="","",IFERROR(INDEX('INVENTORY MASTER'!$AI$4:$AI$63,MATCH($A11,'INVENTORY MASTER'!$A$4:$A$63,0)),"")) | U11: =IF($A11="","",IFERROR(INDEX('INVENTORY MASTER'!$AM$4:$AM$63,MATCH($A11,'INVENTORY MASTER'!$A$4:$A$63,0)),"")) | V11: =IF($A11="","",IFERROR(INDEX('INVENTORY MASTER'!$AO$4:$AO$63,MATCH($A11,'INVENTORY MASTER'!$A$4:$A$63,0)),"")) | W11: =IF($A11="","",IFERROR(INDEX('INVENTORY MASTER'!$AS$4:$AS$63,MATCH($A11,'INVENTORY MASTER'!$A$4:$A$63,0)),"")) | X11: =IF($A11="","",IFERROR(INDEX('INVENTORY MASTER'!$AR$4:$AR$63,MATCH($A11,'INVENTORY MASTER'!$A$4:$A$63,0)),""))
B12: =IF($A12="","",IFERROR(INDEX('INVENTORY MASTER'!$G$4:$G$63,MATCH($A12,'INVENTORY MASTER'!$A$4:$A$63,0)),"")) | C12: =IF($A12="","",IFERROR(INDEX('INVENTORY MASTER'!$H$4:$H$63,MATCH($A12,'INVENTORY MASTER'!$A$4:$A$63,0)),"")) | D12: =IF($A12="","",IFERROR(INDEX('INVENTORY MASTER'!$I$4:$I$63,MATCH($A12,'INVENTORY MASTER'!$A$4:$A$63,0)),"")) | E12: =IF($A12="","",IFERROR(INDEX('INVENTORY MASTER'!$J$4:$J$63,MATCH($A12,'INVENTORY MASTER'!$A$4:$A$63,0)),"")) | F12: =IF($A12="","",IFERROR(INDEX('INVENTORY MASTER'!$V$4:$V$63,MATCH($A12,'INVENTORY MASTER'!$A$4:$A$63,0)),"")) | G12: =IF($A12="","",IFERROR(INDEX('INVENTORY MASTER'!$T$4:$T$63,MATCH($A12,'INVENTORY MASTER'!$A$4:$A$63,0)),"")) | K12: =IF($A12="","",IFERROR(INDEX('INVENTORY MASTER'!$U$4:$U$63,MATCH($A12,'INVENTORY MASTER'!$A$4:$A$63,0)),"")) | L12: =IF($A12="","",IFERROR(INDEX('INVENTORY MASTER'!$U$4:$U$63,MATCH($A12,'INVENTORY MASTER'!$A$4:$A$63,0)),"")) | M12: =IF($A12="","",IFERROR(INDEX('INVENTORY MASTER'!$W$4:$W$63,MATCH($A12,'INVENTORY MASTER'!$A$4:$A$63,0)),"")) | N12: =IF($A12="","",IFERROR(INDEX('INVENTORY MASTER'!$X$4:$X$63,MATCH($A12,'INVENTORY MASTER'!$A$4:$A$63,0)),"")) | O12: =IF($A12="","",IFERROR(INDEX('INVENTORY MASTER'!$Y$4:$Y$63,MATCH($A12,'INVENTORY MASTER'!$A$4:$A$63,0)),"")) | S12: =IF($A12="","",IFERROR(INDEX('INVENTORY MASTER'!$Z$4:$Z$63,MATCH($A12,'INVENTORY MASTER'!$A$4:$A$63,0)),"")) | T12: =IF($A12="","",IFERROR(INDEX('INVENTORY MASTER'!$AI$4:$AI$63,MATCH($A12,'INVENTORY MASTER'!$A$4:$A$63,0)),"")) | U12: =IF($A12="","",IFERROR(INDEX('INVENTORY MASTER'!$AM$4:$AM$63,MATCH($A12,'INVENTORY MASTER'!$A$4:$A$63,0)),"")) | V12: =IF($A12="","",IFERROR(INDEX('INVENTORY MASTER'!$AO$4:$AO$63,MATCH($A12,'INVENTORY MASTER'!$A$4:$A$63,0)),"")) | W12: =IF($A12="","",IFERROR(INDEX('INVENTORY MASTER'!$AS$4:$AS$63,MATCH($A12,'INVENTORY MASTER'!$A$4:$A$63,0)),"")) | X12: =IF($A12="","",IFERROR(INDEX('INVENTORY MASTER'!$AR$4:$AR$63,MATCH($A12,'INVENTORY MASTER'!$A$4:$A$63,0)),""))
B13: =IF($A13="","",IFERROR(INDEX('INVENTORY MASTER'!$G$4:$G$63,MATCH($A13,'INVENTORY MASTER'!$A$4:$A$63,0)),"")) | C13: =IF($A13="","",IFERROR(INDEX('INVENTORY MASTER'!$H$4:$H$63,MATCH($A13,'INVENTORY MASTER'!$A$4:$A$63,0)),"")) | D13: =IF($A13="","",IFERROR(INDEX('INVENTORY MASTER'!$I$4:$I$63,MATCH($A13,'INVENTORY MASTER'!$A$4:$A$63,0)),"")) | E13: =IF($A13="","",IFERROR(INDEX('INVENTORY MASTER'!$J$4:$J$63,MATCH($A13,'INVENTORY MASTER'!$A$4:$A$63,0)),"")) | F13: =IF($A13="","",IFERROR(INDEX('INVENTORY MASTER'!$V$4:$V$63,MATCH($A13,'INVENTORY MASTER'!$A$4:$A$63,0)),"")) | G13: =IF($A13="","",IFERROR(INDEX('INVENTORY MASTER'!$T$4:$T$63,MATCH($A13,'INVENTORY MASTER'!$A$4:$A$63,0)),"")) | K13: =IF($A13="","",IFERROR(INDEX('INVENTORY MASTER'!$U$4:$U$63,MATCH($A13,'INVENTORY MASTER'!$A$4:$A$63,0)),"")) | L13: =IF($A13="","",IFERROR(INDEX('INVENTORY MASTER'!$U$4:$U$63,MATCH($A13,'INVENTORY MASTER'!$A$4:$A$63,0)),"")) | M13: =IF($A13="","",IFERROR(INDEX('INVENTORY MASTER'!$W$4:$W$63,MATCH($A13,'INVENTORY MASTER'!$A$4:$A$63,0)),"")) | N13: =IF($A13="","",IFERROR(INDEX('INVENTORY MASTER'!$X$4:$X$63,MATCH($A13,'INVENTORY MASTER'!$A$4:$A$63,0)),"")) | O13: =IF($A13="","",IFERROR(INDEX('INVENTORY MASTER'!$Y$4:$Y$63,MATCH($A13,'INVENTORY MASTER'!$A$4:$A$63,0)),"")) | S13: =IF($A13="","",IFERROR(INDEX('INVENTORY MASTER'!$Z$4:$Z$63,MATCH($A13,'INVENTORY MASTER'!$A$4:$A$63,0)),"")) | T13: =IF($A13="","",IFERROR(INDEX('INVENTORY MASTER'!$AI$4:$AI$63,MATCH($A13,'INVENTORY MASTER'!$A$4:$A$63,0)),"")) | U13: =IF($A13="","",IFERROR(INDEX('INVENTORY MASTER'!$AM$4:$AM$63,MATCH($A13,'INVENTORY MASTER'!$A$4:$A$63,0)),"")) | V13: =IF($A13="","",IFERROR(INDEX('INVENTORY MASTER'!$AO$4:$AO$63,MATCH($A13,'INVENTORY MASTER'!$A$4:$A$63,0)),"")) | W13: =IF($A13="","",IFERROR(INDEX('INVENTORY MASTER'!$AS$4:$AS$63,MATCH($A13,'INVENTORY MASTER'!$A$4:$A$63,0)),"")) | X13: =IF($A13="","",IFERROR(INDEX('INVENTORY MASTER'!$AR$4:$AR$63,MATCH($A13,'INVENTORY MASTER'!$A$4:$A$63,0)),""))
B14: =IF($A14="","",IFERROR(INDEX('INVENTORY MASTER'!$G$4:$G$63,MATCH($A14,'INVENTORY MASTER'!$A$4:$A$63,0)),"")) | C14: =IF($A14="","",IFERROR(INDEX('INVENTORY MASTER'!$H$4:$H$63,MATCH($A14,'INVENTORY MASTER'!$A$4:$A$63,0)),"")) | D14: =IF($A14="","",IFERROR(INDEX('INVENTORY MASTER'!$I$4:$I$63,MATCH($A14,'INVENTORY MASTER'!$A$4:$A$63,0)),"")) | E14: =IF($A14="","",IFERROR(INDEX('INVENTORY MASTER'!$J$4:$J$63,MATCH($A14,'INVENTORY MASTER'!$A$4:$A$63,0)),"")) | F14: =IF($A14="","",IFERROR(INDEX('INVENTORY MASTER'!$V$4:$V$63,MATCH($A14,'INVENTORY MASTER'!$A$4:$A$63,0)),"")) | G14: =IF($A14="","",IFERROR(INDEX('INVENTORY MASTER'!$T$4:$T$63,MATCH($A14,'INVENTORY MASTER'!$A$4:$A$63,0)),"")) | K14: =IF($A14="","",IFERROR(INDEX('INVENTORY MASTER'!$U$4:$U$63,MATCH($A14,'INVENTORY MASTER'!$A$4:$A$63,0)),"")) | L14: =IF($A14="","",IFERROR(INDEX('INVENTORY MASTER'!$U$4:$U$63,MATCH($A14,'INVENTORY MASTER'!$A$4:$A$63,0)),"")) | M14: =IF($A14="","",IFERROR(INDEX('INVENTORY MASTER'!$W$4:$W$63,MATCH($A14,'INVENTORY MASTER'!$A$4:$A$63,0)),"")) | N14: =IF($A14="","",IFERROR(INDEX('INVENTORY MASTER'!$X$4:$X$63,MATCH($A14,'INVENTORY MASTER'!$A$4:$A$63,0)),"")) | O14: =IF($A14="","",IFERROR(INDEX('INVENTORY MASTER'!$Y$4:$Y$63,MATCH($A14,'INVENTORY MASTER'!$A$4:$A$63,0)),"")) | S14: =IF($A14="","",IFERROR(INDEX('INVENTORY MASTER'!$Z$4:$Z$63,MATCH($A14,'INVENTORY MASTER'!$A$4:$A$63,0)),"")) | T14: =IF($A14="","",IFERROR(INDEX('INVENTORY MASTER'!$AI$4:$AI$63,MATCH($A14,'INVENTORY MASTER'!$A$4:$A$63,0)),"")) | U14: =IF($A14="","",IFERROR(INDEX('INVENTORY MASTER'!$AM$4:$AM$63,MATCH($A14,'INVENTORY MASTER'!$A$4:$A$63,0)),"")) | V14: =IF($A14="","",IFERROR(INDEX('INVENTORY MASTER'!$AO$4:$AO$63,MATCH($A14,'INVENTORY MASTER'!$A$4:$A$63,0)),"")) | W14: =IF($A14="","",IFERROR(INDEX('INVENTORY MASTER'!$AS$4:$AS$63,MATCH($A14,'INVENTORY MASTER'!$A$4:$A$63,0)),"")) | X14: =IF($A14="","",IFERROR(INDEX('INVENTORY MASTER'!$AR$4:$AR$63,MATCH($A14,'INVENTORY MASTER'!$A$4:$A$63,0)),""))
B15: =IF($A15="","",IFERROR(INDEX('INVENTORY MASTER'!$G$4:$G$63,MATCH($A15,'INVENTORY MASTER'!$A$4:$A$63,0)),"")) | C15: =IF($A15="","",IFERROR(INDEX('INVENTORY MASTER'!$H$4:$H$63,MATCH($A15,'INVENTORY MASTER'!$A$4:$A$63,0)),"")) | D15: =IF($A15="","",IFERROR(INDEX('INVENTORY MASTER'!$I$4:$I$63,MATCH($A15,'INVENTORY MASTER'!$A$4:$A$63,0)),"")) | E15: =IF($A15="","",IFERROR(INDEX('INVENTORY MASTER'!$J$4:$J$63,MATCH($A15,'INVENTORY MASTER'!$A$4:$A$63,0)),"")) | F15: =IF($A15="","",IFERROR(INDEX('INVENTORY MASTER'!$V$4:$V$63,MATCH($A15,'INVENTORY MASTER'!$A$4:$A$63,0)),"")) | G15: =IF($A15="","",IFERROR(INDEX('INVENTORY MASTER'!$T$4:$T$63,MATCH($A15,'INVENTORY MASTER'!$A$4:$A$63,0)),"")) | K15: =IF($A15="","",IFERROR(INDEX('INVENTORY MASTER'!$U$4:$U$63,MATCH($A15,'INVENTORY MASTER'!$A$4:$A$63,0)),"")) | L15: =IF($A15="","",IFERROR(INDEX('INVENTORY MASTER'!$U$4:$U$63,MATCH($A15,'INVENTORY MASTER'!$A$4:$A$63,0)),"")) | M15: =IF($A15="","",IFERROR(INDEX('INVENTORY MASTER'!$W$4:$W$63,MATCH($A15,'INVENTORY MASTER'!$A$4:$A$63,0)),"")) | N15: =IF($A15="","",IFERROR(INDEX('INVENTORY MASTER'!$X$4:$X$63,MATCH($A15,'INVENTORY MASTER'!$A$4:$A$63,0)),"")) | O15: =IF($A15="","",IFERROR(INDEX('INVENTORY MASTER'!$Y$4:$Y$63,MATCH($A15,'INVENTORY MASTER'!$A$4:$A$63,0)),"")) | S15: =IF($A15="","",IFERROR(INDEX('INVENTORY MASTER'!$Z$4:$Z$63,MATCH($A15,'INVENTORY MASTER'!$A$4:$A$63,0)),"")) | T15: =IF($A15="","",IFERROR(INDEX('INVENTORY MASTER'!$AI$4:$AI$63,MATCH($A15,'INVENTORY MASTER'!$A$4:$A$63,0)),"")) | U15: =IF($A15="","",IFERROR(INDEX('INVENTORY MASTER'!$AM$4:$AM$63,MATCH($A15,'INVENTORY MASTER'!$A$4:$A$63,0)),"")) | V15: =IF($A15="","",IFERROR(INDEX('INVENTORY MASTER'!$AO$4:$AO$63,MATCH($A15,'INVENTORY MASTER'!$A$4:$A$63,0)),"")) | W15: =IF($A15="","",IFERROR(INDEX('INVENTORY MASTER'!$AS$4:$AS$63,MATCH($A15,'INVENTORY MASTER'!$A$4:$A$63,0)),"")) | X15: =IF($A15="","",IFERROR(INDEX('INVENTORY MASTER'!$AR$4:$AR$63,MATCH($A15,'INVENTORY MASTER'!$A$4:$A$63,0)),""))
B16: =IF($A16="","",IFERROR(INDEX('INVENTORY MASTER'!$G$4:$G$63,MATCH($A16,'INVENTORY MASTER'!$A$4:$A$63,0)),"")) | C16: =IF($A16="","",IFERROR(INDEX('INVENTORY MASTER'!$H$4:$H$63,MATCH($A16,'INVENTORY MASTER'!$A$4:$A$63,0)),"")) | D16: =IF($A16="","",IFERROR(INDEX('INVENTORY MASTER'!$I$4:$I$63,MATCH($A16,'INVENTORY MASTER'!$A$4:$A$63,0)),"")) | E16: =IF($A16="","",IFERROR(INDEX('INVENTORY MASTER'!$J$4:$J$63,MATCH($A16,'INVENTORY MASTER'!$A$4:$A$63,0)),"")) | F16: =IF($A16="","",IFERROR(INDEX('INVENTORY MASTER'!$V$4:$V$63,MATCH($A16,'INVENTORY MASTER'!$A$4:$A$63,0)),"")) | G16: =IF($A16="","",IFERROR(INDEX('INVENTORY MASTER'!$T$4:$T$63,MATCH($A16,'INVENTORY MASTER'!$A$4:$A$63,0)),"")) | K16: =IF($A16="","",IFERROR(INDEX('INVENTORY MASTER'!$U$4:$U$63,MATCH($A16,'INVENTORY MASTER'!$A$4:$A$63,0)),"")) | L16: =IF($A16="","",IFERROR(INDEX('INVENTORY MASTER'!$U$4:$U$63,MATCH($A16,'INVENTORY MASTER'!$A$4:$A$63,0)),"")) | M16: =IF($A16="","",IFERROR(INDEX('INVENTORY MASTER'!$W$4:$W$63,MATCH($A16,'INVENTORY MASTER'!$A$4:$A$63,0)),"")) | N16: =IF($A16="","",IFERROR(INDEX('INVENTORY MASTER'!$X$4:$X$63,MATCH($A16,'INVENTORY MASTER'!$A$4:$A$63,0)),"")) | O16: =IF($A16="","",IFERROR(INDEX('INVENTORY MASTER'!$Y$4:$Y$63,MATCH($A16,'INVENTORY MASTER'!$A$4:$A$63,0)),"")) | S16: =IF($A16="","",IFERROR(INDEX('INVENTORY MASTER'!$Z$4:$Z$63,MATCH($A16,'INVENTORY MASTER'!$A$4:$A$63,0)),"")) | T16: =IF($A16="","",IFERROR(INDEX('INVENTORY MASTER'!$AI$4:$AI$63,MATCH($A16,'INVENTORY MASTER'!$A$4:$A$63,0)),"")) | U16: =IF($A16="","",IFERROR(INDEX('INVENTORY MASTER'!$AM$4:$AM$63,MATCH($A16,'INVENTORY MASTER'!$A$4:$A$63,0)),"")) | V16: =IF($A16="","",IFERROR(INDEX('INVENTORY MASTER'!$AO$4:$AO$63,MATCH($A16,'INVENTORY MASTER'!$A$4:$A$63,0)),"")) | W16: =IF($A16="","",IFERROR(INDEX('INVENTORY MASTER'!$AS$4:$AS$63,MATCH($A16,'INVENTORY MASTER'!$A$4:$A$63,0)),"")) | X16: =IF($A16="","",IFERROR(INDEX('INVENTORY MASTER'!$AR$4:$AR$63,MATCH($A16,'INVENTORY MASTER'!$A$4:$A$63,0)),""))
B17: =IF($A17="","",IFERROR(INDEX('INVENTORY MASTER'!$G$4:$G$63,MATCH($A17,'INVENTORY MASTER'!$A$4:$A$63,0)),"")) | C17: =IF($A17="","",IFERROR(INDEX('INVENTORY MASTER'!$H$4:$H$63,MATCH($A17,'INVENTORY MASTER'!$A$4:$A$63,0)),"")) | D17: =IF($A17="","",IFERROR(INDEX('INVENTORY MASTER'!$I$4:$I$63,MATCH($A17,'INVENTORY MASTER'!$A$4:$A$63,0)),"")) | E17: =IF($A17="","",IFERROR(INDEX('INVENTORY MASTER'!$J$4:$J$63,MATCH($A17,'INVENTORY MASTER'!$A$4:$A$63,0)),"")) | F17: =IF($A17="","",IFERROR(INDEX('INVENTORY MASTER'!$V$4:$V$63,MATCH($A17,'INVENTORY MASTER'!$A$4:$A$63,0)),"")) | G17: =IF($A17="","",IFERROR(INDEX('INVENTORY MASTER'!$T$4:$T$63,MATCH($A17,'INVENTORY MASTER'!$A$4:$A$63,0)),"")) | K17: =IF($A17="","",IFERROR(INDEX('INVENTORY MASTER'!$U$4:$U$63,MATCH($A17,'INVENTORY MASTER'!$A$4:$A$63,0)),"")) | L17: =IF($A17="","",IFERROR(INDEX('INVENTORY MASTER'!$U$4:$U$63,MATCH($A17,'INVENTORY MASTER'!$A$4:$A$63,0)),"")) | M17: =IF($A17="","",IFERROR(INDEX('INVENTORY MASTER'!$W$4:$W$63,MATCH($A17,'INVENTORY MASTER'!$A$4:$A$63,0)),"")) | N17: =IF($A17="","",IFERROR(INDEX('INVENTORY MASTER'!$X$4:$X$63,MATCH($A17,'INVENTORY MASTER'!$A$4:$A$63,0)),"")) | O17: =IF($A17="","",IFERROR(INDEX('INVENTORY MASTER'!$Y$4:$Y$63,MATCH($A17,'INVENTORY MASTER'!$A$4:$A$63,0)),"")) | S17: =IF($A17="","",IFERROR(INDEX('INVENTORY MASTER'!$Z$4:$Z$63,MATCH($A17,'INVENTORY MASTER'!$A$4:$A$63,0)),"")) | T17: =IF($A17="","",IFERROR(INDEX('INVENTORY MASTER'!$AI$4:$AI$63,MATCH($A17,'INVENTORY MASTER'!$A$4:$A$63,0)),"")) | U17: =IF($A17="","",IFERROR(INDEX('INVENTORY MASTER'!$AM$4:$AM$63,MATCH($A17,'INVENTORY MASTER'!$A$4:$A$63,0)),"")) | V17: =IF($A17="","",IFERROR(INDEX('INVENTORY MASTER'!$AO$4:$AO$63,MATCH($A17,'INVENTORY MASTER'!$A$4:$A$63,0)),"")) | W17: =IF($A17="","",IFERROR(INDEX('INVENTORY MASTER'!$AS$4:$AS$63,MATCH($A17,'INVENTORY MASTER'!$A$4:$A$63,0)),"")) | X17: =IF($A17="","",IFERROR(INDEX('INVENTORY MASTER'!$AR$4:$AR$63,MATCH($A17,'INVENTORY MASTER'!$A$4:$A$63,0)),""))
B18: =IF($A18="","",IFERROR(INDEX('INVENTORY MASTER'!$G$4:$G$63,MATCH($A18,'INVENTORY MASTER'!$A$4:$A$63,0)),"")) | C18: =IF($A18="","",IFERROR(INDEX('INVENTORY MASTER'!$H$4:$H$63,MATCH($A18,'INVENTORY MASTER'!$A$4:$A$63,0)),"")) | D18: =IF($A18="","",IFERROR(INDEX('INVENTORY MASTER'!$I$4:$I$63,MATCH($A18,'INVENTORY MASTER'!$A$4:$A$63,0)),"")) | E18: =IF($A18="","",IFERROR(INDEX('INVENTORY MASTER'!$J$4:$J$63,MATCH($A18,'INVENTORY MASTER'!$A$4:$A$63,0)),"")) | F18: =IF($A18="","",IFERROR(INDEX('INVENTORY MASTER'!$V$4:$V$63,MATCH($A18,'INVENTORY MASTER'!$A$4:$A$63,0)),"")) | G18: =IF($A18="","",IFERROR(INDEX('INVENTORY MASTER'!$T$4:$T$63,MATCH($A18,'INVENTORY MASTER'!$A$4:$A$63,0)),"")) | K18: =IF($A18="","",IFERROR(INDEX('INVENTORY MASTER'!$U$4:$U$63,MATCH($A18,'INVENTORY MASTER'!$A$4:$A$63,0)),"")) | L18: =IF($A18="","",IFERROR(INDEX('INVENTORY MASTER'!$U$4:$U$63,MATCH($A18,'INVENTORY MASTER'!$A$4:$A$63,0)),"")) | M18: =IF($A18="","",IFERROR(INDEX('INVENTORY MASTER'!$W$4:$W$63,MATCH($A18,'INVENTORY MASTER'!$A$4:$A$63,0)),"")) | N18: =IF($A18="","",IFERROR(INDEX('INVENTORY MASTER'!$X$4:$X$63,MATCH($A18,'INVENTORY MASTER'!$A$4:$A$63,0)),"")) | O18: =IF($A18="","",IFERROR(INDEX('INVENTORY MASTER'!$Y$4:$Y$63,MATCH($A18,'INVENTORY MASTER'!$A$4:$A$63,0)),"")) | S18: =IF($A18="","",IFERROR(INDEX('INVENTORY MASTER'!$Z$4:$Z$63,MATCH($A18,'INVENTORY MASTER'!$A$4:$A$63,0)),"")) | T18: =IF($A18="","",IFERROR(INDEX('INVENTORY MASTER'!$AI$4:$AI$63,MATCH($A18,'INVENTORY MASTER'!$A$4:$A$63,0)),"")) | U18: =IF($A18="","",IFERROR(INDEX('INVENTORY MASTER'!$AM$4:$AM$63,MATCH($A18,'INVENTORY MASTER'!$A$4:$A$63,0)),"")) | V18: =IF($A18="","",IFERROR(INDEX('INVENTORY MASTER'!$AO$4:$AO$63,MATCH($A18,'INVENTORY MASTER'!$A$4:$A$63,0)),"")) | W18: =IF($A18="","",IFERROR(INDEX('INVENTORY MASTER'!$AS$4:$AS$63,MATCH($A18,'INVENTORY MASTER'!$A$4:$A$63,0)),"")) | X18: =IF($A18="","",IFERROR(INDEX('INVENTORY MASTER'!$AR$4:$AR$63,MATCH($A18,'INVENTORY MASTER'!$A$4:$A$63,0)),""))
... B43: =IF($A43="","",IFERROR(INDEX('INVENTORY MASTER'!$G$4:$G$63,MATCH($A43,'INVENTORY MASTER'!$A$4:$A$63,0)),"")) | C43: =IF($A43="","",IFERROR(INDEX('INVENTORY MASTER'!$H$4:$H$63,MATCH($A43,'INVENTORY MASTER'!$A$4:$A$63,0)),"")) | D43: =IF($A43="","",IFERROR(INDEX('INVENTORY MASTER'!$I$4:$I$63,MATCH($A43,'INVENTORY MASTER'!$A$4:$A$63,0)),"")) | E43: =IF($A43="","",IFERROR(INDEX('INVENTORY MASTER'!$J$4:$J$63,MATCH($A43,'INVENTORY MASTER'!$A$4:$A$63,0)),"")) | F43: =IF($A43="","",IFERROR(INDEX('INVENTORY MASTER'!$V$4:$V$63,MATCH($A43,'INVENTORY MASTER'!$A$4:$A$63,0)),"")) | G43: =IF($A43="","",IFERROR(INDEX('INVENTORY MASTER'!$T$4:$T$63,MATCH($A43,'INVENTORY MASTER'!$A$4:$A$63,0)),"")) | K43: =IF($A43="","",IFERROR(INDEX('INVENTORY MASTER'!$U$4:$U$63,MATCH($A43,'INVENTORY MASTER'!$A$4:$A$63,0)),"")) | L43: =IF($A43="","",IFERROR(INDEX('INVENTORY MASTER'!$U$4:$U$63,MATCH($A43,'INVENTORY MASTER'!$A$4:$A$63,0)),"")) | M43: =IF($A43="","",IFERROR(INDEX('INVENTORY MASTER'!$W$4:$W$63,MATCH($A43,'INVENTORY MASTER'!$A$4:$A$63,0)),"")) | N43: =IF($A43="","",IFERROR(INDEX('INVENTORY MASTER'!$X$4:$X$63,MATCH($A43,'INVENTORY MASTER'!$A$4:$A$63,0)),"")) | O43: =IF($A43="","",IFERROR(INDEX('INVENTORY MASTER'!$Y$4:$Y$63,MATCH($A43,'INVENTORY MASTER'!$A$4:$A$63,0)),"")) | S43: =IF($A43="","",IFERROR(INDEX('INVENTORY MASTER'!$Z$4:$Z$63,MATCH($A43,'INVENTORY MASTER'!$A$4:$A$63,0)),"")) | T43: =IF($A43="","",IFERROR(INDEX('INVENTORY MASTER'!$AI$4:$AI$63,MATCH($A43,'INVENTORY MASTER'!$A$4:$A$63,0)),"")) | U43: =IF($A43="","",IFERROR(INDEX('INVENTORY MASTER'!$AM$4:$AM$63,MATCH($A43,'INVENTORY MASTER'!$A$4:$A$63,0)),"")) | V43: =IF($A43="","",IFERROR(INDEX('INVENTORY MASTER'!$AO$4:$AO$63,MATCH($A43,'INVENTORY MASTER'!$A$4:$A$63,0)),"")) | W43: =IF($A43="","",IFERROR(INDEX('INVENTORY MASTER'!$AS$4:$AS$63,MATCH($A43,'INVENTORY MASTER'!$A$4:$A$63,0)),"")) | X43: =IF($A43="","",IFERROR(INDEX('INVENTORY MASTER'!$AR$4:$AR$63,MATCH($A43,'INVENTORY MASTER'!$A$4:$A$63,0)),""))

Sheet JEWELLERY DETAILS
A1: JEWELLERY DETAILS
A2: Jewellery view with a gold calculator. Enter a Stock ID; details pull from Inventory. Enter Gold Rate/g, Stone Cost and Buy/Sell % — Metal Value, Implied Buy Cost & Suggested Sell calculate automatically.
A3: Stock ID | B3: Jewellery Type | C3: Metal | D3: Purity | E3: Weight (g) | F3: Gold Rate (£/g) | G3: Metal Value (£) | H3: Stone | I3: Stone Carat | J3: Stone Cost (£) | K3: Buy Premium % | L3: Implied Buy Cost (£) | M3: Sell Premium % | N3: Suggested Sell (£) | O3: Diamond Colour | P3: Diamond Clarity | Q3: Cut | R3: Certificate Number | S3: Laboratory | T3: Ring Size | U3: Purchase Price | V3: Cost Per Gram | W3: Target Selling Price | X3: Current Selling Price | Y3: Status | Z3: Location | AA3: Notes
A4: JWL-0001 | B4: =IF($A4="","",IFERROR(INDEX('INVENTORY MASTER'!$F$4:$F$63,MATCH($A4,'INVENTORY MASTER'!$A$4:$A$63,0)),"")) -> Solitaire Ring | C4: =IF($A4="","",IFERROR(INDEX('INVENTORY MASTER'!$L$4:$L$63,MATCH($A4,'INVENTORY MASTER'!$A$4:$A$63,0)),"")) -> Platinum | D4: =IF($A4="","",IFERROR(INDEX('INVENTORY MASTER'!$M$4:$M$63,MATCH($A4,'INVENTORY MASTER'!$A$4:$A$63,0)),"")) -> 950 Platinum | E4: =IF($A4="","",IFERROR(INDEX('INVENTORY MASTER'!$N$4:$N$63,MATCH($A4,'INVENTORY MASTER'!$A$4:$A$63,0)),"")) -> 5.2 | G4: =IF(OR($A4="",E4="",F4=""),"",E4*F4) | H4: =IF($A4="","",IFERROR(INDEX('INVENTORY MASTER'!$O$4:$O$63,MATCH($A4,'INVENTORY MASTER'!$A$4:$A$63,0)),"")) -> Diamond | I4: =IF($A4="","",IFERROR(INDEX('INVENTORY MASTER'!$P$4:$P$63,MATCH($A4,'INVENTORY MASTER'!$A$4:$A$63,0)),"")) -> 1.01 | J4: 2500 | K4: 0.1 | L4: =IF(OR(G4="",K4=""),"",(G4+N(J4))*(1+K4)) | M4: 0.5 | N4: =IF(OR(G4="",M4=""),"",(G4+N(J4))*(1+M4)) | O4: =IF($A4="","",IFERROR(INDEX('INVENTORY MASTER'!$Q$4:$Q$63,MATCH($A4,'INVENTORY MASTER'!$A$4:$A$63,0)),"")) -> F | P4: =IF($A4="","",IFERROR(INDEX('INVENTORY MASTER'!$R$4:$R$63,MATCH($A4,'INVENTORY MASTER'!$A$4:$A$63,0)),"")) -> VS1 | T4: =IF($A4="","",IFERROR(INDEX('INVENTORY MASTER'!$S$4:$S$63,MATCH($A4,'INVENTORY MASTER'!$A$4:$A$63,0)),"")) -> M | U4: =IF($A4="","",IFERROR(INDEX('INVENTORY MASTER'!$AI$4:$AI$63,MATCH($A4,'INVENTORY MASTER'!$A$4:$A$63,0)),"")) -> 3550 | V4: =IF(OR($A4="",E4="",E4=0),"",U4/E4) -> 682.69231 | W4: =IF($A4="","",IFERROR(INDEX('INVENTORY MASTER'!$AM$4:$AM$63,MATCH($A4,'INVENTORY MASTER'!$A$4:$A$63,0)),"")) -> 5500 | X4: =IF($A4="","",IFERROR(INDEX('INVENTORY MASTER'!$AO$4:$AO$63,MATCH($A4,'INVENTORY MASTER'!$A$4:$A$63,0)),"")) -> 5500 | Y4: =IF($A4="","",IFERROR(INDEX('INVENTORY MASTER'!$AS$4:$AS$63,MATCH($A4,'INVENTORY MASTER'!$A$4:$A$63,0)),"")) -> Available | Z4: =IF($A4="","",IFERROR(INDEX('INVENTORY MASTER'!$AR$4:$AR$63,MATCH($A4,'INVENTORY MASTER'!$A$4:$A$63,0)),"")) -> Shop Display
A5: JWL-0002 | B5: =IF($A5="","",IFERROR(INDEX('INVENTORY MASTER'!$F$4:$F$63,MATCH($A5,'INVENTORY MASTER'!$A$4:$A$63,0)),"")) -> Chain Necklace | C5: =IF($A5="","",IFERROR(INDEX('INVENTORY MASTER'!$L$4:$L$63,MATCH($A5,'INVENTORY MASTER'!$A$4:$A$63,0)),"")) -> Gold | D5: =IF($A5="","",IFERROR(INDEX('INVENTORY MASTER'!$M$4:$M$63,MATCH($A5,'INVENTORY MASTER'!$A$4:$A$63,0)),"")) -> 18ct | E5: =IF($A5="","",IFERROR(INDEX('INVENTORY MASTER'!$N$4:$N$63,MATCH($A5,'INVENTORY MASTER'!$A$4:$A$63,0)),"")) -> 22.5 | F5: 55 | G5: =IF(OR($A5="",E5="",F5=""),"",E5*F5) -> 1237.5 | H5: =IF($A5="","",IFERROR(INDEX('INVENTORY MASTER'!$O$4:$O$63,MATCH($A5,'INVENTORY MASTER'!$A$4:$A$63,0)),"")) -> 0 | I5: =IF($A5="","",IFERROR(INDEX('INVENTORY MASTER'!$P$4:$P$63,MATCH($A5,'INVENTORY MASTER'!$A$4:$A$63,0)),"")) -> 0 | J5: 0 | K5: 0.08 | L5: =IF(OR(G5="",K5=""),"",(G5+N(J5))*(1+K5)) -> 1336.5 | M5: 0.45 | N5: =IF(OR(G5="",M5=""),"",(G5+N(J5))*(1+M5)) -> 1794.375 | O5: =IF($A5="","",IFERROR(INDEX('INVENTORY MASTER'!$Q$4:$Q$63,MATCH($A5,'INVENTORY MASTER'!$A$4:$A$63,0)),"")) -> 0 | P5: =IF($A5="","",IFERROR(INDEX('INVENTORY MASTER'!$R$4:$R$63,MATCH($A5,'INVENTORY MASTER'!$A$4:$A$63,0)),"")) -> 0 | T5: =IF($A5="","",IFERROR(INDEX('INVENTORY MASTER'!$S$4:$S$63,MATCH($A5,'INVENTORY MASTER'!$A$4:$A$63,0)),"")) -> 0 | U5: =IF($A5="","",IFERROR(INDEX('INVENTORY MASTER'!$AI$4:$AI$63,MATCH($A5,'INVENTORY MASTER'!$A$4:$A$63,0)),"")) -> 1500 | V5: =IF(OR($A5="",E5="",E5=0),"",U5/E5) -> 66.666667 | W5: =IF($A5="","",IFERROR(INDEX('INVENTORY MASTER'!$AM$4:$AM$63,MATCH($A5,'INVENTORY MASTER'!$A$4:$A$63,0)),"")) -> 2200 | X5: =IF($A5="","",IFERROR(INDEX('INVENTORY MASTER'!$AO$4:$AO$63,MATCH($A5,'INVENTORY MASTER'!$A$4:$A$63,0)),"")) -> 2200 | Y5: =IF($A5="","",IFERROR(INDEX('INVENTORY MASTER'!$AS$4:$AS$63,MATCH($A5,'INVENTORY MASTER'!$A$4:$A$63,0)),"")) -> Available | Z5: =IF($A5="","",IFERROR(INDEX('INVENTORY MASTER'!$AR$4:$AR$63,MATCH($A5,'INVENTORY MASTER'!$A$4:$A$63,0)),"")) -> Shop Safe
A6: JWL-0003 | B6: =IF($A6="","",IFERROR(INDEX('INVENTORY MASTER'!$F$4:$F$63,MATCH($A6,'INVENTORY MASTER'!$A$4:$A$63,0)),"")) -> Bangle | C6: =IF($A6="","",IFERROR(INDEX('INVENTORY MASTER'!$L$4:$L$63,MATCH($A6,'INVENTORY MASTER'!$A$4:$A$63,0)),"")) -> Gold | D6: =IF($A6="","",IFERROR(INDEX('INVENTORY MASTER'!$M$4:$M$63,MATCH($A6,'INVENTORY MASTER'!$A$4:$A$63,0)),"")) -> 22ct | E6: =IF($A6="","",IFERROR(INDEX('INVENTORY MASTER'!$N$4:$N$63,MATCH($A6,'INVENTORY MASTER'!$A$4:$A$63,0)),"")) -> 18 | F6: 68 | G6: =IF(OR($A6="",E6="",F6=""),"",E6*F6) -> 1224 | H6: =IF($A6="","",IFERROR(INDEX('INVENTORY MASTER'!$O$4:$O$63,MATCH($A6,'INVENTORY MASTER'!$A$4:$A$63,0)),"")) -> None | I6: =IF($A6="","",IFERROR(INDEX('INVENTORY MASTER'!$P$4:$P$63,MATCH($A6,'INVENTORY MASTER'!$A$4:$A$63,0)),"")) -> 0 | J6: 0 | K6: 0.06 | L6: =IF(OR(G6="",K6=""),"",(G6+N(J6))*(1+K6)) -> 1297.44 | M6: 0.4 | N6: =IF(OR(G6="",M6=""),"",(G6+N(J6))*(1+M6)) -> 1713.6 | O6: =IF($A6="","",IFERROR(INDEX('INVENTORY MASTER'!$Q$4:$Q$63,MATCH($A6,'INVENTORY MASTER'!$A$4:$A$63,0)),"")) -> 0 | P6: =IF($A6="","",IFERROR(INDEX('INVENTORY MASTER'!$R$4:$R$63,MATCH($A6,'INVENTORY MASTER'!$A$4:$A$63,0)),"")) -> 0 | T6: =IF($A6="","",IFERROR(INDEX('INVENTORY MASTER'!$S$4:$S$63,MATCH($A6,'INVENTORY MASTER'!$A$4:$A$63,0)),"")) -> 0 | U6: =IF($A6="","",IFERROR(INDEX('INVENTORY MASTER'!$AI$4:$AI$63,MATCH($A6,'INVENTORY MASTER'!$A$4:$A$63,0)),"")) -> 1650 | V6: =IF(OR($A6="",E6="",E6=0),"",U6/E6) -> 91.666667 | W6: =IF($A6="","",IFERROR(INDEX('INVENTORY MASTER'!$AM$4:$AM$63,MATCH($A6,'INVENTORY MASTER'!$A$4:$A$63,0)),"")) -> 2400 | X6: =IF($A6="","",IFERROR(INDEX('INVENTORY MASTER'!$AO$4:$AO$63,MATCH($A6,'INVENTORY MASTER'!$A$4:$A$63,0)),"")) -> 2400 | Y6: =IF($A6="","",IFERROR(INDEX('INVENTORY MASTER'!$AS$4:$AS$63,MATCH($A6,'INVENTORY MASTER'!$A$4:$A$63,0)),"")) -> Available | Z6: =IF($A6="","",IFERROR(INDEX('INVENTORY MASTER'!$AR$4:$AR$63,MATCH($A6,'INVENTORY MASTER'!$A$4:$A$63,0)),"")) -> Shop Safe
B7: =IF($A7="","",IFERROR(INDEX('INVENTORY MASTER'!$F$4:$F$63,MATCH($A7,'INVENTORY MASTER'!$A$4:$A$63,0)),"")) | C7: =IF($A7="","",IFERROR(INDEX('INVENTORY MASTER'!$L$4:$L$63,MATCH($A7,'INVENTORY MASTER'!$A$4:$A$63,0)),"")) | D7: =IF($A7="","",IFERROR(INDEX('INVENTORY MASTER'!$M$4:$M$63,MATCH($A7,'INVENTORY MASTER'!$A$4:$A$63,0)),"")) | E7: =IF($A7="","",IFERROR(INDEX('INVENTORY MASTER'!$N$4:$N$63,MATCH($A7,'INVENTORY MASTER'!$A$4:$A$63,0)),"")) | G7: =IF(OR($A7="",E7="",F7=""),"",E7*F7) | H7: =IF($A7="","",IFERROR(INDEX('INVENTORY MASTER'!$O$4:$O$63,MATCH($A7,'INVENTORY MASTER'!$A$4:$A$63,0)),"")) | I7: =IF($A7="","",IFERROR(INDEX('INVENTORY MASTER'!$P$4:$P$63,MATCH($A7,'INVENTORY MASTER'!$A$4:$A$63,0)),"")) | L7: =IF(OR(G7="",K7=""),"",(G7+N(J7))*(1+K7)) | N7: =IF(OR(G7="",M7=""),"",(G7+N(J7))*(1+M7)) | O7: =IF($A7="","",IFERROR(INDEX('INVENTORY MASTER'!$Q$4:$Q$63,MATCH($A7,'INVENTORY MASTER'!$A$4:$A$63,0)),"")) | P7: =IF($A7="","",IFERROR(INDEX('INVENTORY MASTER'!$R$4:$R$63,MATCH($A7,'INVENTORY MASTER'!$A$4:$A$63,0)),"")) | T7: =IF($A7="","",IFERROR(INDEX('INVENTORY MASTER'!$S$4:$S$63,MATCH($A7,'INVENTORY MASTER'!$A$4:$A$63,0)),"")) | U7: =IF($A7="","",IFERROR(INDEX('INVENTORY MASTER'!$AI$4:$AI$63,MATCH($A7,'INVENTORY MASTER'!$A$4:$A$63,0)),"")) | V7: =IF(OR($A7="",E7="",E7=0),"",U7/E7) | W7: =IF($A7="","",IFERROR(INDEX('INVENTORY MASTER'!$AM$4:$AM$63,MATCH($A7,'INVENTORY MASTER'!$A$4:$A$63,0)),"")) | X7: =IF($A7="","",IFERROR(INDEX('INVENTORY MASTER'!$AO$4:$AO$63,MATCH($A7,'INVENTORY MASTER'!$A$4:$A$63,0)),"")) | Y7: =IF($A7="","",IFERROR(INDEX('INVENTORY MASTER'!$AS$4:$AS$63,MATCH($A7,'INVENTORY MASTER'!$A$4:$A$63,0)),"")) | Z7: =IF($A7="","",IFERROR(INDEX('INVENTORY MASTER'!$AR$4:$AR$63,MATCH($A7,'INVENTORY MASTER'!$A$4:$A$63,0)),""))
B8: =IF($A8="","",IFERROR(INDEX('INVENTORY MASTER'!$F$4:$F$63,MATCH($A8,'INVENTORY MASTER'!$A$4:$A$63,0)),"")) | C8: =IF($A8="","",IFERROR(INDEX('INVENTORY MASTER'!$L$4:$L$63,MATCH($A8,'INVENTORY MASTER'!$A$4:$A$63,0)),"")) | D8: =IF($A8="","",IFERROR(INDEX('INVENTORY MASTER'!$M$4:$M$63,MATCH($A8,'INVENTORY MASTER'!$A$4:$A$63,0)),"")) | E8: =IF($A8="","",IFERROR(INDEX('INVENTORY MASTER'!$N$4:$N$63,MATCH($A8,'INVENTORY MASTER'!$A$4:$A$63,0)),"")) | G8: =IF(OR($A8="",E8="",F8=""),"",E8*F8) | H8: =IF($A8="","",IFERROR(INDEX('INVENTORY MASTER'!$O$4:$O$63,MATCH($A8,'INVENTORY MASTER'!$A$4:$A$63,0)),"")) | I8: =IF($A8="","",IFERROR(INDEX('INVENTORY MASTER'!$P$4:$P$63,MATCH($A8,'INVENTORY MASTER'!$A$4:$A$63,0)),"")) | L8: =IF(OR(G8="",K8=""),"",(G8+N(J8))*(1+K8)) | N8: =IF(OR(G8="",M8=""),"",(G8+N(J8))*(1+M8)) | O8: =IF($A8="","",IFERROR(INDEX('INVENTORY MASTER'!$Q$4:$Q$63,MATCH($A8,'INVENTORY MASTER'!$A$4:$A$63,0)),"")) | P8: =IF($A8="","",IFERROR(INDEX('INVENTORY MASTER'!$R$4:$R$63,MATCH($A8,'INVENTORY MASTER'!$A$4:$A$63,0)),"")) | T8: =IF($A8="","",IFERROR(INDEX('INVENTORY MASTER'!$S$4:$S$63,MATCH($A8,'INVENTORY MASTER'!$A$4:$A$63,0)),"")) | U8: =IF($A8="","",IFERROR(INDEX('INVENTORY MASTER'!$AI$4:$AI$63,MATCH($A8,'INVENTORY MASTER'!$A$4:$A$63,0)),"")) | V8: =IF(OR($A8="",E8="",E8=0),"",U8/E8) | W8: =IF($A8="","",IFERROR(INDEX('INVENTORY MASTER'!$AM$4:$AM$63,MATCH($A8,'INVENTORY MASTER'!$A$4:$A$63,0)),"")) | X8: =IF($A8="","",IFERROR(INDEX('INVENTORY MASTER'!$AO$4:$AO$63,MATCH($A8,'INVENTORY MASTER'!$A$4:$A$63,0)),"")) | Y8: =IF($A8="","",IFERROR(INDEX('INVENTORY MASTER'!$AS$4:$AS$63,MATCH($A8,'INVENTORY MASTER'!$A$4:$A$63,0)),"")) | Z8: =IF($A8="","",IFERROR(INDEX('INVENTORY MASTER'!$AR$4:$AR$63,MATCH($A8,'INVENTORY MASTER'!$A$4:$A$63,0)),""))
B9: =IF($A9="","",IFERROR(INDEX('INVENTORY MASTER'!$F$4:$F$63,MATCH($A9,'INVENTORY MASTER'!$A$4:$A$63,0)),"")) | C9: =IF($A9="","",IFERROR(INDEX('INVENTORY MASTER'!$L$4:$L$63,MATCH($A9,'INVENTORY MASTER'!$A$4:$A$63,0)),"")) | D9: =IF($A9="","",IFERROR(INDEX('INVENTORY MASTER'!$M$4:$M$63,MATCH($A9,'INVENTORY MASTER'!$A$4:$A$63,0)),"")) | E9: =IF($A9="","",IFERROR(INDEX('INVENTORY MASTER'!$N$4:$N$63,MATCH($A9,'INVENTORY MASTER'!$A$4:$A$63,0)),"")) | G9: =IF(OR($A9="",E9="",F9=""),"",E9*F9) | H9: =IF($A9="","",IFERROR(INDEX('INVENTORY MASTER'!$O$4:$O$63,MATCH($A9,'INVENTORY MASTER'!$A$4:$A$63,0)),"")) | I9: =IF($A9="","",IFERROR(INDEX('INVENTORY MASTER'!$P$4:$P$63,MATCH($A9,'INVENTORY MASTER'!$A$4:$A$63,0)),"")) | L9: =IF(OR(G9="",K9=""),"",(G9+N(J9))*(1+K9)) | N9: =IF(OR(G9="",M9=""),"",(G9+N(J9))*(1+M9)) | O9: =IF($A9="","",IFERROR(INDEX('INVENTORY MASTER'!$Q$4:$Q$63,MATCH($A9,'INVENTORY MASTER'!$A$4:$A$63,0)),"")) | P9: =IF($A9="","",IFERROR(INDEX('INVENTORY MASTER'!$R$4:$R$63,MATCH($A9,'INVENTORY MASTER'!$A$4:$A$63,0)),"")) | T9: =IF($A9="","",IFERROR(INDEX('INVENTORY MASTER'!$S$4:$S$63,MATCH($A9,'INVENTORY MASTER'!$A$4:$A$63,0)),"")) | U9: =IF($A9="","",IFERROR(INDEX('INVENTORY MASTER'!$AI$4:$AI$63,MATCH($A9,'INVENTORY MASTER'!$A$4:$A$63,0)),"")) | V9: =IF(OR($A9="",E9="",E9=0),"",U9/E9) | W9: =IF($A9="","",IFERROR(INDEX('INVENTORY MASTER'!$AM$4:$AM$63,MATCH($A9,'INVENTORY MASTER'!$A$4:$A$63,0)),"")) | X9: =IF($A9="","",IFERROR(INDEX('INVENTORY MASTER'!$AO$4:$AO$63,MATCH($A9,'INVENTORY MASTER'!$A$4:$A$63,0)),"")) | Y9: =IF($A9="","",IFERROR(INDEX('INVENTORY MASTER'!$AS$4:$AS$63,MATCH($A9,'INVENTORY MASTER'!$A$4:$A$63,0)),"")) | Z9: =IF($A9="","",IFERROR(INDEX('INVENTORY MASTER'!$AR$4:$AR$63,MATCH($A9,'INVENTORY MASTER'!$A$4:$A$63,0)),""))
B10: =IF($A10="","",IFERROR(INDEX('INVENTORY MASTER'!$F$4:$F$63,MATCH($A10,'INVENTORY MASTER'!$A$4:$A$63,0)),"")) | C10: =IF($A10="","",IFERROR(INDEX('INVENTORY MASTER'!$L$4:$L$63,MATCH($A10,'INVENTORY MASTER'!$A$4:$A$63,0)),"")) | D10: =IF($A10="","",IFERROR(INDEX('INVENTORY MASTER'!$M$4:$M$63,MATCH($A10,'INVENTORY MASTER'!$A$4:$A$63,0)),"")) | E10: =IF($A10="","",IFERROR(INDEX('INVENTORY MASTER'!$N$4:$N$63,MATCH($A10,'INVENTORY MASTER'!$A$4:$A$63,0)),"")) | G10: =IF(OR($A10="",E10="",F10=""),"",E10*F10) | H10: =IF($A10="","",IFERROR(INDEX('INVENTORY MASTER'!$O$4:$O$63,MATCH($A10,'INVENTORY MASTER'!$A$4:$A$63,0)),"")) | I10: =IF($A10="","",IFERROR(INDEX('INVENTORY MASTER'!$P$4:$P$63,MATCH($A10,'INVENTORY MASTER'!$A$4:$A$63,0)),"")) | L10: =IF(OR(G10="",K10=""),"",(G10+N(J10))*(1+K10)) | N10: =IF(OR(G10="",M10=""),"",(G10+N(J10))*(1+M10)) | O10: =IF($A10="","",IFERROR(INDEX('INVENTORY MASTER'!$Q$4:$Q$63,MATCH($A10,'INVENTORY MASTER'!$A$4:$A$63,0)),"")) | P10: =IF($A10="","",IFERROR(INDEX('INVENTORY MASTER'!$R$4:$R$63,MATCH($A10,'INVENTORY MASTER'!$A$4:$A$63,0)),"")) | T10: =IF($A10="","",IFERROR(INDEX('INVENTORY MASTER'!$S$4:$S$63,MATCH($A10,'INVENTORY MASTER'!$A$4:$A$63,0)),"")) | U10: =IF($A10="","",IFERROR(INDEX('INVENTORY MASTER'!$AI$4:$AI$63,MATCH($A10,'INVENTORY MASTER'!$A$4:$A$63,0)),"")) | V10: =IF(OR($A10="",E10="",E10=0),"",U10/E10) | W10: =IF($A10="","",IFERROR(INDEX('INVENTORY MASTER'!$AM$4:$AM$63,MATCH($A10,'INVENTORY MASTER'!$A$4:$A$63,0)),"")) | X10: =IF($A10="","",IFERROR(INDEX('INVENTORY MASTER'!$AO$4:$AO$63,MATCH($A10,'INVENTORY MASTER'!$A$4:$A$63,0)),"")) | Y10: =IF($A10="","",IFERROR(INDEX('INVENTORY MASTER'!$AS$4:$AS$63,MATCH($A10,'INVENTORY MASTER'!$A$4:$A$63,0)),"")) | Z10: =IF($A10="","",IFERROR(INDEX('INVENTORY MASTER'!$AR$4:$AR$63,MATCH($A10,'INVENTORY MASTER'!$A$4:$A$63,0)),""))
B11: =IF($A11="","",IFERROR(INDEX('INVENTORY MASTER'!$F$4:$F$63,MATCH($A11,'INVENTORY MASTER'!$A$4:$A$63,0)),"")) | C11: =IF($A11="","",IFERROR(INDEX('INVENTORY MASTER'!$L$4:$L$63,MATCH($A11,'INVENTORY MASTER'!$A$4:$A$63,0)),"")) | D11: =IF($A11="","",IFERROR(INDEX('INVENTORY MASTER'!$M$4:$M$63,MATCH($A11,'INVENTORY MASTER'!$A$4:$A$63,0)),"")) | E11: =IF($A11="","",IFERROR(INDEX('INVENTORY MASTER'!$N$4:$N$63,MATCH($A11,'INVENTORY MASTER'!$A$4:$A$63,0)),"")) | G11: =IF(OR($A11="",E11="",F11=""),"",E11*F11) | H11: =IF($A11="","",IFERROR(INDEX('INVENTORY MASTER'!$O$4:$O$63,MATCH($A11,'INVENTORY MASTER'!$A$4:$A$63,0)),"")) | I11: =IF($A11="","",IFERROR(INDEX('INVENTORY MASTER'!$P$4:$P$63,MATCH($A11,'INVENTORY MASTER'!$A$4:$A$63,0)),"")) | L11: =IF(OR(G11="",K11=""),"",(G11+N(J11))*(1+K11)) | N11: =IF(OR(G11="",M11=""),"",(G11+N(J11))*(1+M11)) | O11: =IF($A11="","",IFERROR(INDEX('INVENTORY MASTER'!$Q$4:$Q$63,MATCH($A11,'INVENTORY MASTER'!$A$4:$A$63,0)),"")) | P11: =IF($A11="","",IFERROR(INDEX('INVENTORY MASTER'!$R$4:$R$63,MATCH($A11,'INVENTORY MASTER'!$A$4:$A$63,0)),"")) | T11: =IF($A11="","",IFERROR(INDEX('INVENTORY MASTER'!$S$4:$S$63,MATCH($A11,'INVENTORY MASTER'!$A$4:$A$63,0)),"")) | U11: =IF($A11="","",IFERROR(INDEX('INVENTORY MASTER'!$AI$4:$AI$63,MATCH($A11,'INVENTORY MASTER'!$A$4:$A$63,0)),"")) | V11: =IF(OR($A11="",E11="",E11=0),"",U11/E11) | W11: =IF($A11="","",IFERROR(INDEX('INVENTORY MASTER'!$AM$4:$AM$63,MATCH($A11,'INVENTORY MASTER'!$A$4:$A$63,0)),"")) | X11: =IF($A11="","",IFERROR(INDEX('INVENTORY MASTER'!$AO$4:$AO$63,MATCH($A11,'INVENTORY MASTER'!$A$4:$A$63,0)),"")) | Y11: =IF($A11="","",IFERROR(INDEX('INVENTORY MASTER'!$AS$4:$AS$63,MATCH($A11,'INVENTORY MASTER'!$A$4:$A$63,0)),"")) | Z11: =IF($A11="","",IFERROR(INDEX('INVENTORY MASTER'!$AR$4:$AR$63,MATCH($A11,'INVENTORY MASTER'!$A$4:$A$63,0)),""))
B12: =IF($A12="","",IFERROR(INDEX('INVENTORY MASTER'!$F$4:$F$63,MATCH($A12,'INVENTORY MASTER'!$A$4:$A$63,0)),"")) | C12: =IF($A12="","",IFERROR(INDEX('INVENTORY MASTER'!$L$4:$L$63,MATCH($A12,'INVENTORY MASTER'!$A$4:$A$63,0)),"")) | D12: =IF($A12="","",IFERROR(INDEX('INVENTORY MASTER'!$M$4:$M$63,MATCH($A12,'INVENTORY MASTER'!$A$4:$A$63,0)),"")) | E12: =IF($A12="","",IFERROR(INDEX('INVENTORY MASTER'!$N$4:$N$63,MATCH($A12,'INVENTORY MASTER'!$A$4:$A$63,0)),"")) | G12: =IF(OR($A12="",E12="",F12=""),"",E12*F12) | H12: =IF($A12="","",IFERROR(INDEX('INVENTORY MASTER'!$O$4:$O$63,MATCH($A12,'INVENTORY MASTER'!$A$4:$A$63,0)),"")) | I12: =IF($A12="","",IFERROR(INDEX('INVENTORY MASTER'!$P$4:$P$63,MATCH($A12,'INVENTORY MASTER'!$A$4:$A$63,0)),"")) | L12: =IF(OR(G12="",K12=""),"",(G12+N(J12))*(1+K12)) | N12: =IF(OR(G12="",M12=""),"",(G12+N(J12))*(1+M12)) | O12: =IF($A12="","",IFERROR(INDEX('INVENTORY MASTER'!$Q$4:$Q$63,MATCH($A12,'INVENTORY MASTER'!$A$4:$A$63,0)),"")) | P12: =IF($A12="","",IFERROR(INDEX('INVENTORY MASTER'!$R$4:$R$63,MATCH($A12,'INVENTORY MASTER'!$A$4:$A$63,0)),"")) | T12: =IF($A12="","",IFERROR(INDEX('INVENTORY MASTER'!$S$4:$S$63,MATCH($A12,'INVENTORY MASTER'!$A$4:$A$63,0)),"")) | U12: =IF($A12="","",IFERROR(INDEX('INVENTORY MASTER'!$AI$4:$AI$63,MATCH($A12,'INVENTORY MASTER'!$A$4:$A$63,0)),"")) | V12: =IF(OR($A12="",E12="",E12=0),"",U12/E12) | W12: =IF($A12="","",IFERROR(INDEX('INVENTORY MASTER'!$AM$4:$AM$63,MATCH($A12,'INVENTORY MASTER'!$A$4:$A$63,0)),"")) | X12: =IF($A12="","",IFERROR(INDEX('INVENTORY MASTER'!$AO$4:$AO$63,MATCH($A12,'INVENTORY MASTER'!$A$4:$A$63,0)),"")) | Y12: =IF($A12="","",IFERROR(INDEX('INVENTORY MASTER'!$AS$4:$AS$63,MATCH($A12,'INVENTORY MASTER'!$A$4:$A$63,0)),"")) | Z12: =IF($A12="","",IFERROR(INDEX('INVENTORY MASTER'!$AR$4:$AR$63,MATCH($A12,'INVENTORY MASTER'!$A$4:$A$63,0)),""))
B13: =IF($A13="","",IFERROR(INDEX('INVENTORY MASTER'!$F$4:$F$63,MATCH($A13,'INVENTORY MASTER'!$A$4:$A$63,0)),"")) | C13: =IF($A13="","",IFERROR(INDEX('INVENTORY MASTER'!$L$4:$L$63,MATCH($A13,'INVENTORY MASTER'!$A$4:$A$63,0)),"")) | D13: =IF($A13="","",IFERROR(INDEX('INVENTORY MASTER'!$M$4:$M$63,MATCH($A13,'INVENTORY MASTER'!$A$4:$A$63,0)),"")) | E13: =IF($A13="","",IFERROR(INDEX('INVENTORY MASTER'!$N$4:$N$63,MATCH($A13,'INVENTORY MASTER'!$A$4:$A$63,0)),"")) | G13: =IF(OR($A13="",E13="",F13=""),"",E13*F13) | H13: =IF($A13="","",IFERROR(INDEX('INVENTORY MASTER'!$O$4:$O$63,MATCH($A13,'INVENTORY MASTER'!$A$4:$A$63,0)),"")) | I13: =IF($A13="","",IFERROR(INDEX('INVENTORY MASTER'!$P$4:$P$63,MATCH($A13,'INVENTORY MASTER'!$A$4:$A$63,0)),"")) | L13: =IF(OR(G13="",K13=""),"",(G13+N(J13))*(1+K13)) | N13: =IF(OR(G13="",M13=""),"",(G13+N(J13))*(1+M13)) | O13: =IF($A13="","",IFERROR(INDEX('INVENTORY MASTER'!$Q$4:$Q$63,MATCH($A13,'INVENTORY MASTER'!$A$4:$A$63,0)),"")) | P13: =IF($A13="","",IFERROR(INDEX('INVENTORY MASTER'!$R$4:$R$63,MATCH($A13,'INVENTORY MASTER'!$A$4:$A$63,0)),"")) | T13: =IF($A13="","",IFERROR(INDEX('INVENTORY MASTER'!$S$4:$S$63,MATCH($A13,'INVENTORY MASTER'!$A$4:$A$63,0)),"")) | U13: =IF($A13="","",IFERROR(INDEX('INVENTORY MASTER'!$AI$4:$AI$63,MATCH($A13,'INVENTORY MASTER'!$A$4:$A$63,0)),"")) | V13: =IF(OR($A13="",E13="",E13=0),"",U13/E13) | W13: =IF($A13="","",IFERROR(INDEX('INVENTORY MASTER'!$AM$4:$AM$63,MATCH($A13,'INVENTORY MASTER'!$A$4:$A$63,0)),"")) | X13: =IF($A13="","",IFERROR(INDEX('INVENTORY MASTER'!$AO$4:$AO$63,MATCH($A13,'INVENTORY MASTER'!$A$4:$A$63,0)),"")) | Y13: =IF($A13="","",IFERROR(INDEX('INVENTORY MASTER'!$AS$4:$AS$63,MATCH($A13,'INVENTORY MASTER'!$A$4:$A$63,0)),"")) | Z13: =IF($A13="","",IFERROR(INDEX('INVENTORY MASTER'!$AR$4:$AR$63,MATCH($A13,'INVENTORY MASTER'!$A$4:$A$63,0)),""))
B14: =IF($A14="","",IFERROR(INDEX('INVENTORY MASTER'!$F$4:$F$63,MATCH($A14,'INVENTORY MASTER'!$A$4:$A$63,0)),"")) | C14: =IF($A14="","",IFERROR(INDEX('INVENTORY MASTER'!$L$4:$L$63,MATCH($A14,'INVENTORY MASTER'!$A$4:$A$63,0)),"")) | D14: =IF($A14="","",IFERROR(INDEX('INVENTORY MASTER'!$M$4:$M$63,MATCH($A14,'INVENTORY MASTER'!$A$4:$A$63,0)),"")) | E14: =IF($A14="","",IFERROR(INDEX('INVENTORY MASTER'!$N$4:$N$63,MATCH($A14,'INVENTORY MASTER'!$A$4:$A$63,0)),"")) | G14: =IF(OR($A14="",E14="",F14=""),"",E14*F14) | H14: =IF($A14="","",IFERROR(INDEX('INVENTORY MASTER'!$O$4:$O$63,MATCH($A14,'INVENTORY MASTER'!$A$4:$A$63,0)),"")) | I14: =IF($A14="","",IFERROR(INDEX('INVENTORY MASTER'!$P$4:$P$63,MATCH($A14,'INVENTORY MASTER'!$A$4:$A$63,0)),"")) | L14: =IF(OR(G14="",K14=""),"",(G14+N(J14))*(1+K14)) | N14: =IF(OR(G14="",M14=""),"",(G14+N(J14))*(1+M14)) | O14: =IF($A14="","",IFERROR(INDEX('INVENTORY MASTER'!$Q$4:$Q$63,MATCH($A14,'INVENTORY MASTER'!$A$4:$A$63,0)),"")) | P14: =IF($A14="","",IFERROR(INDEX('INVENTORY MASTER'!$R$4:$R$63,MATCH($A14,'INVENTORY MASTER'!$A$4:$A$63,0)),"")) | T14: =IF($A14="","",IFERROR(INDEX('INVENTORY MASTER'!$S$4:$S$63,MATCH($A14,'INVENTORY MASTER'!$A$4:$A$63,0)),"")) | U14: =IF($A14="","",IFERROR(INDEX('INVENTORY MASTER'!$AI$4:$AI$63,MATCH($A14,'INVENTORY MASTER'!$A$4:$A$63,0)),"")) | V14: =IF(OR($A14="",E14="",E14=0),"",U14/E14) | W14: =IF($A14="","",IFERROR(INDEX('INVENTORY MASTER'!$AM$4:$AM$63,MATCH($A14,'INVENTORY MASTER'!$A$4:$A$63,0)),"")) | X14: =IF($A14="","",IFERROR(INDEX('INVENTORY MASTER'!$AO$4:$AO$63,MATCH($A14,'INVENTORY MASTER'!$A$4:$A$63,0)),"")) | Y14: =IF($A14="","",IFERROR(INDEX('INVENTORY MASTER'!$AS$4:$AS$63,MATCH($A14,'INVENTORY MASTER'!$A$4:$A$63,0)),"")) | Z14: =IF($A14="","",IFERROR(INDEX('INVENTORY MASTER'!$AR$4:$AR$63,MATCH($A14,'INVENTORY MASTER'!$A$4:$A$63,0)),""))
B15: =IF($A15="","",IFERROR(INDEX('INVENTORY MASTER'!$F$4:$F$63,MATCH($A15,'INVENTORY MASTER'!$A$4:$A$63,0)),"")) | C15: =IF($A15="","",IFERROR(INDEX('INVENTORY MASTER'!$L$4:$L$63,MATCH($A15,'INVENTORY MASTER'!$A$4:$A$63,0)),"")) | D15: =IF($A15="","",IFERROR(INDEX('INVENTORY MASTER'!$M$4:$M$63,MATCH($A15,'INVENTORY MASTER'!$A$4:$A$63,0)),"")) | E15: =IF($A15="","",IFERROR(INDEX('INVENTORY MASTER'!$N$4:$N$63,MATCH($A15,'INVENTORY MASTER'!$A$4:$A$63,0)),"")) | G15: =IF(OR($A15="",E15="",F15=""),"",E15*F15) | H15: =IF($A15="","",IFERROR(INDEX('INVENTORY MASTER'!$O$4:$O$63,MATCH($A15,'INVENTORY MASTER'!$A$4:$A$63,0)),"")) | I15: =IF($A15="","",IFERROR(INDEX('INVENTORY MASTER'!$P$4:$P$63,MATCH($A15,'INVENTORY MASTER'!$A$4:$A$63,0)),"")) | L15: =IF(OR(G15="",K15=""),"",(G15+N(J15))*(1+K15)) | N15: =IF(OR(G15="",M15=""),"",(G15+N(J15))*(1+M15)) | O15: =IF($A15="","",IFERROR(INDEX('INVENTORY MASTER'!$Q$4:$Q$63,MATCH($A15,'INVENTORY MASTER'!$A$4:$A$63,0)),"")) | P15: =IF($A15="","",IFERROR(INDEX('INVENTORY MASTER'!$R$4:$R$63,MATCH($A15,'INVENTORY MASTER'!$A$4:$A$63,0)),"")) | T15: =IF($A15="","",IFERROR(INDEX('INVENTORY MASTER'!$S$4:$S$63,MATCH($A15,'INVENTORY MASTER'!$A$4:$A$63,0)),"")) | U15: =IF($A15="","",IFERROR(INDEX('INVENTORY MASTER'!$AI$4:$AI$63,MATCH($A15,'INVENTORY MASTER'!$A$4:$A$63,0)),"")) | V15: =IF(OR($A15="",E15="",E15=0),"",U15/E15) | W15: =IF($A15="","",IFERROR(INDEX('INVENTORY MASTER'!$AM$4:$AM$63,MATCH($A15,'INVENTORY MASTER'!$A$4:$A$63,0)),"")) | X15: =IF($A15="","",IFERROR(INDEX('INVENTORY MASTER'!$AO$4:$AO$63,MATCH($A15,'INVENTORY MASTER'!$A$4:$A$63,0)),"")) | Y15: =IF($A15="","",IFERROR(INDEX('INVENTORY MASTER'!$AS$4:$AS$63,MATCH($A15,'INVENTORY MASTER'!$A$4:$A$63,0)),"")) | Z15: =IF($A15="","",IFERROR(INDEX('INVENTORY MASTER'!$AR$4:$AR$63,MATCH($A15,'INVENTORY MASTER'!$A$4:$A$63,0)),""))
B16: =IF($A16="","",IFERROR(INDEX('INVENTORY MASTER'!$F$4:$F$63,MATCH($A16,'INVENTORY MASTER'!$A$4:$A$63,0)),"")) | C16: =IF($A16="","",IFERROR(INDEX('INVENTORY MASTER'!$L$4:$L$63,MATCH($A16,'INVENTORY MASTER'!$A$4:$A$63,0)),"")) | D16: =IF($A16="","",IFERROR(INDEX('INVENTORY MASTER'!$M$4:$M$63,MATCH($A16,'INVENTORY MASTER'!$A$4:$A$63,0)),"")) | E16: =IF($A16="","",IFERROR(INDEX('INVENTORY MASTER'!$N$4:$N$63,MATCH($A16,'INVENTORY MASTER'!$A$4:$A$63,0)),"")) | G16: =IF(OR($A16="",E16="",F16=""),"",E16*F16) | H16: =IF($A16="","",IFERROR(INDEX('INVENTORY MASTER'!$O$4:$O$63,MATCH($A16,'INVENTORY MASTER'!$A$4:$A$63,0)),"")) | I16: =IF($A16="","",IFERROR(INDEX('INVENTORY MASTER'!$P$4:$P$63,MATCH($A16,'INVENTORY MASTER'!$A$4:$A$63,0)),"")) | L16: =IF(OR(G16="",K16=""),"",(G16+N(J16))*(1+K16)) | N16: =IF(OR(G16="",M16=""),"",(G16+N(J16))*(1+M16)) | O16: =IF($A16="","",IFERROR(INDEX('INVENTORY MASTER'!$Q$4:$Q$63,MATCH($A16,'INVENTORY MASTER'!$A$4:$A$63,0)),"")) | P16: =IF($A16="","",IFERROR(INDEX('INVENTORY MASTER'!$R$4:$R$63,MATCH($A16,'INVENTORY MASTER'!$A$4:$A$63,0)),"")) | T16: =IF($A16="","",IFERROR(INDEX('INVENTORY MASTER'!$S$4:$S$63,MATCH($A16,'INVENTORY MASTER'!$A$4:$A$63,0)),"")) | U16: =IF($A16="","",IFERROR(INDEX('INVENTORY MASTER'!$AI$4:$AI$63,MATCH($A16,'INVENTORY MASTER'!$A$4:$A$63,0)),"")) | V16: =IF(OR($A16="",E16="",E16=0),"",U16/E16) | W16: =IF($A16="","",IFERROR(INDEX('INVENTORY MASTER'!$AM$4:$AM$63,MATCH($A16,'INVENTORY MASTER'!$A$4:$A$63,0)),"")) | X16: =IF($A16="","",IFERROR(INDEX('INVENTORY MASTER'!$AO$4:$AO$63,MATCH($A16,'INVENTORY MASTER'!$A$4:$A$63,0)),"")) | Y16: =IF($A16="","",IFERROR(INDEX('INVENTORY MASTER'!$AS$4:$AS$63,MATCH($A16,'INVENTORY MASTER'!$A$4:$A$63,0)),"")) | Z16: =IF($A16="","",IFERROR(INDEX('INVENTORY MASTER'!$AR$4:$AR$63,MATCH($A16,'INVENTORY MASTER'!$A$4:$A$63,0)),""))
B17: =IF($A17="","",IFERROR(INDEX('INVENTORY MASTER'!$F$4:$F$63,MATCH($A17,'INVENTORY MASTER'!$A$4:$A$63,0)),"")) | C17: =IF($A17="","",IFERROR(INDEX('INVENTORY MASTER'!$L$4:$L$63,MATCH($A17,'INVENTORY MASTER'!$A$4:$A$63,0)),"")) | D17: =IF($A17="","",IFERROR(INDEX('INVENTORY MASTER'!$M$4:$M$63,MATCH($A17,'INVENTORY MASTER'!$A$4:$A$63,0)),"")) | E17: =IF($A17="","",IFERROR(INDEX('INVENTORY MASTER'!$N$4:$N$63,MATCH($A17,'INVENTORY MASTER'!$A$4:$A$63,0)),"")) | G17: =IF(OR($A17="",E17="",F17=""),"",E17*F17) | H17: =IF($A17="","",IFERROR(INDEX('INVENTORY MASTER'!$O$4:$O$63,MATCH($A17,'INVENTORY MASTER'!$A$4:$A$63,0)),"")) | I17: =IF($A17="","",IFERROR(INDEX('INVENTORY MASTER'!$P$4:$P$63,MATCH($A17,'INVENTORY MASTER'!$A$4:$A$63,0)),"")) | L17: =IF(OR(G17="",K17=""),"",(G17+N(J17))*(1+K17)) | N17: =IF(OR(G17="",M17=""),"",(G17+N(J17))*(1+M17)) | O17: =IF($A17="","",IFERROR(INDEX('INVENTORY MASTER'!$Q$4:$Q$63,MATCH($A17,'INVENTORY MASTER'!$A$4:$A$63,0)),"")) | P17: =IF($A17="","",IFERROR(INDEX('INVENTORY MASTER'!$R$4:$R$63,MATCH($A17,'INVENTORY MASTER'!$A$4:$A$63,0)),"")) | T17: =IF($A17="","",IFERROR(INDEX('INVENTORY MASTER'!$S$4:$S$63,MATCH($A17,'INVENTORY MASTER'!$A$4:$A$63,0)),"")) | U17: =IF($A17="","",IFERROR(INDEX('INVENTORY MASTER'!$AI$4:$AI$63,MATCH($A17,'INVENTORY MASTER'!$A$4:$A$63,0)),"")) | V17: =IF(OR($A17="",E17="",E17=0),"",U17/E17) | W17: =IF($A17="","",IFERROR(INDEX('INVENTORY MASTER'!$AM$4:$AM$63,MATCH($A17,'INVENTORY MASTER'!$A$4:$A$63,0)),"")) | X17: =IF($A17="","",IFERROR(INDEX('INVENTORY MASTER'!$AO$4:$AO$63,MATCH($A17,'INVENTORY MASTER'!$A$4:$A$63,0)),"")) | Y17: =IF($A17="","",IFERROR(INDEX('INVENTORY MASTER'!$AS$4:$AS$63,MATCH($A17,'INVENTORY MASTER'!$A$4:$A$63,0)),"")) | Z17: =IF($A17="","",IFERROR(INDEX('INVENTORY MASTER'!$AR$4:$AR$63,MATCH($A17,'INVENTORY MASTER'!$A$4:$A$63,0)),""))
B18: =IF($A18="","",IFERROR(INDEX('INVENTORY MASTER'!$F$4:$F$63,MATCH($A18,'INVENTORY MASTER'!$A$4:$A$63,0)),"")) | C18: =IF($A18="","",IFERROR(INDEX('INVENTORY MASTER'!$L$4:$L$63,MATCH($A18,'INVENTORY MASTER'!$A$4:$A$63,0)),"")) | D18: =IF($A18="","",IFERROR(INDEX('INVENTORY MASTER'!$M$4:$M$63,MATCH($A18,'INVENTORY MASTER'!$A$4:$A$63,0)),"")) | E18: =IF($A18="","",IFERROR(INDEX('INVENTORY MASTER'!$N$4:$N$63,MATCH($A18,'INVENTORY MASTER'!$A$4:$A$63,0)),"")) | G18: =IF(OR($A18="",E18="",F18=""),"",E18*F18) | H18: =IF($A18="","",IFERROR(INDEX('INVENTORY MASTER'!$O$4:$O$63,MATCH($A18,'INVENTORY MASTER'!$A$4:$A$63,0)),"")) | I18: =IF($A18="","",IFERROR(INDEX('INVENTORY MASTER'!$P$4:$P$63,MATCH($A18,'INVENTORY MASTER'!$A$4:$A$63,0)),"")) | L18: =IF(OR(G18="",K18=""),"",(G18+N(J18))*(1+K18)) | N18: =IF(OR(G18="",M18=""),"",(G18+N(J18))*(1+M18)) | O18: =IF($A18="","",IFERROR(INDEX('INVENTORY MASTER'!$Q$4:$Q$63,MATCH($A18,'INVENTORY MASTER'!$A$4:$A$63,0)),"")) | P18: =IF($A18="","",IFERROR(INDEX('INVENTORY MASTER'!$R$4:$R$63,MATCH($A18,'INVENTORY MASTER'!$A$4:$A$63,0)),"")) | T18: =IF($A18="","",IFERROR(INDEX('INVENTORY MASTER'!$S$4:$S$63,MATCH($A18,'INVENTORY MASTER'!$A$4:$A$63,0)),"")) | U18: =IF($A18="","",IFERROR(INDEX('INVENTORY MASTER'!$AI$4:$AI$63,MATCH($A18,'INVENTORY MASTER'!$A$4:$A$63,0)),"")) | V18: =IF(OR($A18="",E18="",E18=0),"",U18/E18) | W18: =IF($A18="","",IFERROR(INDEX('INVENTORY MASTER'!$AM$4:$AM$63,MATCH($A18,'INVENTORY MASTER'!$A$4:$A$63,0)),"")) | X18: =IF($A18="","",IFERROR(INDEX('INVENTORY MASTER'!$AO$4:$AO$63,MATCH($A18,'INVENTORY MASTER'!$A$4:$A$63,0)),"")) | Y18: =IF($A18="","",IFERROR(INDEX('INVENTORY MASTER'!$AS$4:$AS$63,MATCH($A18,'INVENTORY MASTER'!$A$4:$A$63,0)),"")) | Z18: =IF($A18="","",IFERROR(INDEX('INVENTORY MASTER'!$AR$4:$AR$63,MATCH($A18,'INVENTORY MASTER'!$A$4:$A$63,0)),""))
... B43: =IF($A43="","",IFERROR(INDEX('INVENTORY MASTER'!$F$4:$F$63,MATCH($A43,'INVENTORY MASTER'!$A$4:$A$63,0)),"")) | C43: =IF($A43="","",IFERROR(INDEX('INVENTORY MASTER'!$L$4:$L$63,MATCH($A43,'INVENTORY MASTER'!$A$4:$A$63,0)),"")) | D43: =IF($A43="","",IFERROR(INDEX('INVENTORY MASTER'!$M$4:$M$63,MATCH($A43,'INVENTORY MASTER'!$A$4:$A$63,0)),"")) | E43: =IF($A43="","",IFERROR(INDEX('INVENTORY MASTER'!$N$4:$N$63,MATCH($A43,'INVENTORY MASTER'!$A$4:$A$63,0)),"")) | G43: =IF(OR($A43="",E43="",F43=""),"",E43*F43) | H43: =IF($A43="","",IFERROR(INDEX('INVENTORY MASTER'!$O$4:$O$63,MATCH($A43,'INVENTORY MASTER'!$A$4:$A$63,0)),"")) | I43: =IF($A43="","",IFERROR(INDEX('INVENTORY MASTER'!$P$4:$P$63,MATCH($A43,'INVENTORY MASTER'!$A$4:$A$63,0)),"")) | L43: =IF(OR(G43="",K43=""),"",(G43+N(J43))*(1+K43)) | N43: =IF(OR(G43="",M43=""),"",(G43+N(J43))*(1+M43)) | O43: =IF($A43="","",IFERROR(INDEX('INVENTORY MASTER'!$Q$4:$Q$63,MATCH($A43,'INVENTORY MASTER'!$A$4:$A$63,0)),"")) | P43: =IF($A43="","",IFERROR(INDEX('INVENTORY MASTER'!$R$4:$R$63,MATCH($A43,'INVENTORY MASTER'!$A$4:$A$63,0)),"")) | T43: =IF($A43="","",IFERROR(INDEX('INVENTORY MASTER'!$S$4:$S$63,MATCH($A43,'INVENTORY MASTER'!$A$4:$A$63,0)),"")) | U43: =IF($A43="","",IFERROR(INDEX('INVENTORY MASTER'!$AI$4:$AI$63,MATCH($A43,'INVENTORY MASTER'!$A$4:$A$63,0)),"")) | V43: =IF(OR($A43="",E43="",E43=0),"",U43/E43) | W43: =IF($A43="","",IFERROR(INDEX('INVENTORY MASTER'!$AM$4:$AM$63,MATCH($A43,'INVENTORY MASTER'!$A$4:$A$63,0)),"")) | X43: =IF($A43="","",IFERROR(INDEX('INVENTORY MASTER'!$AO$4:$AO$63,MATCH($A43,'INVENTORY MASTER'!$A$4:$A$63,0)),"")) | Y43: =IF($A43="","",IFERROR(INDEX('INVENTORY MASTER'!$AS$4:$AS$63,MATCH($A43,'INVENTORY MASTER'!$A$4:$A$63,0)),"")) | Z43: =IF($A43="","",IFERROR(INDEX('INVENTORY MASTER'!$AR$4:$AR$63,MATCH($A43,'INVENTORY MASTER'!$A$4:$A$63,0)),""))

Sheet SALES
A1: SALES
A2: Sales transactions. Enter Sale ID, Date, Stock ID (dropdown), Salesperson & Selling Price — cost/description/profit calculate automatically. Rows below the minimum price are highlighted red.
A3: Sale ID | B3: Sale Date | C3: Stock ID | D3: Item Description | E3: Category | F3: Salesperson | G3: Customer Name/Ref | H3: Invoice Number | I3: Cost Price | J3: Advertised Price | K3: Selling Price | L3: Discount Amount | M3: Discount % | N3: Gross Profit | O3: Gross Margin % | P3: VAT Treatment | Q3: Payment Method | R3: Deposit Received | S3: Balance Received | T3: Amount Outstanding | U3: Payment Status | V3: Trade-In | W3: Trade-In Value | X3: Refund/Return | Y3: Notes
A4: SALE-0001 | B4: 46063 | C4: WAT-0001 | D4: =IF($C4="","",IFERROR(INDEX('INVENTORY MASTER'!$K$4:$K$63,MATCH($C4,'INVENTORY MASTER'!$A$4:$A$63,0)),"")) -> Rolex Submariner Date 41mm, black dial | E4: =IF($C4="","",IFERROR(INDEX('INVENTORY MASTER'!$E$4:$E$63,MATCH($C4,'INVENTORY MASTER'!$A$4:$A$63,0)),"")) -> Watch | F4: Sarah Hughes | G4: C-001 (J. Smith) | H4: INV-1001 | I4: =IF($C4="","",IFERROR(INDEX('INVENTORY MASTER'!$AI$4:$AI$63,MATCH($C4,'INVENTORY MASTER'!$A$4:$A$63,0)),"")) -> 8100 | J4: =IF($C4="","",IFERROR(INDEX('INVENTORY MASTER'!$AO$4:$AO$63,MATCH($C4,'INVENTORY MASTER'!$A$4:$A$63,0)),"")) -> 10500 | K4: 10200 | L4: =IF(OR($J4="",$K4=""),"",$J4-$K4) -> 300 | M4: =IF(OR($J4="",$L4="",$J4=0),"",$L4/$J4) -> 0.028571429 | N4: =IF(OR($K4="",$I4=""),"",$K4-$I4) -> 2100 | O4: =IF(OR($K4="",$K4=0,$N4=""),"",$N4/$K4) -> 0.20588235 | P4: Margin Scheme | Q4: Bank Transfer | R4: 2000 | S4: 8200 | T4: =IF($K4="","",$K4-N($R4)-N($S4)) -> 0 | U4: Paid | V4: No | X4: No | Y4: EXAMPLE completed sale – safe to delete
D5: =IF($C5="","",IFERROR(INDEX('INVENTORY MASTER'!$K$4:$K$63,MATCH($C5,'INVENTORY MASTER'!$A$4:$A$63,0)),"")) | E5: =IF($C5="","",IFERROR(INDEX('INVENTORY MASTER'!$E$4:$E$63,MATCH($C5,'INVENTORY MASTER'!$A$4:$A$63,0)),"")) | I5: =IF($C5="","",IFERROR(INDEX('INVENTORY MASTER'!$AI$4:$AI$63,MATCH($C5,'INVENTORY MASTER'!$A$4:$A$63,0)),"")) | J5: =IF($C5="","",IFERROR(INDEX('INVENTORY MASTER'!$AO$4:$AO$63,MATCH($C5,'INVENTORY MASTER'!$A$4:$A$63,0)),"")) | L5: =IF(OR($J5="",$K5=""),"",$J5-$K5) | M5: =IF(OR($J5="",$L5="",$J5=0),"",$L5/$J5) | N5: =IF(OR($K5="",$I5=""),"",$K5-$I5) | O5: =IF(OR($K5="",$K5=0,$N5=""),"",$N5/$K5) | T5: =IF($K5="","",$K5-N($R5)-N($S5))
D6: =IF($C6="","",IFERROR(INDEX('INVENTORY MASTER'!$K$4:$K$63,MATCH($C6,'INVENTORY MASTER'!$A$4:$A$63,0)),"")) | E6: =IF($C6="","",IFERROR(INDEX('INVENTORY MASTER'!$E$4:$E$63,MATCH($C6,'INVENTORY MASTER'!$A$4:$A$63,0)),"")) | I6: =IF($C6="","",IFERROR(INDEX('INVENTORY MASTER'!$AI$4:$AI$63,MATCH($C6,'INVENTORY MASTER'!$A$4:$A$63,0)),"")) | J6: =IF($C6="","",IFERROR(INDEX('INVENTORY MASTER'!$AO$4:$AO$63,MATCH($C6,'INVENTORY MASTER'!$A$4:$A$63,0)),"")) | L6: =IF(OR($J6="",$K6=""),"",$J6-$K6) | M6: =IF(OR($J6="",$L6="",$J6=0),"",$L6/$J6) | N6: =IF(OR($K6="",$I6=""),"",$K6-$I6) | O6: =IF(OR($K6="",$K6=0,$N6=""),"",$N6/$K6) | T6: =IF($K6="","",$K6-N($R6)-N($S6))
D7: =IF($C7="","",IFERROR(INDEX('INVENTORY MASTER'!$K$4:$K$63,MATCH($C7,'INVENTORY MASTER'!$A$4:$A$63,0)),"")) | E7: =IF($C7="","",IFERROR(INDEX('INVENTORY MASTER'!$E$4:$E$63,MATCH($C7,'INVENTORY MASTER'!$A$4:$A$63,0)),"")) | I7: =IF($C7="","",IFERROR(INDEX('INVENTORY MASTER'!$AI$4:$AI$63,MATCH($C7,'INVENTORY MASTER'!$A$4:$A$63,0)),"")) | J7: =IF($C7="","",IFERROR(INDEX('INVENTORY MASTER'!$AO$4:$AO$63,MATCH($C7,'INVENTORY MASTER'!$A$4:$A$63,0)),"")) | L7: =IF(OR($J7="",$K7=""),"",$J7-$K7) | M7: =IF(OR($J7="",$L7="",$J7=0),"",$L7/$J7) | N7: =IF(OR($K7="",$I7=""),"",$K7-$I7) | O7: =IF(OR($K7="",$K7=0,$N7=""),"",$N7/$K7) | T7: =IF($K7="","",$K7-N($R7)-N($S7))
D8: =IF($C8="","",IFERROR(INDEX('INVENTORY MASTER'!$K$4:$K$63,MATCH($C8,'INVENTORY MASTER'!$A$4:$A$63,0)),"")) | E8: =IF($C8="","",IFERROR(INDEX('INVENTORY MASTER'!$E$4:$E$63,MATCH($C8,'INVENTORY MASTER'!$A$4:$A$63,0)),"")) | I8: =IF($C8="","",IFERROR(INDEX('INVENTORY MASTER'!$AI$4:$AI$63,MATCH($C8,'INVENTORY MASTER'!$A$4:$A$63,0)),"")) | J8: =IF($C8="","",IFERROR(INDEX('INVENTORY MASTER'!$AO$4:$AO$63,MATCH($C8,'INVENTORY MASTER'!$A$4:$A$63,0)),"")) | L8: =IF(OR($J8="",$K8=""),"",$J8-$K8) | M8: =IF(OR($J8="",$L8="",$J8=0),"",$L8/$J8) | N8: =IF(OR($K8="",$I8=""),"",$K8-$I8) | O8: =IF(OR($K8="",$K8=0,$N8=""),"",$N8/$K8) | T8: =IF($K8="","",$K8-N($R8)-N($S8))
D9: =IF($C9="","",IFERROR(INDEX('INVENTORY MASTER'!$K$4:$K$63,MATCH($C9,'INVENTORY MASTER'!$A$4:$A$63,0)),"")) | E9: =IF($C9="","",IFERROR(INDEX('INVENTORY MASTER'!$E$4:$E$63,MATCH($C9,'INVENTORY MASTER'!$A$4:$A$63,0)),"")) | I9: =IF($C9="","",IFERROR(INDEX('INVENTORY MASTER'!$AI$4:$AI$63,MATCH($C9,'INVENTORY MASTER'!$A$4:$A$63,0)),"")) | J9: =IF($C9="","",IFERROR(INDEX('INVENTORY MASTER'!$AO$4:$AO$63,MATCH($C9,'INVENTORY MASTER'!$A$4:$A$63,0)),"")) | L9: =IF(OR($J9="",$K9=""),"",$J9-$K9) | M9: =IF(OR($J9="",$L9="",$J9=0),"",$L9/$J9) | N9: =IF(OR($K9="",$I9=""),"",$K9-$I9) | O9: =IF(OR($K9="",$K9=0,$N9=""),"",$N9/$K9) | T9: =IF($K9="","",$K9-N($R9)-N($S9))
D10: =IF($C10="","",IFERROR(INDEX('INVENTORY MASTER'!$K$4:$K$63,MATCH($C10,'INVENTORY MASTER'!$A$4:$A$63,0)),"")) | E10: =IF($C10="","",IFERROR(INDEX('INVENTORY MASTER'!$E$4:$E$63,MATCH($C10,'INVENTORY MASTER'!$A$4:$A$63,0)),"")) | I10: =IF($C10="","",IFERROR(INDEX('INVENTORY MASTER'!$AI$4:$AI$63,MATCH($C10,'INVENTORY MASTER'!$A$4:$A$63,0)),"")) | J10: =IF($C10="","",IFERROR(INDEX('INVENTORY MASTER'!$AO$4:$AO$63,MATCH($C10,'INVENTORY MASTER'!$A$4:$A$63,0)),"")) | L10: =IF(OR($J10="",$K10=""),"",$J10-$K10) | M10: =IF(OR($J10="",$L10="",$J10=0),"",$L10/$J10) | N10: =IF(OR($K10="",$I10=""),"",$K10-$I10) | O10: =IF(OR($K10="",$K10=0,$N10=""),"",$N10/$K10) | T10: =IF($K10="","",$K10-N($R10)-N($S10))
D11: =IF($C11="","",IFERROR(INDEX('INVENTORY MASTER'!$K$4:$K$63,MATCH($C11,'INVENTORY MASTER'!$A$4:$A$63,0)),"")) | E11: =IF($C11="","",IFERROR(INDEX('INVENTORY MASTER'!$E$4:$E$63,MATCH($C11,'INVENTORY MASTER'!$A$4:$A$63,0)),"")) | I11: =IF($C11="","",IFERROR(INDEX('INVENTORY MASTER'!$AI$4:$AI$63,MATCH($C11,'INVENTORY MASTER'!$A$4:$A$63,0)),"")) | J11: =IF($C11="","",IFERROR(INDEX('INVENTORY MASTER'!$AO$4:$AO$63,MATCH($C11,'INVENTORY MASTER'!$A$4:$A$63,0)),"")) | L11: =IF(OR($J11="",$K11=""),"",$J11-$K11) | M11: =IF(OR($J11="",$L11="",$J11=0),"",$L11/$J11) | N11: =IF(OR($K11="",$I11=""),"",$K11-$I11) | O11: =IF(OR($K11="",$K11=0,$N11=""),"",$N11/$K11) | T11: =IF($K11="","",$K11-N($R11)-N($S11))
D12: =IF($C12="","",IFERROR(INDEX('INVENTORY MASTER'!$K$4:$K$63,MATCH($C12,'INVENTORY MASTER'!$A$4:$A$63,0)),"")) | E12: =IF($C12="","",IFERROR(INDEX('INVENTORY MASTER'!$E$4:$E$63,MATCH($C12,'INVENTORY MASTER'!$A$4:$A$63,0)),"")) | I12: =IF($C12="","",IFERROR(INDEX('INVENTORY MASTER'!$AI$4:$AI$63,MATCH($C12,'INVENTORY MASTER'!$A$4:$A$63,0)),"")) | J12: =IF($C12="","",IFERROR(INDEX('INVENTORY MASTER'!$AO$4:$AO$63,MATCH($C12,'INVENTORY MASTER'!$A$4:$A$63,0)),"")) | L12: =IF(OR($J12="",$K12=""),"",$J12-$K12) | M12: =IF(OR($J12="",$L12="",$J12=0),"",$L12/$J12) | N12: =IF(OR($K12="",$I12=""),"",$K12-$I12) | O12: =IF(OR($K12="",$K12=0,$N12=""),"",$N12/$K12) | T12: =IF($K12="","",$K12-N($R12)-N($S12))
D13: =IF($C13="","",IFERROR(INDEX('INVENTORY MASTER'!$K$4:$K$63,MATCH($C13,'INVENTORY MASTER'!$A$4:$A$63,0)),"")) | E13: =IF($C13="","",IFERROR(INDEX('INVENTORY MASTER'!$E$4:$E$63,MATCH($C13,'INVENTORY MASTER'!$A$4:$A$63,0)),"")) | I13: =IF($C13="","",IFERROR(INDEX('INVENTORY MASTER'!$AI$4:$AI$63,MATCH($C13,'INVENTORY MASTER'!$A$4:$A$63,0)),"")) | J13: =IF($C13="","",IFERROR(INDEX('INVENTORY MASTER'!$AO$4:$AO$63,MATCH($C13,'INVENTORY MASTER'!$A$4:$A$63,0)),"")) | L13: =IF(OR($J13="",$K13=""),"",$J13-$K13) | M13: =IF(OR($J13="",$L13="",$J13=0),"",$L13/$J13) | N13: =IF(OR($K13="",$I13=""),"",$K13-$I13) | O13: =IF(OR($K13="",$K13=0,$N13=""),"",$N13/$K13) | T13: =IF($K13="","",$K13-N($R13)-N($S13))
D14: =IF($C14="","",IFERROR(INDEX('INVENTORY MASTER'!$K$4:$K$63,MATCH($C14,'INVENTORY MASTER'!$A$4:$A$63,0)),"")) | E14: =IF($C14="","",IFERROR(INDEX('INVENTORY MASTER'!$E$4:$E$63,MATCH($C14,'INVENTORY MASTER'!$A$4:$A$63,0)),"")) | I14: =IF($C14="","",IFERROR(INDEX('INVENTORY MASTER'!$AI$4:$AI$63,MATCH($C14,'INVENTORY MASTER'!$A$4:$A$63,0)),"")) | J14: =IF($C14="","",IFERROR(INDEX('INVENTORY MASTER'!$AO$4:$AO$63,MATCH($C14,'INVENTORY MASTER'!$A$4:$A$63,0)),"")) | L14: =IF(OR($J14="",$K14=""),"",$J14-$K14) | M14: =IF(OR($J14="",$L14="",$J14=0),"",$L14/$J14) | N14: =IF(OR($K14="",$I14=""),"",$K14-$I14) | O14: =IF(OR($K14="",$K14=0,$N14=""),"",$N14/$K14) | T14: =IF($K14="","",$K14-N($R14)-N($S14))
D15: =IF($C15="","",IFERROR(INDEX('INVENTORY MASTER'!$K$4:$K$63,MATCH($C15,'INVENTORY MASTER'!$A$4:$A$63,0)),"")) | E15: =IF($C15="","",IFERROR(INDEX('INVENTORY MASTER'!$E$4:$E$63,MATCH($C15,'INVENTORY MASTER'!$A$4:$A$63,0)),"")) | I15: =IF($C15="","",IFERROR(INDEX('INVENTORY MASTER'!$AI$4:$AI$63,MATCH($C15,'INVENTORY MASTER'!$A$4:$A$63,0)),"")) | J15: =IF($C15="","",IFERROR(INDEX('INVENTORY MASTER'!$AO$4:$AO$63,MATCH($C15,'INVENTORY MASTER'!$A$4:$A$63,0)),"")) | L15: =IF(OR($J15="",$K15=""),"",$J15-$K15) | M15: =IF(OR($J15="",$L15="",$J15=0),"",$L15/$J15) | N15: =IF(OR($K15="",$I15=""),"",$K15-$I15) | O15: =IF(OR($K15="",$K15=0,$N15=""),"",$N15/$K15) | T15: =IF($K15="","",$K15-N($R15)-N($S15))
D16: =IF($C16="","",IFERROR(INDEX('INVENTORY MASTER'!$K$4:$K$63,MATCH($C16,'INVENTORY MASTER'!$A$4:$A$63,0)),"")) | E16: =IF($C16="","",IFERROR(INDEX('INVENTORY MASTER'!$E$4:$E$63,MATCH($C16,'INVENTORY MASTER'!$A$4:$A$63,0)),"")) | I16: =IF($C16="","",IFERROR(INDEX('INVENTORY MASTER'!$AI$4:$AI$63,MATCH($C16,'INVENTORY MASTER'!$A$4:$A$63,0)),"")) | J16: =IF($C16="","",IFERROR(INDEX('INVENTORY MASTER'!$AO$4:$AO$63,MATCH($C16,'INVENTORY MASTER'!$A$4:$A$63,0)),"")) | L16: =IF(OR($J16="",$K16=""),"",$J16-$K16) | M16: =IF(OR($J16="",$L16="",$J16=0),"",$L16/$J16) | N16: =IF(OR($K16="",$I16=""),"",$K16-$I16) | O16: =IF(OR($K16="",$K16=0,$N16=""),"",$N16/$K16) | T16: =IF($K16="","",$K16-N($R16)-N($S16))
... D63: =IF($C63="","",IFERROR(INDEX('INVENTORY MASTER'!$K$4:$K$63,MATCH($C63,'INVENTORY MASTER'!$A$4:$A$63,0)),"")) | E63: =IF($C63="","",IFERROR(INDEX('INVENTORY MASTER'!$E$4:$E$63,MATCH($C63,'INVENTORY MASTER'!$A$4:$A$63,0)),"")) | I63: =IF($C63="","",IFERROR(INDEX('INVENTORY MASTER'!$AI$4:$AI$63,MATCH($C63,'INVENTORY MASTER'!$A$4:$A$63,0)),"")) | J63: =IF($C63="","",IFERROR(INDEX('INVENTORY MASTER'!$AO$4:$AO$63,MATCH($C63,'INVENTORY MASTER'!$A$4:$A$63,0)),"")) | L63: =IF(OR($J63="",$K63=""),"",$J63-$K63) | M63: =IF(OR($J63="",$L63="",$J63=0),"",$L63/$J63) | N63: =IF(OR($K63="",$I63=""),"",$K63-$I63) | O63: =IF(OR($K63="",$K63=0,$N63=""),"",$N63/$K63) | T63: =IF($K63="","",$K63-N($R63)-N($S63))

Sheet PARTNER CONTRIBUTIONS
A1: PARTNER CONTRIBUTIONS
A2: Every pound a partner introduces (stock, rent, refurbishment, capital, loans). Outstanding = Amount − Reimbursed. This ledger is the source of truth for what the business owes each partner.
A3: Transaction ID | B3: Date | C3: Partner | D3: Transaction Type | E3: Description | F3: Related Stock ID | G3: Related Expense ID | H3: Amount | I3: Payment Method | J3: Business Purpose | K3: Reimbursed Amount | L3: Reimbursement Date | M3: Amount Outstanding | N3: Notes
A4: PC-0001 | B4: 46037 | C4: Partner 1 | D4: Stock Purchase | E4: Rolex Submariner purchase | F4: WAT-0001 | H4: 8100 | I4: Bank Transfer | J4: Stock funded personally by Partner 1 | K4: 0 | M4: =IF($H4="","",N($H4)-N($K4)) -> 8100 | N4: EXAMPLE – safe to delete
A5: PC-0002 | B5: 46042 | C5: Partner 2 | D5: Stock Purchase | E5: Platinum diamond ring purchase | F5: JWL-0001 | H5: 3550 | I5: Debit Card | J5: Stock funded personally by Partner 2 | K5: 0 | M5: =IF($H5="","",N($H5)-N($K5)) -> 3550 | N5: EXAMPLE – safe to delete
A6: PC-0003 | B6: 46030 | C6: Partner 3 | D6: Building Works | E6: Shop refurbishment – shopfitting | G6: EXP-0002 | H6: 5000 | I6: Bank Transfer | J6: Refurbishment funded personally by Partner 3 | K6: 2000 | L6: 46081 | M6: =IF($H6="","",N($H6)-N($K6)) -> 3000 | N6: EXAMPLE – partly reimbursed
A7: PC-0004 | B7: 46027 | C7: Partner 1 | D7: Capital Contribution | E7: Opening capital introduced | H7: 10000 | I7: Bank Transfer | J7: Working capital | K7: 0 | M7: =IF($H7="","",N($H7)-N($K7)) -> 10000 | N7: EXAMPLE – safe to delete
A8: PC-0005 | B8: 46027 | C8: Partner 3 | D8: Stock Purchase | E8: Cartier Santos purchase (paid in AED) | F8: WAT-0003 | H8: 4790 | I8: Bank Transfer | J8: Stock funded personally by Partner 3 | K8: 0 | M8: =IF($H8="","",N($H8)-N($K8)) -> 4790 | N8: EXAMPLE – safe to delete
M9: =IF($H9="","",N($H9)-N($K9))
M10: =IF($H10="","",N($H10)-N($K10))
M11: =IF($H11="","",N($H11)-N($K11))
M12: =IF($H12="","",N($H12)-N($K12))
M13: =IF($H13="","",N($H13)-N($K13))
M14: =IF($H14="","",N($H14)-N($K14))
M15: =IF($H15="","",N($H15)-N($K15))
M16: =IF($H16="","",N($H16)-N($K16))
M17: =IF($H17="","",N($H17)-N($K17))
M18: =IF($H18="","",N($H18)-N($K18))
M19: =IF($H19="","",N($H19)-N($K19))
M20: =IF($H20="","",N($H20)-N($K20))
... M63: =IF($H63="","",N($H63)-N($K63))

Sheet PARTNER SUMMARY
A1: PARTNER SUMMARY
A2: Financial position of each partner. All figures pull from the Partner Contributions ledger. Ownership % is informational only and is NOT used to split profit automatically.
A4: Ownership % (from Settings — informational): | B4: =SETTINGS!$W$15 -> 0.4 | C4: =SETTINGS!$W$16 -> 0.35 | D4: =SETTINGS!$W$17 -> 0.25
A6: Metric | B6: Partner 1 | C6: Partner 2 | D6: Partner 3 | E6: Combined Total
A7: Stock purchases personally funded | B7: =SUMIFS('PARTNER CONTRIBUTIONS'!$H$4:$H$63,'PARTNER CONTRIBUTIONS'!$C$4:$C$63,"Partner 1",'PARTNER CONTRIBUTIONS'!$D$4:$D$63,"Stock Purchase") -> 8100 | C7: =SUMIFS('PARTNER CONTRIBUTIONS'!$H$4:$H$63,'PARTNER CONTRIBUTIONS'!$C$4:$C$63,"Partner 2",'PARTNER CONTRIBUTIONS'!$D$4:$D$63,"Stock Purchase") -> 3550 | D7: =SUMIFS('PARTNER CONTRIBUTIONS'!$H$4:$H$63,'PARTNER CONTRIBUTIONS'!$C$4:$C$63,"Partner 3",'PARTNER CONTRIBUTIONS'!$D$4:$D$63,"Stock Purchase") -> 4790 | E7: =SUM(B7:D7) -> 16440
A8: Rent personally funded | B8: =SUMIFS('PARTNER CONTRIBUTIONS'!$H$4:$H$63,'PARTNER CONTRIBUTIONS'!$C$4:$C$63,"Partner 1",'PARTNER CONTRIBUTIONS'!$D$4:$D$63,"Rent") -> 0 | C8: =SUMIFS('PARTNER CONTRIBUTIONS'!$H$4:$H$63,'PARTNER CONTRIBUTIONS'!$C$4:$C$63,"Partner 2",'PARTNER CONTRIBUTIONS'!$D$4:$D$63,"Rent") -> 0 | D8: =SUMIFS('PARTNER CONTRIBUTIONS'!$H$4:$H$63,'PARTNER CONTRIBUTIONS'!$C$4:$C$63,"Partner 3",'PARTNER CONTRIBUTIONS'!$D$4:$D$63,"Rent") -> 0 | E8: =SUM(B8:D8) -> 0
A9: Building / refurbishment funded | B9: =SUMIFS('PARTNER CONTRIBUTIONS'!$H$4:$H$63,'PARTNER CONTRIBUTIONS'!$C$4:$C$63,"Partner 1",'PARTNER CONTRIBUTIONS'!$D$4:$D$63,"Building Works")+SUMIFS('PARTNER CONTRIBUTIONS'!$H$4:$H$63,'PARTNER CONTRIBUTIONS'!$C$4:$C$63,"Partner 1",'PARTNER CONTRIBUTIONS'!$D$4:$D$63,"Shop Fittings") -> 0 | C9: =SUMIFS('PARTNER CONTRIBUTIONS'!$H$4:$H$63,'PARTNER CONTRIBUTIONS'!$C$4:$C$63,"Partner 2",'PARTNER CONTRIBUTIONS'!$D$4:$D$63,"Building Works")+SUMIFS('PARTNER CONTRIBUTIONS'!$H$4:$H$63,'PARTNER CONTRIBUTIONS'!$C$4:$C$63,"Partner 2",'PARTNER CONTRIBUTIONS'!$D$4:$D$63,"Shop Fittings") -> 0 | D9: =SUMIFS('PARTNER CONTRIBUTIONS'!$H$4:$H$63,'PARTNER CONTRIBUTIONS'!$C$4:$C$63,"Partner 3",'PARTNER CONTRIBUTIONS'!$D$4:$D$63,"Building Works")+SUMIFS('PARTNER CONTRIBUTIONS'!$H$4:$H$63,'PARTNER CONTRIBUTIONS'!$C$4:$C$63,"Partner 3",'PARTNER CONTRIBUTIONS'!$D$4:$D$63,"Shop Fittings") -> 5000 | E9: =SUM(B9:D9) -> 5000
A10: Other business expenses funded | B10: =SUMIFS('PARTNER CONTRIBUTIONS'!$H$4:$H$63,'PARTNER CONTRIBUTIONS'!$C$4:$C$63,"Partner 1")-SUMIFS('PARTNER CONTRIBUTIONS'!$H$4:$H$63,'PARTNER CONTRIBUTIONS'!$C$4:$C$63,"Partner 1",'PARTNER CONTRIBUTIONS'!$D$4:$D$63,"Stock Purchase")-SUMIFS('PARTNER CONTRIBUTIONS'!$H$4:$H$63,'PARTNER CONTRIBUTIONS'!$C$4:$C$63,"Partner 1",'PARTNER CONTRIBUTIONS'!$D$4:$D$63,"Rent")-SUMIFS('PARTNER CONTRIBUTIONS'!$H$4:$H$63,'PARTNER CONTRIBUTIONS'!$C$4:$C$63,"Partner 1",'PARTNER CONTRIBUTIONS'!$D$4:$D$63,"Building Works")-SUMIFS('PARTNER CONTRIBUTIONS'!$H$4:$H$63,'PARTNER CONTRIBUTIONS'!$C$4:$C$63,"Partner 1",'PARTNER CONTRIBUTIONS'!$D$4:$D$63,"Shop Fittings")-SUMIFS('PARTNER CONTRIBUTIONS'!$H$4:$H$63,'PARTNER CONTRIBUTIONS'!$C$4:$C$63,"Partner 1",'PARTNER CONTRIBUTIONS'!$D$4:$D$63,"Capital Contribution")-SUMIFS('PARTNER CONTRIBUTIONS'!$H$4:$H$63,'PARTNER CONTRIBUTIONS'!$C$4:$C$63,"Partner 1",'PARTNER CONTRIBUTIONS'!$D$4:$D$63,"Partner Loan")-SUMIFS('PARTNER CONTRIBUTIONS'!$H$4:$H$63,'PARTNER CONTRIBUTIONS'!$C$4:$C$63,"Partner 1",'PARTNER CONTRIBUTIONS'!$D$4:$D$63,"Withdrawal") -> 0 | C10: =SUMIFS('PARTNER CONTRIBUTIONS'!$H$4:$H$63,'PARTNER CONTRIBUTIONS'!$C$4:$C$63,"Partner 2")-SUMIFS('PARTNER CONTRIBUTIONS'!$H$4:$H$63,'PARTNER CONTRIBUTIONS'!$C$4:$C$63,"Partner 2",'PARTNER CONTRIBUTIONS'!$D$4:$D$63,"Stock Purchase")-SUMIFS('PARTNER CONTRIBUTIONS'!$H$4:$H$63,'PARTNER CONTRIBUTIONS'!$C$4:$C$63,"Partner 2",'PARTNER CONTRIBUTIONS'!$D$4:$D$63,"Rent")-SUMIFS('PARTNER CONTRIBUTIONS'!$H$4:$H$63,'PARTNER CONTRIBUTIONS'!$C$4:$C$63,"Partner 2",'PARTNER CONTRIBUTIONS'!$D$4:$D$63,"Building Works")-SUMIFS('PARTNER CONTRIBUTIONS'!$H$4:$H$63,'PARTNER CONTRIBUTIONS'!$C$4:$C$63,"Partner 2",'PARTNER CONTRIBUTIONS'!$D$4:$D$63,"Shop Fittings")-SUMIFS('PARTNER CONTRIBUTIONS'!$H$4:$H$63,'PARTNER CONTRIBUTIONS'!$C$4:$C$63,"Partner 2",'PARTNER CONTRIBUTIONS'!$D$4:$D$63,"Capital Contribution")-SUMIFS('PARTNER CONTRIBUTIONS'!$H$4:$H$63,'PARTNER CONTRIBUTIONS'!$C$4:$C$63,"Partner 2",'PARTNER CONTRIBUTIONS'!$D$4:$D$63,"Partner Loan")-SUMIFS('PARTNER CONTRIBUTIONS'!$H$4:$H$63,'PARTNER CONTRIBUTIONS'!$C$4:$C$63,"Partner 2",'PARTNER CONTRIBUTIONS'!$D$4:$D$63,"Withdrawal") -> 0 | D10: =SUMIFS('PARTNER CONTRIBUTIONS'!$H$4:$H$63,'PARTNER CONTRIBUTIONS'!$C$4:$C$63,"Partner 3")-SUMIFS('PARTNER CONTRIBUTIONS'!$H$4:$H$63,'PARTNER CONTRIBUTIONS'!$C$4:$C$63,"Partner 3",'PARTNER CONTRIBUTIONS'!$D$4:$D$63,"Stock Purchase")-SUMIFS('PARTNER CONTRIBUTIONS'!$H$4:$H$63,'PARTNER CONTRIBUTIONS'!$C$4:$C$63,"Partner 3",'PARTNER CONTRIBUTIONS'!$D$4:$D$63,"Rent")-SUMIFS('PARTNER CONTRIBUTIONS'!$H$4:$H$63,'PARTNER CONTRIBUTIONS'!$C$4:$C$63,"Partner 3",'PARTNER CONTRIBUTIONS'!$D$4:$D$63,"Building Works")-SUMIFS('PARTNER CONTRIBUTIONS'!$H$4:$H$63,'PARTNER CONTRIBUTIONS'!$C$4:$C$63,"Partner 3",'PARTNER CONTRIBUTIONS'!$D$4:$D$63,"Shop Fittings")-SUMIFS('PARTNER CONTRIBUTIONS'!$H$4:$H$63,'PARTNER CONTRIBUTIONS'!$C$4:$C$63,"Partner 3",'PARTNER CONTRIBUTIONS'!$D$4:$D$63,"Capital Contribution")-SUMIFS('PARTNER CONTRIBUTIONS'!$H$4:$H$63,'PARTNER CONTRIBUTIONS'!$C$4:$C$63,"Partner 3",'PARTNER CONTRIBUTIONS'!$D$4:$D$63,"Partner Loan")-SUMIFS('PARTNER CONTRIBUTIONS'!$H$4:$H$63,'PARTNER CONTRIBUTIONS'!$C$4:$C$63,"Partner 3",'PARTNER CONTRIBUTIONS'!$D$4:$D$63,"Withdrawal") -> 0 | E10: =SUM(B10:D10) -> 0
A11: Capital contributions | B11: =SUMIFS('PARTNER CONTRIBUTIONS'!$H$4:$H$63,'PARTNER CONTRIBUTIONS'!$C$4:$C$63,"Partner 1",'PARTNER CONTRIBUTIONS'!$D$4:$D$63,"Capital Contribution") -> 10000 | C11: =SUMIFS('PARTNER CONTRIBUTIONS'!$H$4:$H$63,'PARTNER CONTRIBUTIONS'!$C$4:$C$63,"Partner 2",'PARTNER CONTRIBUTIONS'!$D$4:$D$63,"Capital Contribution") -> 0 | D11: =SUMIFS('PARTNER CONTRIBUTIONS'!$H$4:$H$63,'PARTNER CONTRIBUTIONS'!$C$4:$C$63,"Partner 3",'PARTNER CONTRIBUTIONS'!$D$4:$D$63,"Capital Contribution") -> 0 | E11: =SUM(B11:D11) -> 10000
A12: Partner loans | B12: =SUMIFS('PARTNER CONTRIBUTIONS'!$H$4:$H$63,'PARTNER CONTRIBUTIONS'!$C$4:$C$63,"Partner 1",'PARTNER CONTRIBUTIONS'!$D$4:$D$63,"Partner Loan") -> 0 | C12: =SUMIFS('PARTNER CONTRIBUTIONS'!$H$4:$H$63,'PARTNER CONTRIBUTIONS'!$C$4:$C$63,"Partner 2",'PARTNER CONTRIBUTIONS'!$D$4:$D$63,"Partner Loan") -> 0 | D12: =SUMIFS('PARTNER CONTRIBUTIONS'!$H$4:$H$63,'PARTNER CONTRIBUTIONS'!$C$4:$C$63,"Partner 3",'PARTNER CONTRIBUTIONS'!$D$4:$D$63,"Partner Loan") -> 0 | E12: =SUM(B12:D12) -> 0
A13: TOTAL FUNDS INTRODUCED | B13: =SUMIFS('PARTNER CONTRIBUTIONS'!$H$4:$H$63,'PARTNER CONTRIBUTIONS'!$C$4:$C$63,"Partner 1")-SUMIFS('PARTNER CONTRIBUTIONS'!$H$4:$H$63,'PARTNER CONTRIBUTIONS'!$C$4:$C$63,"Partner 1",'PARTNER CONTRIBUTIONS'!$D$4:$D$63,"Withdrawal") -> 18100 | C13: =SUMIFS('PARTNER CONTRIBUTIONS'!$H$4:$H$63,'PARTNER CONTRIBUTIONS'!$C$4:$C$63,"Partner 2")-SUMIFS('PARTNER CONTRIBUTIONS'!$H$4:$H$63,'PARTNER CONTRIBUTIONS'!$C$4:$C$63,"Partner 2",'PARTNER CONTRIBUTIONS'!$D$4:$D$63,"Withdrawal") -> 3550 | D13: =SUMIFS('PARTNER CONTRIBUTIONS'!$H$4:$H$63,'PARTNER CONTRIBUTIONS'!$C$4:$C$63,"Partner 3")-SUMIFS('PARTNER CONTRIBUTIONS'!$H$4:$H$63,'PARTNER CONTRIBUTIONS'!$C$4:$C$63,"Partner 3",'PARTNER CONTRIBUTIONS'!$D$4:$D$63,"Withdrawal") -> 9790 | E13: =SUM(B13:D13) -> 31440
A14: Amount reimbursed | B14: =SUMIFS('PARTNER CONTRIBUTIONS'!$K$4:$K$63,'PARTNER CONTRIBUTIONS'!$C$4:$C$63,"Partner 1") -> 0 | C14: =SUMIFS('PARTNER CONTRIBUTIONS'!$K$4:$K$63,'PARTNER CONTRIBUTIONS'!$C$4:$C$63,"Partner 2") -> 0 | D14: =SUMIFS('PARTNER CONTRIBUTIONS'!$K$4:$K$63,'PARTNER CONTRIBUTIONS'!$C$4:$C$63,"Partner 3") -> 2000 | E14: =SUM(B14:D14) -> 2000
A15: Withdrawals / distributions | B15: =SUMIFS('PARTNER CONTRIBUTIONS'!$H$4:$H$63,'PARTNER CONTRIBUTIONS'!$C$4:$C$63,"Partner 1",'PARTNER CONTRIBUTIONS'!$D$4:$D$63,"Withdrawal") -> 0 | C15: =SUMIFS('PARTNER CONTRIBUTIONS'!$H$4:$H$63,'PARTNER CONTRIBUTIONS'!$C$4:$C$63,"Partner 2",'PARTNER CONTRIBUTIONS'!$D$4:$D$63,"Withdrawal") -> 0 | D15: =SUMIFS('PARTNER CONTRIBUTIONS'!$H$4:$H$63,'PARTNER CONTRIBUTIONS'!$C$4:$C$63,"Partner 3",'PARTNER CONTRIBUTIONS'!$D$4:$D$63,"Withdrawal") -> 0 | E15: =SUM(B15:D15) -> 0
A16: CURRENT AMOUNT OWED TO PARTNER | B16: =B13-B14 -> 18100 | C16: =C13-C14 -> 3550 | D16: =D13-D14 -> 7790 | E16: =SUM(B16:D16) -> 29440
A17: NET PARTNER POSITION | B17: =B16-B15 -> 18100 | C17: =C16-C15 -> 3550 | D17: =D16-D15 -> 7790 | E17: =SUM(B17:D17) -> 29440
A19: Note: 'Paid By' ≠ ownership. This summary tracks funding & reimbursement only. Profit is NOT auto-split — ownership % above is informational unless you choose to apply it.

Sheet EXPENSES
A1: EXPENSES
A2: Complete operating-expense ledger. Gross = Net + VAT (auto). Analyse monthly/annually via the Dashboard. Where 'Paid By' is a partner, also record it in Partner Contributions.
A3: Expense ID | B3: Date | C3: Supplier | D3: Expense Category | E3: Description | F3: Invoice/Receipt No | G3: Net Amount | H3: VAT | I3: Gross Amount | J3: Paid By | K3: Payment Method | L3: Recurring? | M3: Related Partner Contribution? | N3: Partner | O3: Reimbursed? | P3: Reimbursement Date | Q3: Notes | R3: Receipt Link
A4: EXP-0001 | B4: 46054 | C4: City Lettings | D4: Rent | E4: Monthly shop rent February | F4: RENT-0202 | G4: 3000 | H4: 0 | I4: =IF(N($G4)+N($H4)=0,"",N($G4)+N($H4)) -> 3000 | J4: Business Bank Account | K4: Bank Transfer | L4: Yes | M4: No | O4: No | Q4: EXAMPLE – safe to delete
A5: EXP-0002 | B5: 46030 | C5: Prestige Shopfitters | D5: Refurbishment | E5: Shop refurbishment & shopfitting | F5: PSF-1188 | G5: 5000 | H5: 0 | I5: =IF(N($G5)+N($H5)=0,"",N($G5)+N($H5)) -> 5000 | J5: Partner 3 | K5: Bank Transfer | L5: No | M5: Yes | N5: Partner 3 | O5: No | Q5: EXAMPLE refurbishment paid by Partner 3 – mirrored in PC-0003
A6: EXP-0003 | B6: 46068 | C6: SecureCover Insurance | D6: Stock Insurance | E6: Stock & premises insurance | F6: SC-7742 | G6: 600 | H6: 120 | I6: =IF(N($G6)+N($H6)=0,"",N($G6)+N($H6)) -> 720 | J6: Business Bank Account | K6: Bank Transfer | L6: Yes | M6: No | O6: No | Q6: EXAMPLE – safe to delete
I7: =IF(N($G7)+N($H7)=0,"",N($G7)+N($H7))
I8: =IF(N($G8)+N($H8)=0,"",N($G8)+N($H8))
I9: =IF(N($G9)+N($H9)=0,"",N($G9)+N($H9))
I10: =IF(N($G10)+N($H10)=0,"",N($G10)+N($H10))
I11: =IF(N($G11)+N($H11)=0,"",N($G11)+N($H11))
I12: =IF(N($G12)+N($H12)=0,"",N($G12)+N($H12))
I13: =IF(N($G13)+N($H13)=0,"",N($G13)+N($H13))
I14: =IF(N($G14)+N($H14)=0,"",N($G14)+N($H14))
I15: =IF(N($G15)+N($H15)=0,"",N($G15)+N($H15))
I16: =IF(N($G16)+N($H16)=0,"",N($G16)+N($H16))
I17: =IF(N($G17)+N($H17)=0,"",N($G17)+N($H17))
I18: =IF(N($G18)+N($H18)=0,"",N($G18)+N($H18))
... I83: =IF(N($G83)+N($H83)=0,"",N($G83)+N($H83))

Sheet BUILDING & SETUP
A1: BUILDING & SETUP COSTS
A2: Initial shop set-up project costs. Variance = Budget − Actual. Outstanding = Actual − Reimbursed. Summary totals shown to the right.
A3: Project Cost ID | B3: Date | C3: Category | D3: Contractor/Supplier | E3: Description | F3: Original Budget | G3: Actual Cost | H3: Variance | I3: VAT | J3: Paid By | K3: Amount Reimbursed | L3: Amount Outstanding | M3: Invoice Number | N3: Completion Status | O3: Notes | Q3: SET-UP COST SUMMARY
A4: PROJ-0001 | B4: 46024 | C4: Construction | D4: Prestige Shopfitters | E4: Full shop refurbishment & fit-out | F4: 5500 | G4: 5000 | H4: =IF(OR($F4="",$G4=""),"",$F4-$G4) -> 500 | I4: 0 | J4: Partner 3 | K4: 2000 | L4: =IF($G4="","",N($G4)-N($K4)) -> 3000 | M4: PSF-1188 | N4: Completed | O4: EXAMPLE – funded by Partner 3 (see PC-0003) | Q4: Total Budget | R4: =SUM('BUILDING & SETUP'!$F$4:$F$63) -> 12500
A5: PROJ-0002 | B5: 46025 | C5: Display Cabinets | D5: LuxDisplay Ltd | E5: Lockable glass display cabinets x4 | F5: 3000 | G5: 3200 | H5: =IF(OR($F5="",$G5=""),"",$F5-$G5) -> -200 | I5: 640 | J5: Business Bank Account | K5: 0 | L5: =IF($G5="","",N($G5)-N($K5)) -> 3200 | M5: LUX-4410 | N5: Completed | O5: EXAMPLE – safe to delete | Q5: Total Actual Spend | R5: =SUM('BUILDING & SETUP'!$G$4:$G$63) -> 12100
A6: PROJ-0003 | B6: 46026 | C6: Safe | D6: FortKnox Safes | E6: Grade 5 retail safe | F6: 4000 | G6: 3900 | H6: =IF(OR($F6="",$G6=""),"",$F6-$G6) -> 100 | I6: 780 | J6: Business Bank Account | K6: 0 | L6: =IF($G6="","",N($G6)-N($K6)) -> 3900 | M6: FK-2290 | N6: Completed | O6: EXAMPLE – safe to delete | Q6: Budget Variance | R6: =$R$4-$R$5 -> 400
H7: =IF(OR($F7="",$G7=""),"",$F7-$G7) | L7: =IF($G7="","",N($G7)-N($K7)) | Q7: Funded by Partner 1 | R7: =SUMIFS('BUILDING & SETUP'!$G$4:$G$63,'BUILDING & SETUP'!$J$4:$J$63,"Partner 1") -> 0
H8: =IF(OR($F8="",$G8=""),"",$F8-$G8) | L8: =IF($G8="","",N($G8)-N($K8)) | Q8: Funded by Partner 2 | R8: =SUMIFS('BUILDING & SETUP'!$G$4:$G$63,'BUILDING & SETUP'!$J$4:$J$63,"Partner 2") -> 0
H9: =IF(OR($F9="",$G9=""),"",$F9-$G9) | L9: =IF($G9="","",N($G9)-N($K9)) | Q9: Funded by Partner 3 | R9: =SUMIFS('BUILDING & SETUP'!$G$4:$G$63,'BUILDING & SETUP'!$J$4:$J$63,"Partner 3") -> 5000
H10: =IF(OR($F10="",$G10=""),"",$F10-$G10) | L10: =IF($G10="","",N($G10)-N($K10)) | Q10: Funded by Business | R10: =SUMIFS('BUILDING & SETUP'!$G$4:$G$63,'BUILDING & SETUP'!$J$4:$J$63,"Business Bank Account")+SUMIFS('BUILDING & SETUP'!$G$4:$G$63,'BUILDING & SETUP'!$J$4:$J$63,"Business Cash") -> 7100
H11: =IF(OR($F11="",$G11=""),"",$F11-$G11) | L11: =IF($G11="","",N($G11)-N($K11)) | Q11: Outstanding Reimbursements | R11: =SUM('BUILDING & SETUP'!$L$4:$L$63) -> 10100
H12: =IF(OR($F12="",$G12=""),"",$F12-$G12) | L12: =IF($G12="","",N($G12)-N($K12))
H13: =IF(OR($F13="",$G13=""),"",$F13-$G13) | L13: =IF($G13="","",N($G13)-N($K13))
H14: =IF(OR($F14="",$G14=""),"",$F14-$G14) | L14: =IF($G14="","",N($G14)-N($K14))
H15: =IF(OR($F15="",$G15=""),"",$F15-$G15) | L15: =IF($G15="","",N($G15)-N($K15))
H16: =IF(OR($F16="",$G16=""),"",$F16-$G16) | L16: =IF($G16="","",N($G16)-N($K16))
H17: =IF(OR($F17="",$G17=""),"",$F17-$G17) | L17: =IF($G17="","",N($G17)-N($K17))
H18: =IF(OR($F18="",$G18=""),"",$F18-$G18) | L18: =IF($G18="","",N($G18)-N($K18))
H19: =IF(OR($F19="",$G19=""),"",$F19-$G19) | L19: =IF($G19="","",N($G19)-N($K19))
H20: =IF(OR($F20="",$G20=""),"",$F20-$G20) | L20: =IF($G20="","",N($G20)-N($K20))
H21: =IF(OR($F21="",$G21=""),"",$F21-$G21) | L21: =IF($G21="","",N($G21)-N($K21))
H22: =IF(OR($F22="",$G22=""),"",$F22-$G22) | L22: =IF($G22="","",N($G22)-N($K22))
H23: =IF(OR($F23="",$G23=""),"",$F23-$G23) | L23: =IF($G23="","",N($G23)-N($K23))
... H63: =IF(OR($F63="",$G63=""),"",$F63-$G63) | L63: =IF($G63="","",N($G63)-N($K63))

Sheet STOCK MOVEMENT
A1: STOCK MOVEMENT LOG
A2: High-value control: log every time an item leaves its location. Overdue items (past Expected Return Date and not returned) are highlighted red.
A3: Movement ID | B3: Date | C3: Time | D3: Stock ID | E3: Item | F3: Previous Location | G3: New Location | H3: Person Taking Item | I3: Staff Authorising | J3: Reason | K3: Expected Return Date | L3: Actual Return Date | M3: Returned? | N3: Notes
A4: MOV-0001 | B4: 46058 | C4: 0.60416667 | D4: WAT-0003 | E4: =IF($D4="","",IFERROR(INDEX('INVENTORY MASTER'!$K$4:$K$63,MATCH($D4,'INVENTORY MASTER'!$A$4:$A$63,0)),"")) -> Cartier Santos Medium steel | F4: Shop Safe | G4: Partner 3 | H4: Partner 3 | I4: Sarah Hughes | J4: Partner Viewing | K4: 46065 | M4: No | N4: EXAMPLE – overdue if past expected return date
A5: MOV-0002 | B5: 46063 | C5: 0.45833333 | D5: WAT-0001 | E5: =IF($D5="","",IFERROR(INDEX('INVENTORY MASTER'!$K$4:$K$63,MATCH($D5,'INVENTORY MASTER'!$A$4:$A$63,0)),"")) -> Rolex Submariner Date 41mm, black dial | F5: Shop Safe | G5: Customer | H5: J. Smith | I5: Sarah Hughes | J5: Sale | L5: 46063 | M5: N/A | N5: EXAMPLE – sold, no return expected
E6: =IF($D6="","",IFERROR(INDEX('INVENTORY MASTER'!$K$4:$K$63,MATCH($D6,'INVENTORY MASTER'!$A$4:$A$63,0)),""))
E7: =IF($D7="","",IFERROR(INDEX('INVENTORY MASTER'!$K$4:$K$63,MATCH($D7,'INVENTORY MASTER'!$A$4:$A$63,0)),""))
E8: =IF($D8="","",IFERROR(INDEX('INVENTORY MASTER'!$K$4:$K$63,MATCH($D8,'INVENTORY MASTER'!$A$4:$A$63,0)),""))
E9: =IF($D9="","",IFERROR(INDEX('INVENTORY MASTER'!$K$4:$K$63,MATCH($D9,'INVENTORY MASTER'!$A$4:$A$63,0)),""))
E10: =IF($D10="","",IFERROR(INDEX('INVENTORY MASTER'!$K$4:$K$63,MATCH($D10,'INVENTORY MASTER'!$A$4:$A$63,0)),""))
E11: =IF($D11="","",IFERROR(INDEX('INVENTORY MASTER'!$K$4:$K$63,MATCH($D11,'INVENTORY MASTER'!$A$4:$A$63,0)),""))
E12: =IF($D12="","",IFERROR(INDEX('INVENTORY MASTER'!$K$4:$K$63,MATCH($D12,'INVENTORY MASTER'!$A$4:$A$63,0)),""))
E13: =IF($D13="","",IFERROR(INDEX('INVENTORY MASTER'!$K$4:$K$63,MATCH($D13,'INVENTORY MASTER'!$A$4:$A$63,0)),""))
E14: =IF($D14="","",IFERROR(INDEX('INVENTORY MASTER'!$K$4:$K$63,MATCH($D14,'INVENTORY MASTER'!$A$4:$A$63,0)),""))
E15: =IF($D15="","",IFERROR(INDEX('INVENTORY MASTER'!$K$4:$K$63,MATCH($D15,'INVENTORY MASTER'!$A$4:$A$63,0)),""))
E16: =IF($D16="","",IFERROR(INDEX('INVENTORY MASTER'!$K$4:$K$63,MATCH($D16,'INVENTORY MASTER'!$A$4:$A$63,0)),""))
E17: =IF($D17="","",IFERROR(INDEX('INVENTORY MASTER'!$K$4:$K$63,MATCH($D17,'INVENTORY MASTER'!$A$4:$A$63,0)),""))
... E63: =IF($D63="","",IFERROR(INDEX('INVENTORY MASTER'!$K$4:$K$63,MATCH($D63,'INVENTORY MASTER'!$A$4:$A$63,0)),""))

Sheet STAFF
A1: STAFF
A2: Staff database. Sales This Month, Gross Profit, Transactions & Average Sale are calculated automatically from the SALES sheet. 'This Month' uses the reporting date on the Settings sheet.
A3: Staff ID | B3: Staff Name | C3: Position | D3: Start Date | E3: Active? | F3: Sales Target | G3: Sales This Month | H3: Gross Profit Generated | I3: Number of Transactions | J3: Average Sale | K3: Notes
A4: EMP-001 | B4: Sarah Hughes | C4: Sales Manager | D4: 46024 | E4: Yes | F4: 20000 | G4: =IF($B4="","",SUMIFS(SALES!$K$4:$K$63,SALES!$F$4:$F$63,$B4,SALES!$B$4:$B$63,">="&SETTINGS!$W$7,SALES!$B$4:$B$63,"<="&SETTINGS!$W$8)) -> 0 | H4: =IF($B4="","",SUMIFS(SALES!$N$4:$N$63,SALES!$F$4:$F$63,$B4)) -> 2100 | I4: =IF($B4="","",COUNTIFS(SALES!$F$4:$F$63,$B4)) -> 1 | J4: =IF(OR($B4="",$I4=0),"",SUMIFS(SALES!$K$4:$K$63,SALES!$F$4:$F$63,$B4)/$I4) -> 10200 | K4: EXAMPLE
A5: EMP-002 | B5: James Patel | C5: Sales Associate | D5: 46024 | E5: Yes | F5: 15000 | G5: =IF($B5="","",SUMIFS(SALES!$K$4:$K$63,SALES!$F$4:$F$63,$B5,SALES!$B$4:$B$63,">="&SETTINGS!$W$7,SALES!$B$4:$B$63,"<="&SETTINGS!$W$8)) -> 0 | H5: =IF($B5="","",SUMIFS(SALES!$N$4:$N$63,SALES!$F$4:$F$63,$B5)) -> 0 | I5: =IF($B5="","",COUNTIFS(SALES!$F$4:$F$63,$B5)) -> 0 | J5: =IF(OR($B5="",$I5=0),"",SUMIFS(SALES!$K$4:$K$63,SALES!$F$4:$F$63,$B5)/$I5) | K5: EXAMPLE
A6: EMP-003 | B6: Olivia Brown | C6: Sales Associate | D6: 46037 | E6: Yes | F6: 15000 | G6: =IF($B6="","",SUMIFS(SALES!$K$4:$K$63,SALES!$F$4:$F$63,$B6,SALES!$B$4:$B$63,">="&SETTINGS!$W$7,SALES!$B$4:$B$63,"<="&SETTINGS!$W$8)) -> 0 | H6: =IF($B6="","",SUMIFS(SALES!$N$4:$N$63,SALES!$F$4:$F$63,$B6)) -> 0 | I6: =IF($B6="","",COUNTIFS(SALES!$F$4:$F$63,$B6)) -> 0 | J6: =IF(OR($B6="",$I6=0),"",SUMIFS(SALES!$K$4:$K$63,SALES!$F$4:$F$63,$B6)/$I6) | K6: EXAMPLE
A7: EMP-004 | B7: David Khan | C7: Workshop / Repairs | D7: 46024 | E7: Yes | F7: 0 | G7: =IF($B7="","",SUMIFS(SALES!$K$4:$K$63,SALES!$F$4:$F$63,$B7,SALES!$B$4:$B$63,">="&SETTINGS!$W$7,SALES!$B$4:$B$63,"<="&SETTINGS!$W$8)) -> 0 | H7: =IF($B7="","",SUMIFS(SALES!$N$4:$N$63,SALES!$F$4:$F$63,$B7)) -> 0 | I7: =IF($B7="","",COUNTIFS(SALES!$F$4:$F$63,$B7)) -> 0 | J7: =IF(OR($B7="",$I7=0),"",SUMIFS(SALES!$K$4:$K$63,SALES!$F$4:$F$63,$B7)/$I7) | K7: EXAMPLE
G8: =IF($B8="","",SUMIFS(SALES!$K$4:$K$63,SALES!$F$4:$F$63,$B8,SALES!$B$4:$B$63,">="&SETTINGS!$W$7,SALES!$B$4:$B$63,"<="&SETTINGS!$W$8)) | H8: =IF($B8="","",SUMIFS(SALES!$N$4:$N$63,SALES!$F$4:$F$63,$B8)) | I8: =IF($B8="","",COUNTIFS(SALES!$F$4:$F$63,$B8)) | J8: =IF(OR($B8="",$I8=0),"",SUMIFS(SALES!$K$4:$K$63,SALES!$F$4:$F$63,$B8)/$I8)
G9: =IF($B9="","",SUMIFS(SALES!$K$4:$K$63,SALES!$F$4:$F$63,$B9,SALES!$B$4:$B$63,">="&SETTINGS!$W$7,SALES!$B$4:$B$63,"<="&SETTINGS!$W$8)) | H9: =IF($B9="","",SUMIFS(SALES!$N$4:$N$63,SALES!$F$4:$F$63,$B9)) | I9: =IF($B9="","",COUNTIFS(SALES!$F$4:$F$63,$B9)) | J9: =IF(OR($B9="",$I9=0),"",SUMIFS(SALES!$K$4:$K$63,SALES!$F$4:$F$63,$B9)/$I9)
G10: =IF($B10="","",SUMIFS(SALES!$K$4:$K$63,SALES!$F$4:$F$63,$B10,SALES!$B$4:$B$63,">="&SETTINGS!$W$7,SALES!$B$4:$B$63,"<="&SETTINGS!$W$8)) | H10: =IF($B10="","",SUMIFS(SALES!$N$4:$N$63,SALES!$F$4:$F$63,$B10)) | I10: =IF($B10="","",COUNTIFS(SALES!$F$4:$F$63,$B10)) | J10: =IF(OR($B10="",$I10=0),"",SUMIFS(SALES!$K$4:$K$63,SALES!$F$4:$F$63,$B10)/$I10)
G11: =IF($B11="","",SUMIFS(SALES!$K$4:$K$63,SALES!$F$4:$F$63,$B11,SALES!$B$4:$B$63,">="&SETTINGS!$W$7,SALES!$B$4:$B$63,"<="&SETTINGS!$W$8)) | H11: =IF($B11="","",SUMIFS(SALES!$N$4:$N$63,SALES!$F$4:$F$63,$B11)) | I11: =IF($B11="","",COUNTIFS(SALES!$F$4:$F$63,$B11)) | J11: =IF(OR($B11="",$I11=0),"",SUMIFS(SALES!$K$4:$K$63,SALES!$F$4:$F$63,$B11)/$I11)
G12: =IF($B12="","",SUMIFS(SALES!$K$4:$K$63,SALES!$F$4:$F$63,$B12,SALES!$B$4:$B$63,">="&SETTINGS!$W$7,SALES!$B$4:$B$63,"<="&SETTINGS!$W$8)) | H12: =IF($B12="","",SUMIFS(SALES!$N$4:$N$63,SALES!$F$4:$F$63,$B12)) | I12: =IF($B12="","",COUNTIFS(SALES!$F$4:$F$63,$B12)) | J12: =IF(OR($B12="",$I12=0),"",SUMIFS(SALES!$K$4:$K$63,SALES!$F$4:$F$63,$B12)/$I12)
G13: =IF($B13="","",SUMIFS(SALES!$K$4:$K$63,SALES!$F$4:$F$63,$B13,SALES!$B$4:$B$63,">="&SETTINGS!$W$7,SALES!$B$4:$B$63,"<="&SETTINGS!$W$8)) | H13: =IF($B13="","",SUMIFS(SALES!$N$4:$N$63,SALES!$F$4:$F$63,$B13)) | I13: =IF($B13="","",COUNTIFS(SALES!$F$4:$F$63,$B13)) | J13: =IF(OR($B13="",$I13=0),"",SUMIFS(SALES!$K$4:$K$63,SALES!$F$4:$F$63,$B13)/$I13)
G14: =IF($B14="","",SUMIFS(SALES!$K$4:$K$63,SALES!$F$4:$F$63,$B14,SALES!$B$4:$B$63,">="&SETTINGS!$W$7,SALES!$B$4:$B$63,"<="&SETTINGS!$W$8)) | H14: =IF($B14="","",SUMIFS(SALES!$N$4:$N$63,SALES!$F$4:$F$63,$B14)) | I14: =IF($B14="","",COUNTIFS(SALES!$F$4:$F$63,$B14)) | J14: =IF(OR($B14="",$I14=0),"",SUMIFS(SALES!$K$4:$K$63,SALES!$F$4:$F$63,$B14)/$I14)
G15: =IF($B15="","",SUMIFS(SALES!$K$4:$K$63,SALES!$F$4:$F$63,$B15,SALES!$B$4:$B$63,">="&SETTINGS!$W$7,SALES!$B$4:$B$63,"<="&SETTINGS!$W$8)) | H15: =IF($B15="","",SUMIFS(SALES!$N$4:$N$63,SALES!$F$4:$F$63,$B15)) | I15: =IF($B15="","",COUNTIFS(SALES!$F$4:$F$63,$B15)) | J15: =IF(OR($B15="",$I15=0),"",SUMIFS(SALES!$K$4:$K$63,SALES!$F$4:$F$63,$B15)/$I15)
G16: =IF($B16="","",SUMIFS(SALES!$K$4:$K$63,SALES!$F$4:$F$63,$B16,SALES!$B$4:$B$63,">="&SETTINGS!$W$7,SALES!$B$4:$B$63,"<="&SETTINGS!$W$8)) | H16: =IF($B16="","",SUMIFS(SALES!$N$4:$N$63,SALES!$F$4:$F$63,$B16)) | I16: =IF($B16="","",COUNTIFS(SALES!$F$4:$F$63,$B16)) | J16: =IF(OR($B16="",$I16=0),"",SUMIFS(SALES!$K$4:$K$63,SALES!$F$4:$F$63,$B16)/$I16)
G17: =IF($B17="","",SUMIFS(SALES!$K$4:$K$63,SALES!$F$4:$F$63,$B17,SALES!$B$4:$B$63,">="&SETTINGS!$W$7,SALES!$B$4:$B$63,"<="&SETTINGS!$W$8)) | H17: =IF($B17="","",SUMIFS(SALES!$N$4:$N$63,SALES!$F$4:$F$63,$B17)) | I17: =IF($B17="","",COUNTIFS(SALES!$F$4:$F$63,$B17)) | J17: =IF(OR($B17="",$I17=0),"",SUMIFS(SALES!$K$4:$K$63,SALES!$F$4:$F$63,$B17)/$I17)
G18: =IF($B18="","",SUMIFS(SALES!$K$4:$K$63,SALES!$F$4:$F$63,$B18,SALES!$B$4:$B$63,">="&SETTINGS!$W$7,SALES!$B$4:$B$63,"<="&SETTINGS!$W$8)) | H18: =IF($B18="","",SUMIFS(SALES!$N$4:$N$63,SALES!$F$4:$F$63,$B18)) | I18: =IF($B18="","",COUNTIFS(SALES!$F$4:$F$63,$B18)) | J18: =IF(OR($B18="",$I18=0),"",SUMIFS(SALES!$K$4:$K$63,SALES!$F$4:$F$63,$B18)/$I18)
G19: =IF($B19="","",SUMIFS(SALES!$K$4:$K$63,SALES!$F$4:$F$63,$B19,SALES!$B$4:$B$63,">="&SETTINGS!$W$7,SALES!$B$4:$B$63,"<="&SETTINGS!$W$8)) | H19: =IF($B19="","",SUMIFS(SALES!$N$4:$N$63,SALES!$F$4:$F$63,$B19)) | I19: =IF($B19="","",COUNTIFS(SALES!$F$4:$F$63,$B19)) | J19: =IF(OR($B19="",$I19=0),"",SUMIFS(SALES!$K$4:$K$63,SALES!$F$4:$F$63,$B19)/$I19)
... G43: =IF($B43="","",SUMIFS(SALES!$K$4:$K$63,SALES!$F$4:$F$63,$B43,SALES!$B$4:$B$63,">="&SETTINGS!$W$7,SALES!$B$4:$B$63,"<="&SETTINGS!$W$8)) | H43: =IF($B43="","",SUMIFS(SALES!$N$4:$N$63,SALES!$F$4:$F$63,$B43)) | I43: =IF($B43="","",COUNTIFS(SALES!$F$4:$F$63,$B43)) | J43: =IF(OR($B43="",$I43=0),"",SUMIFS(SALES!$K$4:$K$63,SALES!$F$4:$F$63,$B43)/$I43)

Sheet SUPPLIERS
A1: SUPPLIERS
A2: Supplier database. Total Purchases pulls automatically from Inventory Master (matched on Supplier Name). Enter Outstanding manually.
A3: Supplier ID | B3: Supplier Name | C3: Supplier Type | D3: Contact Name | E3: Telephone | F3: Email | G3: Address | H3: VAT Number | I3: Payment Terms | J3: Total Purchases | K3: Outstanding Amount | L3: Notes
A4: SUP-001 | B4: Prestige Watch Co | C4: Watch Dealer | D4: Mark Reed | E4: 020 7000 1111 | F4: sales@prestigewatch.example | I4: 30 days | J4: =IF($B4="","",SUMIFS('INVENTORY MASTER'!$AI$4:$AI$63,'INVENTORY MASTER'!$AA$4:$AA$63,$B4)) -> 8100 | K4: 0 | L4: EXAMPLE
A5: SUP-002 | B5: Hatton Diamonds | C5: Jewellery Dealer | D5: Rachel Cohen | E5: 020 7000 2222 | F5: info@hattondiamonds.example | I5: On collection | J5: =IF($B5="","",SUMIFS('INVENTORY MASTER'!$AI$4:$AI$63,'INVENTORY MASTER'!$AA$4:$AA$63,$B5)) -> 3550 | K5: 0 | L5: EXAMPLE
A6: SUP-003 | B6: Goldsmith Wholesale | C6: Wholesaler | D6: Tom Green | E6: 0161 000 3333 | F6: orders@goldsmithws.example | I6: 14 days | J6: =IF($B6="","",SUMIFS('INVENTORY MASTER'!$AI$4:$AI$63,'INVENTORY MASTER'!$AA$4:$AA$63,$B6)) -> 3150 | K6: 0 | L6: EXAMPLE
J7: =IF($B7="","",SUMIFS('INVENTORY MASTER'!$AI$4:$AI$63,'INVENTORY MASTER'!$AA$4:$AA$63,$B7))
J8: =IF($B8="","",SUMIFS('INVENTORY MASTER'!$AI$4:$AI$63,'INVENTORY MASTER'!$AA$4:$AA$63,$B8))
J9: =IF($B9="","",SUMIFS('INVENTORY MASTER'!$AI$4:$AI$63,'INVENTORY MASTER'!$AA$4:$AA$63,$B9))
J10: =IF($B10="","",SUMIFS('INVENTORY MASTER'!$AI$4:$AI$63,'INVENTORY MASTER'!$AA$4:$AA$63,$B10))
J11: =IF($B11="","",SUMIFS('INVENTORY MASTER'!$AI$4:$AI$63,'INVENTORY MASTER'!$AA$4:$AA$63,$B11))
J12: =IF($B12="","",SUMIFS('INVENTORY MASTER'!$AI$4:$AI$63,'INVENTORY MASTER'!$AA$4:$AA$63,$B12))
J13: =IF($B13="","",SUMIFS('INVENTORY MASTER'!$AI$4:$AI$63,'INVENTORY MASTER'!$AA$4:$AA$63,$B13))
J14: =IF($B14="","",SUMIFS('INVENTORY MASTER'!$AI$4:$AI$63,'INVENTORY MASTER'!$AA$4:$AA$63,$B14))
J15: =IF($B15="","",SUMIFS('INVENTORY MASTER'!$AI$4:$AI$63,'INVENTORY MASTER'!$AA$4:$AA$63,$B15))
J16: =IF($B16="","",SUMIFS('INVENTORY MASTER'!$AI$4:$AI$63,'INVENTORY MASTER'!$AA$4:$AA$63,$B16))
J17: =IF($B17="","",SUMIFS('INVENTORY MASTER'!$AI$4:$AI$63,'INVENTORY MASTER'!$AA$4:$AA$63,$B17))
J18: =IF($B18="","",SUMIFS('INVENTORY MASTER'!$AI$4:$AI$63,'INVENTORY MASTER'!$AA$4:$AA$63,$B18))
... J63: =IF($B63="","",SUMIFS('INVENTORY MASTER'!$AI$4:$AI$63,'INVENTORY MASTER'!$AA$4:$AA$63,$B63))

Sheet CUSTOMERS
A1: CUSTOMERS
A2: Minimal customer reference database (avoid storing unnecessary sensitive data). Number of Purchases & Total Spend auto-calculate from SALES, matched on Customer Name/Ref.
A3: Customer ID | B3: Name | C3: Telephone | D3: Email | E3: Date First Purchased | F3: Number of Purchases | G3: Total Spend | H3: Last Purchase | I3: Notes
A4: C-001 (J. Smith) | B4: J. Smith | C4: 07700 900123 | D4: jsmith@example.com | E4: 46063 | F4: =IF($A4="","",COUNTIFS(SALES!$G$4:$G$63,$A4)) -> 1 | G4: =IF($A4="","",SUMIFS(SALES!$K$4:$K$63,SALES!$G$4:$G$63,$A4)) -> 10200 | H4: 46063 | I4: EXAMPLE – Total Spend / count auto from SALES. Keep data minimal (GDPR).
F5: =IF($A5="","",COUNTIFS(SALES!$G$4:$G$63,$A5)) | G5: =IF($A5="","",SUMIFS(SALES!$K$4:$K$63,SALES!$G$4:$G$63,$A5))
F6: =IF($A6="","",COUNTIFS(SALES!$G$4:$G$63,$A6)) | G6: =IF($A6="","",SUMIFS(SALES!$K$4:$K$63,SALES!$G$4:$G$63,$A6))
F7: =IF($A7="","",COUNTIFS(SALES!$G$4:$G$63,$A7)) | G7: =IF($A7="","",SUMIFS(SALES!$K$4:$K$63,SALES!$G$4:$G$63,$A7))
F8: =IF($A8="","",COUNTIFS(SALES!$G$4:$G$63,$A8)) | G8: =IF($A8="","",SUMIFS(SALES!$K$4:$K$63,SALES!$G$4:$G$63,$A8))
F9: =IF($A9="","",COUNTIFS(SALES!$G$4:$G$63,$A9)) | G9: =IF($A9="","",SUMIFS(SALES!$K$4:$K$63,SALES!$G$4:$G$63,$A9))
F10: =IF($A10="","",COUNTIFS(SALES!$G$4:$G$63,$A10)) | G10: =IF($A10="","",SUMIFS(SALES!$K$4:$K$63,SALES!$G$4:$G$63,$A10))
F11: =IF($A11="","",COUNTIFS(SALES!$G$4:$G$63,$A11)) | G11: =IF($A11="","",SUMIFS(SALES!$K$4:$K$63,SALES!$G$4:$G$63,$A11))
F12: =IF($A12="","",COUNTIFS(SALES!$G$4:$G$63,$A12)) | G12: =IF($A12="","",SUMIFS(SALES!$K$4:$K$63,SALES!$G$4:$G$63,$A12))
F13: =IF($A13="","",COUNTIFS(SALES!$G$4:$G$63,$A13)) | G13: =IF($A13="","",SUMIFS(SALES!$K$4:$K$63,SALES!$G$4:$G$63,$A13))
F14: =IF($A14="","",COUNTIFS(SALES!$G$4:$G$63,$A14)) | G14: =IF($A14="","",SUMIFS(SALES!$K$4:$K$63,SALES!$G$4:$G$63,$A14))
F15: =IF($A15="","",COUNTIFS(SALES!$G$4:$G$63,$A15)) | G15: =IF($A15="","",SUMIFS(SALES!$K$4:$K$63,SALES!$G$4:$G$63,$A15))
F16: =IF($A16="","",COUNTIFS(SALES!$G$4:$G$63,$A16)) | G16: =IF($A16="","",SUMIFS(SALES!$K$4:$K$63,SALES!$G$4:$G$63,$A16))
... F53: =IF($A53="","",COUNTIFS(SALES!$G$4:$G$63,$A53)) | G53: =IF($A53="","",SUMIFS(SALES!$K$4:$K$63,SALES!$G$4:$G$63,$A53))

Sheet RETURNS & REFUNDS
A1: RETURNS & REFUNDS
A2: Returns & refunds. Original selling price pulls from SALES (matched on Original Sale ID). Set 'New Stock Status' to Available to return an item to stock — the original SALES row is never deleted, preserving history.
A3: Return ID | B3: Date | C3: Original Sale ID | D3: Stock ID | E3: Customer Reference | F3: Original Selling Price | G3: Refund Amount | H3: Reason | I3: Item Condition on Return | J3: Returned to Stock? | K3: New Stock Status | L3: Approved By | M3: Notes
A4: RET-0001 | B4: 46073 | F4: =IF($C4="","",IFERROR(INDEX(SALES!$K$4:$K$63,MATCH($C4,SALES!$A$4:$A$63,0)),"")) | H4: EXAMPLE row – enter a Sale ID to auto-fill price | I4: Excellent | J4: Yes | K4: Available | L4: Sarah Hughes | M4: Returned stock goes back to Available; original sale history is preserved.
F5: =IF($C5="","",IFERROR(INDEX(SALES!$K$4:$K$63,MATCH($C5,SALES!$A$4:$A$63,0)),""))
F6: =IF($C6="","",IFERROR(INDEX(SALES!$K$4:$K$63,MATCH($C6,SALES!$A$4:$A$63,0)),""))
F7: =IF($C7="","",IFERROR(INDEX(SALES!$K$4:$K$63,MATCH($C7,SALES!$A$4:$A$63,0)),""))
F8: =IF($C8="","",IFERROR(INDEX(SALES!$K$4:$K$63,MATCH($C8,SALES!$A$4:$A$63,0)),""))
F9: =IF($C9="","",IFERROR(INDEX(SALES!$K$4:$K$63,MATCH($C9,SALES!$A$4:$A$63,0)),""))
F10: =IF($C10="","",IFERROR(INDEX(SALES!$K$4:$K$63,MATCH($C10,SALES!$A$4:$A$63,0)),""))
F11: =IF($C11="","",IFERROR(INDEX(SALES!$K$4:$K$63,MATCH($C11,SALES!$A$4:$A$63,0)),""))
F12: =IF($C12="","",IFERROR(INDEX(SALES!$K$4:$K$63,MATCH($C12,SALES!$A$4:$A$63,0)),""))
F13: =IF($C13="","",IFERROR(INDEX(SALES!$K$4:$K$63,MATCH($C13,SALES!$A$4:$A$63,0)),""))
F14: =IF($C14="","",IFERROR(INDEX(SALES!$K$4:$K$63,MATCH($C14,SALES!$A$4:$A$63,0)),""))
F15: =IF($C15="","",IFERROR(INDEX(SALES!$K$4:$K$63,MATCH($C15,SALES!$A$4:$A$63,0)),""))
F16: =IF($C16="","",IFERROR(INDEX(SALES!$K$4:$K$63,MATCH($C16,SALES!$A$4:$A$63,0)),""))
... F63: =IF($C63="","",IFERROR(INDEX(SALES!$K$4:$K$63,MATCH($C63,SALES!$A$4:$A$63,0)),""))

Sheet STOCK TAKE
A1: STOCK TAKE
A2: Physical stock-count reconciliation. Expected location/status/item pull from Inventory Master. 'Difference' flags MISSING or LOCATION DIFF automatically. Missing items are highlighted red.
A3: Stock Take Date | B3: Stock ID | C3: Item | D3: Expected Location | E3: Expected Status | F3: Physically Found? | G3: Actual Location | H3: Checked By | I3: Difference | J3: Notes | L3: STOCK TAKE SUMMARY
A4: 46081 | B4: WAT-0002 | C4: =IF($B4="","",IFERROR(INDEX('INVENTORY MASTER'!$K$4:$K$63,MATCH($B4,'INVENTORY MASTER'!$A$4:$A$63,0)),"")) -> Omega Speedmaster Moonwatch 42mm | D4: =IF($B4="","",IFERROR(INDEX('INVENTORY MASTER'!$AR$4:$AR$63,MATCH($B4,'INVENTORY MASTER'!$A$4:$A$63,0)),"")) -> Shop Display | E4: =IF($B4="","",IFERROR(INDEX('INVENTORY MASTER'!$AS$4:$AS$63,MATCH($B4,'INVENTORY MASTER'!$A$4:$A$63,0)),"")) -> Available | F4: Yes | G4: Shop Display | H4: James Patel | I4: =IF($B4="","",IF($F4="No","MISSING",IF($G4="","",IF($G4=$D4,"OK","LOCATION DIFF")))) -> OK | J4: EXAMPLE | L4: Expected items (counted rows) | M4: =COUNTA('STOCK TAKE'!$B$4:$B$63) -> 3
A5: 46081 | B5: JWL-0001 | C5: =IF($B5="","",IFERROR(INDEX('INVENTORY MASTER'!$K$4:$K$63,MATCH($B5,'INVENTORY MASTER'!$A$4:$A$63,0)),"")) -> Platinum solitaire diamond ring 1.01ct | D5: =IF($B5="","",IFERROR(INDEX('INVENTORY MASTER'!$AR$4:$AR$63,MATCH($B5,'INVENTORY MASTER'!$A$4:$A$63,0)),"")) -> Shop Display | E5: =IF($B5="","",IFERROR(INDEX('INVENTORY MASTER'!$AS$4:$AS$63,MATCH($B5,'INVENTORY MASTER'!$A$4:$A$63,0)),"")) -> Available | F5: Yes | G5: Shop Display | H5: James Patel | I5: =IF($B5="","",IF($F5="No","MISSING",IF($G5="","",IF($G5=$D5,"OK","LOCATION DIFF")))) -> OK | J5: EXAMPLE | L5: Items counted (found) | M5: =COUNTIF('STOCK TAKE'!$F$4:$F$63,"Yes") -> 2
A6: 46081 | B6: WAT-0003 | C6: =IF($B6="","",IFERROR(INDEX('INVENTORY MASTER'!$K$4:$K$63,MATCH($B6,'INVENTORY MASTER'!$A$4:$A$63,0)),"")) -> Cartier Santos Medium steel | D6: =IF($B6="","",IFERROR(INDEX('INVENTORY MASTER'!$AR$4:$AR$63,MATCH($B6,'INVENTORY MASTER'!$A$4:$A$63,0)),"")) -> Partner 3 | E6: =IF($B6="","",IFERROR(INDEX('INVENTORY MASTER'!$AS$4:$AS$63,MATCH($B6,'INVENTORY MASTER'!$A$4:$A$63,0)),"")) -> With Partner | F6: No | H6: James Patel | I6: =IF($B6="","",IF($F6="No","MISSING",IF($G6="","",IF($G6=$D6,"OK","LOCATION DIFF")))) -> MISSING | J6: EXAMPLE – out with Partner 3 (see movement log) | L6: Missing items | M6: =COUNTIF('STOCK TAKE'!$F$4:$F$63,"No") -> 1
C7: =IF($B7="","",IFERROR(INDEX('INVENTORY MASTER'!$K$4:$K$63,MATCH($B7,'INVENTORY MASTER'!$A$4:$A$63,0)),"")) | D7: =IF($B7="","",IFERROR(INDEX('INVENTORY MASTER'!$AR$4:$AR$63,MATCH($B7,'INVENTORY MASTER'!$A$4:$A$63,0)),"")) | E7: =IF($B7="","",IFERROR(INDEX('INVENTORY MASTER'!$AS$4:$AS$63,MATCH($B7,'INVENTORY MASTER'!$A$4:$A$63,0)),"")) | I7: =IF($B7="","",IF($F7="No","MISSING",IF($G7="","",IF($G7=$D7,"OK","LOCATION DIFF")))) | L7: Location discrepancies | M7: =COUNTIF('STOCK TAKE'!$I$4:$I$63,"LOCATION DIFF") -> 0
C8: =IF($B8="","",IFERROR(INDEX('INVENTORY MASTER'!$K$4:$K$63,MATCH($B8,'INVENTORY MASTER'!$A$4:$A$63,0)),"")) | D8: =IF($B8="","",IFERROR(INDEX('INVENTORY MASTER'!$AR$4:$AR$63,MATCH($B8,'INVENTORY MASTER'!$A$4:$A$63,0)),"")) | E8: =IF($B8="","",IFERROR(INDEX('INVENTORY MASTER'!$AS$4:$AS$63,MATCH($B8,'INVENTORY MASTER'!$A$4:$A$63,0)),"")) | I8: =IF($B8="","",IF($F8="No","MISSING",IF($G8="","",IF($G8=$D8,"OK","LOCATION DIFF")))) | L8: Cost value of missing items | M8: =SUMPRODUCT(('STOCK TAKE'!$F$4:$F$63="No")*IFERROR(INDEX('INVENTORY MASTER'!$AI$4:$AI$63,MATCH('STOCK TAKE'!$B$4:$B$63,'INVENTORY MASTER'!$A$4:$A$63,0)),0)) -> 4790
C9: =IF($B9="","",IFERROR(INDEX('INVENTORY MASTER'!$K$4:$K$63,MATCH($B9,'INVENTORY MASTER'!$A$4:$A$63,0)),"")) | D9: =IF($B9="","",IFERROR(INDEX('INVENTORY MASTER'!$AR$4:$AR$63,MATCH($B9,'INVENTORY MASTER'!$A$4:$A$63,0)),"")) | E9: =IF($B9="","",IFERROR(INDEX('INVENTORY MASTER'!$AS$4:$AS$63,MATCH($B9,'INVENTORY MASTER'!$A$4:$A$63,0)),"")) | I9: =IF($B9="","",IF($F9="No","MISSING",IF($G9="","",IF($G9=$D9,"OK","LOCATION DIFF"))))
C10: =IF($B10="","",IFERROR(INDEX('INVENTORY MASTER'!$K$4:$K$63,MATCH($B10,'INVENTORY MASTER'!$A$4:$A$63,0)),"")) | D10: =IF($B10="","",IFERROR(INDEX('INVENTORY MASTER'!$AR$4:$AR$63,MATCH($B10,'INVENTORY MASTER'!$A$4:$A$63,0)),"")) | E10: =IF($B10="","",IFERROR(INDEX('INVENTORY MASTER'!$AS$4:$AS$63,MATCH($B10,'INVENTORY MASTER'!$A$4:$A$63,0)),"")) | I10: =IF($B10="","",IF($F10="No","MISSING",IF($G10="","",IF($G10=$D10,"OK","LOCATION DIFF"))))
C11: =IF($B11="","",IFERROR(INDEX('INVENTORY MASTER'!$K$4:$K$63,MATCH($B11,'INVENTORY MASTER'!$A$4:$A$63,0)),"")) | D11: =IF($B11="","",IFERROR(INDEX('INVENTORY MASTER'!$AR$4:$AR$63,MATCH($B11,'INVENTORY MASTER'!$A$4:$A$63,0)),"")) | E11: =IF($B11="","",IFERROR(INDEX('INVENTORY MASTER'!$AS$4:$AS$63,MATCH($B11,'INVENTORY MASTER'!$A$4:$A$63,0)),"")) | I11: =IF($B11="","",IF($F11="No","MISSING",IF($G11="","",IF($G11=$D11,"OK","LOCATION DIFF"))))
C12: =IF($B12="","",IFERROR(INDEX('INVENTORY MASTER'!$K$4:$K$63,MATCH($B12,'INVENTORY MASTER'!$A$4:$A$63,0)),"")) | D12: =IF($B12="","",IFERROR(INDEX('INVENTORY MASTER'!$AR$4:$AR$63,MATCH($B12,'INVENTORY MASTER'!$A$4:$A$63,0)),"")) | E12: =IF($B12="","",IFERROR(INDEX('INVENTORY MASTER'!$AS$4:$AS$63,MATCH($B12,'INVENTORY MASTER'!$A$4:$A$63,0)),"")) | I12: =IF($B12="","",IF($F12="No","MISSING",IF($G12="","",IF($G12=$D12,"OK","LOCATION DIFF"))))
C13: =IF($B13="","",IFERROR(INDEX('INVENTORY MASTER'!$K$4:$K$63,MATCH($B13,'INVENTORY MASTER'!$A$4:$A$63,0)),"")) | D13: =IF($B13="","",IFERROR(INDEX('INVENTORY MASTER'!$AR$4:$AR$63,MATCH($B13,'INVENTORY MASTER'!$A$4:$A$63,0)),"")) | E13: =IF($B13="","",IFERROR(INDEX('INVENTORY MASTER'!$AS$4:$AS$63,MATCH($B13,'INVENTORY MASTER'!$A$4:$A$63,0)),"")) | I13: =IF($B13="","",IF($F13="No","MISSING",IF($G13="","",IF($G13=$D13,"OK","LOCATION DIFF"))))
C14: =IF($B14="","",IFERROR(INDEX('INVENTORY MASTER'!$K$4:$K$63,MATCH($B14,'INVENTORY MASTER'!$A$4:$A$63,0)),"")) | D14: =IF($B14="","",IFERROR(INDEX('INVENTORY MASTER'!$AR$4:$AR$63,MATCH($B14,'INVENTORY MASTER'!$A$4:$A$63,0)),"")) | E14: =IF($B14="","",IFERROR(INDEX('INVENTORY MASTER'!$AS$4:$AS$63,MATCH($B14,'INVENTORY MASTER'!$A$4:$A$63,0)),"")) | I14: =IF($B14="","",IF($F14="No","MISSING",IF($G14="","",IF($G14=$D14,"OK","LOCATION DIFF"))))
C15: =IF($B15="","",IFERROR(INDEX('INVENTORY MASTER'!$K$4:$K$63,MATCH($B15,'INVENTORY MASTER'!$A$4:$A$63,0)),"")) | D15: =IF($B15="","",IFERROR(INDEX('INVENTORY MASTER'!$AR$4:$AR$63,MATCH($B15,'INVENTORY MASTER'!$A$4:$A$63,0)),"")) | E15: =IF($B15="","",IFERROR(INDEX('INVENTORY MASTER'!$AS$4:$AS$63,MATCH($B15,'INVENTORY MASTER'!$A$4:$A$63,0)),"")) | I15: =IF($B15="","",IF($F15="No","MISSING",IF($G15="","",IF($G15=$D15,"OK","LOCATION DIFF"))))
C16: =IF($B16="","",IFERROR(INDEX('INVENTORY MASTER'!$K$4:$K$63,MATCH($B16,'INVENTORY MASTER'!$A$4:$A$63,0)),"")) | D16: =IF($B16="","",IFERROR(INDEX('INVENTORY MASTER'!$AR$4:$AR$63,MATCH($B16,'INVENTORY MASTER'!$A$4:$A$63,0)),"")) | E16: =IF($B16="","",IFERROR(INDEX('INVENTORY MASTER'!$AS$4:$AS$63,MATCH($B16,'INVENTORY MASTER'!$A$4:$A$63,0)),"")) | I16: =IF($B16="","",IF($F16="No","MISSING",IF($G16="","",IF($G16=$D16,"OK","LOCATION DIFF"))))
C17: =IF($B17="","",IFERROR(INDEX('INVENTORY MASTER'!$K$4:$K$63,MATCH($B17,'INVENTORY MASTER'!$A$4:$A$63,0)),"")) | D17: =IF($B17="","",IFERROR(INDEX('INVENTORY MASTER'!$AR$4:$AR$63,MATCH($B17,'INVENTORY MASTER'!$A$4:$A$63,0)),"")) | E17: =IF($B17="","",IFERROR(INDEX('INVENTORY MASTER'!$AS$4:$AS$63,MATCH($B17,'INVENTORY MASTER'!$A$4:$A$63,0)),"")) | I17: =IF($B17="","",IF($F17="No","MISSING",IF($G17="","",IF($G17=$D17,"OK","LOCATION DIFF"))))
C18: =IF($B18="","",IFERROR(INDEX('INVENTORY MASTER'!$K$4:$K$63,MATCH($B18,'INVENTORY MASTER'!$A$4:$A$63,0)),"")) | D18: =IF($B18="","",IFERROR(INDEX('INVENTORY MASTER'!$AR$4:$AR$63,MATCH($B18,'INVENTORY MASTER'!$A$4:$A$63,0)),"")) | E18: =IF($B18="","",IFERROR(INDEX('INVENTORY MASTER'!$AS$4:$AS$63,MATCH($B18,'INVENTORY MASTER'!$A$4:$A$63,0)),"")) | I18: =IF($B18="","",IF($F18="No","MISSING",IF($G18="","",IF($G18=$D18,"OK","LOCATION DIFF"))))
C19: =IF($B19="","",IFERROR(INDEX('INVENTORY MASTER'!$K$4:$K$63,MATCH($B19,'INVENTORY MASTER'!$A$4:$A$63,0)),"")) | D19: =IF($B19="","",IFERROR(INDEX('INVENTORY MASTER'!$AR$4:$AR$63,MATCH($B19,'INVENTORY MASTER'!$A$4:$A$63,0)),"")) | E19: =IF($B19="","",IFERROR(INDEX('INVENTORY MASTER'!$AS$4:$AS$63,MATCH($B19,'INVENTORY MASTER'!$A$4:$A$63,0)),"")) | I19: =IF($B19="","",IF($F19="No","MISSING",IF($G19="","",IF($G19=$D19,"OK","LOCATION DIFF"))))
C20: =IF($B20="","",IFERROR(INDEX('INVENTORY MASTER'!$K$4:$K$63,MATCH($B20,'INVENTORY MASTER'!$A$4:$A$63,0)),"")) | D20: =IF($B20="","",IFERROR(INDEX('INVENTORY MASTER'!$AR$4:$AR$63,MATCH($B20,'INVENTORY MASTER'!$A$4:$A$63,0)),"")) | E20: =IF($B20="","",IFERROR(INDEX('INVENTORY MASTER'!$AS$4:$AS$63,MATCH($B20,'INVENTORY MASTER'!$A$4:$A$63,0)),"")) | I20: =IF($B20="","",IF($F20="No","MISSING",IF($G20="","",IF($G20=$D20,"OK","LOCATION DIFF"))))
... C63: =IF($B63="","",IFERROR(INDEX('INVENTORY MASTER'!$K$4:$K$63,MATCH($B63,'INVENTORY MASTER'!$A$4:$A$63,0)),"")) | D63: =IF($B63="","",IFERROR(INDEX('INVENTORY MASTER'!$AR$4:$AR$63,MATCH($B63,'INVENTORY MASTER'!$A$4:$A$63,0)),"")) | E63: =IF($B63="","",IFERROR(INDEX('INVENTORY MASTER'!$AS$4:$AS$63,MATCH($B63,'INVENTORY MASTER'!$A$4:$A$63,0)),"")) | I63: =IF($B63="","",IF($F63="No","MISSING",IF($G63="","",IF($G63=$D63,"OK","LOCATION DIFF"))))

Sheet MONTH-END
A1: MONTH-END SUMMARY
A2: Choose a Year and Month below — every figure recalculates for that period. Opening stock is derived: Closing − Purchases + COGS.
B4: Reporting Year | C4: 2026
B5: Reporting Month (1-12) | C5: 2
B6: Period | C6: =TEXT(DATE($C$4,$C$5,1),"MMMM YYYY") -> February 2026
B8: Figure | C8: Amount | D8: Notes
B9: Opening stock (at cost, derived) | C9: =C12-C10+C11 -> 14850 | D9: Closing − Purchases + COGS
B10: Purchases (stock bought in month) | C10: =SUMIFS('INVENTORY MASTER'!$AI$4:$AI$63,'INVENTORY MASTER'!$D$4:$D$63,">="&DATE($C$4,$C$5,1),'INVENTORY MASTER'!$D$4:$D$63,"<="&EOMONTH(DATE($C$4,$C$5,1),0)) -> 7940 | D10: Inventory: Date Purchased in period
B11: Cost of goods sold (COGS) | C11: =SUMIFS(SALES!$I$4:$I$63,SALES!$B$4:$B$63,">="&DATE($C$4,$C$5,1),SALES!$B$4:$B$63,"<="&EOMONTH(DATE($C$4,$C$5,1),0)) -> 8100 | D11: Cost price of items sold in period
B12: Closing stock (current snapshot) | C12: =SUMIF('INVENTORY MASTER'!$AS$4:$AS$63,"<>Sold",'INVENTORY MASTER'!$AI$4:$AI$63)-SUMIF('INVENTORY MASTER'!$AS$4:$AS$63,"Written Off",'INVENTORY MASTER'!$AI$4:$AI$63) -> 14690 | D12: All unsold stock at landed cost
B13: Sales revenue | C13: =SUMIFS(SALES!$K$4:$K$63,SALES!$B$4:$B$63,">="&DATE($C$4,$C$5,1),SALES!$B$4:$B$63,"<="&EOMONTH(DATE($C$4,$C$5,1),0)) -> 10200 | D13: SALES: Selling Price in period
B14: Gross profit | C14: =SUMIFS(SALES!$N$4:$N$63,SALES!$B$4:$B$63,">="&DATE($C$4,$C$5,1),SALES!$B$4:$B$63,"<="&EOMONTH(DATE($C$4,$C$5,1),0)) -> 2100 | D14: SALES: Gross Profit in period
B15: Gross margin % | C15: =IFERROR(C14/C13,0) -> 0.20588235 | D15: Gross profit / revenue
B16: Operating expenses | C16: =SUMIFS(EXPENSES!$I$4:$I$83,EXPENSES!$B$4:$B$83,">="&DATE($C$4,$C$5,1),EXPENSES!$B$4:$B$83,"<="&EOMONTH(DATE($C$4,$C$5,1),0)) -> 3720 | D16: EXPENSES: Gross Amount in period
B17: Estimated operating profit | C17: =C14-C16 -> -1620 | D17: Gross profit − expenses
B18: Partner contributions | C18: =SUMIFS('PARTNER CONTRIBUTIONS'!$H$4:$H$63,'PARTNER CONTRIBUTIONS'!$B$4:$B$63,">="&DATE($C$4,$C$5,1),'PARTNER CONTRIBUTIONS'!$B$4:$B$63,"<="&EOMONTH(DATE($C$4,$C$5,1),0)) -> 0 | D18: Funds introduced in period
B19: Partner reimbursements | C19: =SUMIFS('PARTNER CONTRIBUTIONS'!$K$4:$K$63,'PARTNER CONTRIBUTIONS'!$L$4:$L$63,">="&DATE($C$4,$C$5,1),'PARTNER CONTRIBUTIONS'!$L$4:$L$63,"<="&EOMONTH(DATE($C$4,$C$5,1),0)) -> 2000 | D19: Repaid to partners in period
B20: Cash introduced (capital+loans) | C20: =SUMIFS('PARTNER CONTRIBUTIONS'!$H$4:$H$63,'PARTNER CONTRIBUTIONS'!$B$4:$B$63,">="&DATE($C$4,$C$5,1),'PARTNER CONTRIBUTIONS'!$B$4:$B$63,"<="&EOMONTH(DATE($C$4,$C$5,1),0),'PARTNER CONTRIBUTIONS'!$D$4:$D$63,"Capital Contribution")+SUMIFS('PARTNER CONTRIBUTIONS'!$H$4:$H$63,'PARTNER CONTRIBUTIONS'!$B$4:$B$63,">="&DATE($C$4,$C$5,1),'PARTNER CONTRIBUTIONS'!$B$4:$B$63,"<="&EOMONTH(DATE($C$4,$C$5,1),0),'PARTNER CONTRIBUTIONS'!$D$4:$D$63,"Partner Loan") -> 0 | D20: Capital + partner loans introduced
B21: Cash withdrawn | C21: =SUMIFS('PARTNER CONTRIBUTIONS'!$H$4:$H$63,'PARTNER CONTRIBUTIONS'!$B$4:$B$63,">="&DATE($C$4,$C$5,1),'PARTNER CONTRIBUTIONS'!$B$4:$B$63,"<="&EOMONTH(DATE($C$4,$C$5,1),0),'PARTNER CONTRIBUTIONS'!$D$4:$D$63,"Withdrawal") -> 0 | D21: Partner withdrawals / distributions

Sheet SETTINGS
A1: SETTINGS — Configuration & Dropdown Lists
A2: Single source of truth. Edit these lists to control dropdowns across the workbook. Cells in cream are safe to edit.
A4: Partner Names | B4: Staff Names | C4: Locations | D4: Categories | E4: Subcategories | F4: Stock Status | G4: Payment Methods | H4: Expense Categories | I4: Funding Types | J4: Transaction Types | K4: Supplier Types | L4: Paid By | M4: Condition | N4: Yes / No | O4: VAT Treatment | P4: Payment Status | Q4: Movement Reasons | R4: Project Cost Categories | S4: Completion Status | T4: Metal Purity | V4: REPORTING & CONFIG
A5: Partner 1 | B5: Sarah Hughes | C5: Shop Display | D5: Watch | E5: Luxury Watch | F5: Available | G5: Cash | H5: Rent | I5: Partner Capital | J5: Stock Purchase | K5: Watch Dealer | L5: Partner 1 | M5: New | N5: Yes | O5: Standard VAT | P5: Paid | Q5: Customer Viewing | R5: Lease Deposit | S5: Not Started | T5: 9ct | V5: Business Name | W5: Your Jewellery & Watch Shop Ltd
A6: Partner 2 | B6: James Patel | C6: Shop Safe | D6: Ring | E6: Vintage Watch | F6: Reserved | G6: Debit Card | H6: Business Rates | I6: Partner Loan | J6: Capital Contribution | K6: Jewellery Dealer | L6: Partner 2 | M6: Unworn | N6: No | O6: Margin Scheme | P6: Part Paid | Q6: Partner Viewing | R6: Rent | S6: In Progress | T6: 14ct | V6: Reporting Date (today) | W6: =TODAY() -> 46264
A7: Partner 3 | B7: Olivia Brown | C7: Office | D7: Bracelet | E7: Solitaire Ring | F7: Sold | G7: Credit Card | H7: Refurbishment | I7: Business Purchase | J7: Partner Loan | K7: Private Seller | L7: Partner 3 | M7: Excellent | O7: VAT Exempt | P7: Deposit Only | Q7: Photography | R7: Construction | S7: Completed | T7: 18ct | V7: Current Month Start | W7: =DATE(YEAR($W$6),MONTH($W$6),1) -> 46235
B8: David Khan | C8: Partner 1 | D8: Necklace | E8: Eternity Ring | F8: On Approval | G8: Bank Transfer | H8: Building Works | I8: Personally Owned Stock | J8: Rent | K8: Auction | L8: Business Bank Account | M8: Very Good | O8: Zero Rated | P8: Outstanding | Q8: Repair | R8: Electrical | S8: On Hold | T8: 22ct | V8: Current Month End | W8: =EOMONTH($W$6,0) -> 46265
C9: Partner 2 | D9: Pendant | E9: Signet Ring | F9: With Partner | G9: Finance | H9: Shop Fittings | I9: Consignment | J9: Deposit | K9: Manufacturer | L9: Business Cash | M9: Good | O9: Not Registered | P9: Refunded | Q9: Valuation | R9: Plumbing | S9: Cancelled | T9: 24ct | V9: Current Year Start | W9: =DATE(YEAR($W$6),1,1) -> 46023
C10: Partner 3 | D10: Earrings | E10: Tennis Bracelet | F10: With Customer | G10: Split Payment | H10: Display Cabinets | I10: Supplier Credit | J10: Building Works | K10: Wholesaler | L10: Supplier Credit | M10: Fair | Q10: Authentication | R10: Decorating | T10: 925 Silver | V10: Current Year End | W10: =DATE(YEAR($W$6),12,31) -> 46387
C11: Customer | D11: Chain | E11: Bangle | F11: Repair | G11: Other | H11: Safe/Security | I11: Other | J11: Shop Fittings | K11: Repairer | L11: Other | M11: For Repair | Q11: Stock Transfer | R11: Flooring | T11: 950 Platinum | V11: Week Start (Mon) | W11: =$W$6-WEEKDAY($W$6,2)+1 -> 46258
C12: Repairer | D12: Gold | E12: Chain Necklace | F12: Consignment | H12: CCTV | J12: Professional Fees | K12: Other | Q12: Sale | R12: Lighting | T12: 999 Fine | V12: Base Currency | W12: GBP (£)
C13: Supplier | D13: Diamond Jewellery | E13: Pendant Necklace | F13: Returned | H13: Insurance | J13: Marketing | Q13: Return | R13: Security | T13: N/A
C14: Other | D14: Other | E14: Stud Earrings | F14: Lost/Missing | H14: Electricity | J14: Equipment | Q14: Other | R14: CCTV | V14: PARTNERSHIP OWNERSHIP % (informational)
E15: Drop Earrings | F15: Written Off | H15: Gas | J15: Reimbursement | R15: Safe | V15: Partner 1 | W15: 0.4
E16: Other | H16: Water | J16: Withdrawal | R16: Display Cabinets | V16: Partner 2 | W16: 0.35
H17: Internet | J17: Other | R17: Furniture | V17: Partner 3 | W17: 0.25
H18: Telephone | R18: Signage | V18: Total (must equal 100%) | W18: =SUM($W$15:$W$17) -> 1
H19: Staff Wages | R19: POS Equipment | V19: =IF(ROUND($W$18,4)=1,"✓ Ownership totals 100%","⚠ CHECK: ownership must total 100%") -> ✓ Ownership totals 100%
H20: Employer Costs | R20: Computers
H21: Accounting | R21: Professional Fees
H22: Legal | R22: Other | V22: STOCK ID HELPER (next suggested numbers)
H23: Marketing | V23: Next Watch ID (WAT-) | W23: ="WAT-"&TEXT(COUNTIF('INVENTORY MASTER'!$A$3:$A$203,"WAT-*")+1,"0000") -> WAT-0004
H24: Website | V24: Next Jewellery ID (JWL-) | W24: ="JWL-"&TEXT(COUNTIF('INVENTORY MASTER'!$A$3:$A$203,"JWL-*")+1,"0000") -> JWL-0004
H25: Software
H26: Card Processing Fees
H27: Bank Fees | V27: CURRENCIES & FX RATES → GBP
H28: Repairs | V28: Currency | W28: Rate to GBP (1 unit = £)
H29: Cleaning | V29: GBP | W29: 1
H30: Packaging | V30: USD | W30: 0.79
H31: Delivery | V31: EUR | W31: 0.85
H32: Travel | V32: AED | W32: 0.215
H33: Stock Insurance | V33: CHF | W33: 0.88
H34: Professional Fees | V34: HKD | W34: 0.1
H35: Miscellaneous | V35: JPY | W35: 0.0053
V36: Other | W36: 1
V37: Indicative rates — update as needed. Each stock row can override with the exact rate paid.

Sheet AUDIT LOG
A1: AUDIT LOG
A2: Manual change log for important events: price reductions, write-offs, refunds, and changes to purchase costs. Excel cannot log automatically — record material changes here for accountability.
A3: Date | B3: Time | C3: User | D3: Action | E3: Stock ID / Transaction ID | F3: Field Changed | G3: Previous Value | H3: New Value | I3: Reason | J3: Authorised By
A4: 46065 | B4: 0.67708333 | C4: Sarah Hughes | D4: Price Reduction | E4: WAT-0001 | F4: Advertised Price | G4: £10,800 | H4: £10,500 | I4: Negotiation with customer | J4: Partner 1
